Workbook

Sheet Contents
D4: Statutory homelessness: Detailed local authority-level tables
D5: April 2024 to March 2025
D6: England
D7: 45988
C9: Accredited Official Statistics
C10: Households initially assessed as threatened with homelessness (owed prevention duty) or homeless (owed relief duty)1
C11: Table No. | D11: Subject | L11: Geography
C12: A1 | D12: Initial assessment of homelessness circumstances and needs | L12: Local authority
C13: A2P | D13: Households owed a prevention duty by reason for loss, or threat of loss, of last settled home | L13: Local authority
C14: A2R | D14: Households owed a relief duty by reason for loss, or threat of loss, of last settled home | L14: Local authority
C15: A3 | D15: Support needs of household | L15: Local authority
C16: A4P | D16: Households owed a prevention duty by accommodation at time of application | L16: Local authority
C17: A4R | D17: Households owed a relief duty by accommodation at time of application | L17: Local authority
C18: A5P | D18: Household composition (threatened with homelessness) | L18: Local authority
C19: A5R | D19: Household composition (homeless) | L19: Local authority
C20: A6 | D20: Age of main applicant | L20: Local authority
C21: A7 | D21: Referrals, including under the Duty to Refer | L21: Local authority
C22: A8 | D22: Ethnicity of main applicant | L22: Local authority
... C27: A13 | D27: Gender identity of main applicant | L27: local authority
C29: Households whose prevention duty ended2
C30: P1 | D30: Reason for end of prevention duty | L30: Local authority
C31: P2 | D31: Accommodation secured at prevention duty end | L31: Local authority
C32: P3 | D32: Main prevention activity to secure accommodation | L32: Local authority
C33: P4 | D33: Location of alternative accommodation secured | L33: Local authority
C34: P5 | D34: Household composition of those secured accommodation | L34: Local authority
C36: Households whose relief duty ended2
C37: R1 | D37: Reason for end of relief duty | L37: Local authority
C38: R2 | D38: Accommodation secured at relief duty end | L38: Local authority
C39: R3 | D39: Main relief activity to secure accommodation | L39: Local authority
C40: R4 | D40: Location of accommodation secured | L40: Local authority
C41: R5 | D41: Household composition of those secured accommodation | L41: Local authority
C43: Households assessed, following relief duty end, as unintentionally homeless and priority need (owed main duty)3
C44: MD1 | D44: Decision on duty owed at end of relief duty | L44: Local authority
C45: MD3 | D45: Priority need of households owed main duty | L45: Local authority
C47: Households whose main duty ended3
C48: MD2 | D48: Reason for end of main duty | L48: Local authority
B51: 1 | C51: These tables include information on new prevention and relief duties owed. Prevention duties include any activities aimed at preventing a household threatened with homelessness within 56 days from becoming homeless. Relief duties are owed to households that are already homeless and require help to secure settled accommodation. They are not comparable with the homelessness decisions or prevention/relief activity reported prior to May 2018. This is because amendments to legislation, as introduced by the 2017 HRA, have introduced new duties that mean more people will be eligible for assistance out of homelessness from local authorities.
C55: 18 local authorities had missing data on initial assessment information. National and regional totals were weighted based on previous trends for these authorities. They are highlighted and referenced in the data tables, and are estimated to comprise of 6.9% of total assessments in England. There may be seasonal trends in this data, which is not currently adjusted.
B56: 2 | C56: 15 out of 296 local authorities had missing data on prevention and relief outcomes. Therefore the corresponding regional totals were weighted to account for these. These are estimated to comprise of 4.6% of prevention outcomes and 6.4% of relief outcomes in England.
B58: 3 | C58: Main duty describes the duty a local authority has towards an applicant who is unintentionally homeless, eligible for assistance and has priority need. This definition has not been changed by the 2017 HRA. However, these households are now only owed a main duty if they did not secure accommodation in the prevention or relief stage.
C61: 13 out of 296 local authorities had missing data on main duty decisions. Therefore the corresponding regional totals were weighted to account for these. These are estimated to comprise of 6.4% of total main duty decisions in England. 15 out of 296 local authorities had missing data on main duty outcomes. Therefore the corresponding regional totals were weighted to account for these. These are estimated to comprise of 5.8% of main duty outcomes in England.
B63: * | C63: These tables are now only published as part of the expanded annual release at end of financial year. The latest published figures can be found in the latest Annual Detailed LA-level tables.
C65: Data in each new release is provisional and subject to revision in future quarters. Local authorities may add new cases late or revise previous data submissions where mistakes have been spotted. Where revisions to earlier quarters are made, these will be incorporated into the dataset at the end of the financial year.
C66: More information on data quality and limitations can be found in the written statistical release and technical notes:
C67: https://www.gov.uk/government/collections/homelessness-statistics
C69: Forthcoming Releases: | M69: Responsible Analyst: Madeha Asim
C70: February 2026: July-September 2025 quarterly data | M70: Statistical enquiries: Homelessnessstats@communities.gov.uk
M71: Media Enquiries: 0303 444 1209

Sheet LA_dropdown_(A1-A12)
C3: Initial assessments of statutory homelessness duties owed England, April 2024 to March 2025
C5: Select local authority by clicking on the box below and using the drop-down button below:
C6: York
C8: Number and % of households | G8: Number and % of households
B9: Total number of households assessed1,2 | C9: =INDEX('A1'!$B$2:$R$331,MATCH($C$6,'A1'!$B2:$B331,0),MATCH(B9,'A1'!B$2:R$2,0)) -> 810 | F9: Total households with support need(s) owed a duty | G9: =INDEX('A3'!$B$2:$AI$323,MATCH($C$6,'A3'!$B$2:$B$323,0),MATCH(F9,'A3'!$B$2:$AI$2,0)) -> 485 | H9: =IF(OR(G9="..",G9="-",$C$10=0),"",G9/$C$10) -> 0.60099133
B10: Total households assessed as owed a duty | C10: =INDEX('A1'!$B$2:$R$331,MATCH($C$6,'A1'!$B$2:$B$331,0),MATCH(B10,'A1'!B$2:R$2,0)) -> 807 | D10: =IF(OR(C10="..",C10="-",$C$9=0),"",C10/$C$9) -> 0.9962963 | F10: Total number of support needs for those owed a duty5 | G10: =INDEX('A3'!$B$2:$AI$323,MATCH($C$6,'A3'!$B$2:$B$323,0),MATCH(F10,'A3'!$B$2:$AI$2,0)) -> 830
B12: Households assessed and duty owed: | F12: Support needs of households owed a prevention or relief duty7:
B13: Threatened with homelessness - Prevention duty owed | C13: =INDEX('A1'!$B$2:$AG$321,MATCH($C$6,'A1'!$B$2:$B$321,0),MATCH(B13,'A1'!$B$2:$AG$2,0)) -> 529 | D13: =IF(OR(C13="..",C13="-",$C$9=0),"",C13/$C$9) -> 0.65308642 | F13: History of mental health problems | G13: =INDEX('A3'!$B$2:$AK$323,MATCH($C$6,'A3'!$B$2:$B$323,0),MATCH(F13,'A3'!$B$2:$AK$2,0)) -> 130 | H13: =IF(OR(G13="..",G13="-",$C$10=0),"",G13/$C$10) -> 0.16109046
B14: Of which: due to service of valid Section 21 Notice | C14: =INDEX('A1'!$B$2:$AG$321,MATCH($C$6,'A1'!$B$2:$B$321,0),MATCH(B14,'A1'!$B$2:$AG$2,0)) -> 118 | D14: =IF(OR(C14="..",C14="-",$C$9=0),"",C14/$C$9) -> 0.14567901 | F14: Physical ill health and disability | G14: =INDEX('A3'!$B$2:$AK$323,MATCH($C$6,'A3'!$B$2:$B$323,0),MATCH(F14,'A3'!$B$2:$AK$2,0)) -> 93 | H14: =IF(OR(G14="..",G14="-",$C$10=0),"",G14/$C$10) -> 0.11524164
B15: Homeless - Relief duty owed | C15: =INDEX('A1'!$B$2:$AG$321,MATCH($C$6,'A1'!$B$2:$B$321,0),MATCH(B15,'A1'!$B$2:$AG$2,0)) -> 278 | D15: =IF(OR(C15="..",C15="-",$C$9=0),"",C15/$C$9) -> 0.34320988 | F15: At risk of / has experienced domestic abuse | G15: =INDEX('A3'!$B$2:$AK$323,MATCH($C$6,'A3'!$B$2:$B$323,0),MATCH(F15,'A3'!$B$2:$AK$2,0)) -> 75 | H15: =IF(OR(G15="..",G15="-",$C$10=0),"",G15/$C$10) -> 0.092936803
B16: Not threatened with homelessness within 56 days - no duty owed | C16: =INDEX('A1'!$B$2:$AG$321,MATCH($C$6,'A1'!$B$2:$B$321,0),MATCH(B16,'A1'!$B$2:$AG$2,0)) -> 3 | D16: =IF(OR(C16="..",C16="-",$C$9=0),"",C16/$C$9) -> 0.0037037037 | F16: Offending history | G16: =INDEX('A3'!$B$2:$AK$323,MATCH($C$6,'A3'!$B$2:$B$323,0),MATCH(F16,'A3'!$B$2:$AK$2,0)) -> 73 | H16: =IF(OR(G16="..",G16="-",$C$10=0),"",G16/$C$10) -> 0.090458488
B17: Withdrew application before assessment - no duty owed | C17: =INDEX('A1'!$B$2:$AG$321,MATCH($C$6,'A1'!$B$2:$B$321,0),MATCH(B17,'A1'!$B$2:$AG$2,0)) -> 0 | D17: =IF(OR(C17="..",C17="-",$C$9=0),"",C17/$C$9) -> 0 | F17: History of repeat homelessness | G17: =INDEX('A3'!$B$2:$AK$323,MATCH($C$6,'A3'!$B$2:$B$323,0),MATCH(F17,'A3'!$B$2:$AK$2,0)) -> 54 | H17: =IF(OR(G17="..",G17="-",$C$10=0),"",G17/$C$10) -> 0.066914498
B18: Not eligible / no longer eligible - no duty owed | C18: =INDEX('A1'!$B$2:$AG$321,MATCH($C$6,'A1'!$B$2:$B$321,0),MATCH(B18,'A1'!$B$2:$AG$2,0)) -> 0 | D18: =IF(OR(C18="..",C18="-",$C$9=0),"",C18/$C$9) -> 0 | F18: Drug dependency needs | G18: =INDEX('A3'!$B$2:$AK$323,MATCH($C$6,'A3'!$B$2:$B$323,0),MATCH(F18,'A3'!$B$2:$AK$2,0)) -> 44 | H18: =IF(OR(G18="..",G18="-",$C$10=0),"",G18/$C$10) -> 0.054522924
F19: History of rough sleeping | G19: =INDEX('A3'!$B$2:$AK$323,MATCH($C$6,'A3'!$B$2:$B$323,0),MATCH(F19,'A3'!$B$2:$AK$2,0)) -> 22 | H19: =IF(OR(G19="..",G19="-",$C$10=0),"",G19/$C$10) -> 0.027261462
B20: Reason for loss of last settled home for households owed a prevention duty: | F20: Alcohol dependency needs | G20: =INDEX('A3'!$B$2:$AK$323,MATCH($C$6,'A3'!$B$2:$B$323,0),MATCH(F20,'A3'!$B$2:$AK$2,0)) -> 35 | H20: =IF(OR(G20="..",G20="-",$C$10=0),"",G20/$C$10) -> 0.043370508
B21: Family or friends no longer willing or able to accommodate | C21: =INDEX(A2P!$B$2:$BF$318, MATCH($C$6, A2P!$B$2:$B$318,0), MATCH(B21, A2P!$B$2:$BF$2, 0)) -> 153 | D21: =IF(OR(C21="..",C21="-",$C$13=0),"",C21/$C$13) -> 0.28922495 | F21: Learning disability | G21: =INDEX('A3'!$B$2:$AK$323,MATCH($C$6,'A3'!$B$2:$B$323,0),MATCH(F21,'A3'!$B$2:$AK$2,0)) -> 16 | H21: =IF(OR(G21="..",G21="-",$C$10=0),"",G21/$C$10) -> 0.019826518
B22: End of private rented tenancy - assured shorthold | C22: =INDEX(A2P!$B$2:$BF$318, MATCH($C$6, A2P!$B$2:$B$318,0), MATCH(B22, A2P!$B$2:$BF$2, 0)) -> 190 | D22: =IF(OR(C22="..",C22="-",$C$13=0),"",C22/$C$13) -> 0.35916824 | F22: Young person aged 18-25 years requiring support to manage independently | G22: =INDEX('A3'!$B$2:$AK$323,MATCH($C$6,'A3'!$B$2:$B$323,0),MATCH(F22,'A3'!$B$2:$AK$2,0)) -> 55 | H22: =IF(OR(G22="..",G22="-",$C$10=0),"",G22/$C$10) -> 0.068153656
B23: Domestic abuse | C23: =INDEX(A2P!$B$2:$BF$318, MATCH($C$6, A2P!$B$2:$B$318,0), MATCH(B23, A2P!$B$2:$BF$2, 0)) -> 30 | D23: =IF(OR(C23="..",C23="-",$C$13=0),"",C23/$C$13) -> 0.056710775 | F23: Access to education, employment or training | G23: =INDEX('A3'!$B$2:$AK$323,MATCH($C$6,'A3'!$B$2:$B$323,0),MATCH(F23,'A3'!$B$2:$AK$2,0)) -> 4 | H23: =IF(OR(G23="..",G23="-",$C$10=0),"",G23/$C$10) -> 0.0049566295
B24: Non-violent relationship breakdown with partner | C24: =INDEX(A2P!$B$2:$BF$318, MATCH($C$6, A2P!$B$2:$B$318,0), MATCH(B24, A2P!$B$2:$BF$2, 0)) -> 58 | D24: =IF(OR(C24="..",C24="-",$C$13=0),"",C24/$C$13) -> 0.10964083 | F24: At risk of / has experienced abuse (non-domestic abuse) | G24: =INDEX('A3'!$B$2:$AK$323,MATCH($C$6,'A3'!$B$2:$B$323,0),MATCH(F24,'A3'!$B$2:$AK$2,0)) -> 12 | H24: =IF(OR(G24="..",G24="-",$C$10=0),"",G24/$C$10) -> 0.014869888
B25: End of social rented tenancy | C25: =INDEX(A2P!$B$2:$BF$318, MATCH($C$6, A2P!$B$2:$B$318,0), MATCH(B25, A2P!$B$2:$BF$2, 0)) -> 10 | D25: =IF(OR(C25="..",C25="-",$C$13=0),"",C25/$C$13) -> 0.018903592 | F25: At risk of / has experienced sexual abuse / exploitation | G25: =INDEX('A3'!$B$2:$AK$323,MATCH($C$6,'A3'!$B$2:$B$323,0),MATCH(F25,'A3'!$B$2:$AK$2,0)) -> 7 | H25: =IF(OR(G25="..",G25="-",$C$10=0),"",G25/$C$10) -> 0.0086741016
B26: Eviction from supported housing | C26: =INDEX(A2P!$B$2:$BF$318, MATCH($C$6, A2P!$B$2:$B$318,0), MATCH(B26, A2P!$B$2:$BF$2, 0)) -> 7 | D26: =IF(OR(C26="..",C26="-",$C$13=0),"",C26/$C$13) -> 0.013232514 | F26: Old age | G26: =INDEX('A3'!$B$2:$AK$323,MATCH($C$6,'A3'!$B$2:$B$323,0),MATCH(F26,'A3'!$B$2:$AK$2,0)) -> 16 | H26: =IF(OR(G26="..",G26="-",$C$10=0),"",G26/$C$10) -> 0.019826518
B27: End of private rented tenancy - not assured shorthold | C27: =INDEX(A2P!$B$2:$BF$318, MATCH($C$6, A2P!$B$2:$B$318,0), MATCH(B27, A2P!$B$2:$BF$2, 0)) -> 10 | D27: =IF(OR(C27="..",C27="-",$C$13=0),"",C27/$C$13) -> 0.018903592 | F27: Care leaver aged 18-20 years | G27: =INDEX('A3'!$B$2:$AK$323,MATCH($C$6,'A3'!$B$2:$B$323,0),MATCH(F27,'A3'!$B$2:$AK$2,0)) -> 3 | H27: =IF(OR(G27="..",G27="-",$C$10=0),"",G27/$C$10) -> 0.0037174721
B28: Other violence or harrassment | C28: =INDEX(A2P!$B$2:$BF$318, MATCH($C$6, A2P!$B$2:$B$318,0), MATCH(B28, A2P!$B$2:$BF$2, 0)) -> 4 | D28: =IF(OR(C28="..",C28="-",$C$13=0),"",C28/$C$13) -> 0.0075614367 | F28: Care leaver aged 21-24 years | G28: =INDEX('A3'!$B$2:$AK$323,MATCH($C$6,'A3'!$B$2:$B$323,0),MATCH(F28,'A3'!$B$2:$AK$2,0)) -> 2 | H28: =IF(OR(G28="..",G28="-",$C$10=0),"",G28/$C$10) -> 0.0024783147
B29: Left institution with no accommodation available | C29: =INDEX(A2P!$B$2:$BF$318, MATCH($C$6, A2P!$B$2:$B$318,0), MATCH(B29, A2P!$B$2:$BF$2, 0)) -> 18 | D29: =IF(OR(C29="..",C29="-",$C$13=0),"",C29/$C$13) -> 0.034026465 | F29: Care leaver aged 25+ years | G29: =INDEX('A3'!$B$2:$AK$323,MATCH($C$6,'A3'!$B$2:$B$323,0),MATCH(F29,'A3'!$B$2:$AK$2,0)) -> 2 | H29: =IF(OR(G29="..",G29="-",$C$10=0),"",G29/$C$10) -> 0.0024783147
B30: Required to leave accommodation provided by Home Office as asylum support | C30: =INDEX(A2P!$B$2:$BF$318, MATCH($C$6, A2P!$B$2:$B$318,0), MATCH(B30, A2P!$B$2:$BF$2, 0)) -> 17 | D30: =IF(OR(C30="..",C30="-",$C$13=0),"",C30/$C$13) -> 0.032136106 | F30: Care leaver aged 21+ years (retired option) | G30: =INDEX('A3'!$B$2:$AK$323,MATCH($C$6,'A3'!$B$2:$B$323,0),MATCH(F30,'A3'!$B$2:$AK$2,0)) -> 1 | H30: =IF(OR(G30="..",G30="-",$C$10=0),"",G30/$C$10) -> 0.0012391574
B31: Home no longer suitable - disability / ill health | C31: =INDEX(A2P!$B$2:$BF$318, MATCH($C$6, A2P!$B$2:$B$318,0), MATCH(B31, A2P!$B$2:$BF$2, 0)) -> 1 | D31: =IF(OR(C31="..",C31="-",$C$13=0),"",C31/$C$13) -> 0.0018903592 | F31: Young person aged 16-17 years | G31: =INDEX('A3'!$B$2:$AK$323,MATCH($C$6,'A3'!$B$2:$B$323,0),MATCH(F31,'A3'!$B$2:$AK$2,0)) -> 13 | H31: =IF(OR(G31="..",G31="-",$C$10=0),"",G31/$C$10) -> 0.016109046
B32: Other reasons / not known6 | C32: =INDEX(A2P!$B$2:$BF$318, MATCH($C$6, A2P!$B$2:$B$318,0), MATCH(B32, A2P!$B$2:$BF$2, 0)) -> 29 | D32: =IF(OR(C32="..",C32="-",$C$13=0),"",C32/$C$13) -> 0.054820416 | F32: Young parent requiring support to manage independently | G32: =INDEX('A3'!$B$2:$AK$323,MATCH($C$6,'A3'!$B$2:$B$323,0),MATCH(F32,'A3'!$B$2:$AK$2,0)) -> 17 | H32: =IF(OR(G32="..",G32="-",$C$10=0),"",G32/$C$10) -> 0.021065675
F33: Former asylum seeker | G33: =INDEX('A3'!$B$2:$AK$323,MATCH($C$6,'A3'!$B$2:$B$323,0),MATCH(F33,'A3'!$B$2:$AK$2,0)) -> 23 | H33: =IF(OR(G33="..",G33="-",$C$10=0),"",G33/$C$10) -> 0.02850062
B34: Reason for loss of last settled home for households owed a relief duty: | F34: Served in HM Forces | G34: =INDEX('A3'!$B$2:$AK$323,MATCH($C$6,'A3'!$B$2:$B$323,0),MATCH(F34,'A3'!$B$2:$AK$2,0)) -> 3 | H34: =IF(OR(G34="..",G34="-",$C$10=0),"",G34/$C$10) -> 0.0037174721
B35: Family or friends no longer willing or able to accommodate | C35: =INDEX(A2R!$B$2:$BF$318, MATCH($C$6, A2R!$B$2:$B$318,0), MATCH(B35, A2R!$B$2:$BF$2, 0)) -> 117 | D35: =IF(OR(C35="..",C35="-",$C$15=0),"",C35/$C$15) -> 0.42086331 | F35: Victim of modern slavery | G35: =INDEX('A3'!$B$2:$AK$323,MATCH($C$6,'A3'!$B$2:$B$323,0),MATCH(F35,'A3'!$B$2:$AK$2,0)) -> 1 | H35: =IF(OR(G35="..",G35="-",$C$10=0),"",G35/$C$10) -> 0.0012391574
B36: End of private rented tenancy - assured shorthold | C36: =INDEX(A2R!$B$2:$BF$318, MATCH($C$6, A2R!$B$2:$B$318,0), MATCH(B36, A2R!$B$2:$BF$2, 0)) -> 16 | D36: =IF(OR(C36="..",C36="-",$C$15=0),"",C36/$C$15) -> 0.057553957 | F36: Difficulties budgeting | G36: =INDEX('A3'!$B$2:$AK$323,MATCH($C$6,'A3'!$B$2:$B$323,0),MATCH(F36,'A3'!$B$2:$AK$2,0)) -> 129 | H36: =IF(OR(G36="..",G36="-",$C$10=0),"",G36/$C$10) -> 0.1598513
B37: Domestic abuse | C37: =INDEX(A2R!$B$2:$BF$318, MATCH($C$6, A2R!$B$2:$B$318,0), MATCH(B37, A2R!$B$2:$BF$2, 0)) -> 43 | D37: =IF(OR(C37="..",C37="-",$C$15=0),"",C37/$C$15) -> 0.15467626
B38: Non-violent relationship breakdown with partner | C38: =INDEX(A2R!$B$2:$BF$318, MATCH($C$6, A2R!$B$2:$B$318,0), MATCH(B38, A2R!$B$2:$BF$2, 0)) -> 14 | D38: =IF(OR(C38="..",C38="-",$C$15=0),"",C38/$C$15) -> 0.050359712 | F38: Age of main applicants owed a prevention or relief duty7:
B39: End of social rented tenancy | C39: =INDEX(A2R!$B$2:$BF$318, MATCH($C$6, A2R!$B$2:$B$318,0), MATCH(B39, A2R!$B$2:$BF$2, 0)) -> 7 | D39: =IF(OR(C39="..",C39="-",$C$15=0),"",C39/$C$15) -> 0.025179856 | F39: 16-17 | G39: =INDEX('A6'!$B$2:$X$319,MATCH($C$6,'A6'!$B$2:$B$319,0),MATCH(F39,'A6'!$B$2:$X$2,0)) -> 10 | H39: =IF(OR(G39="..",G39="-",$C$10=0),"",G39/$C$10) -> 0.012391574
B40: Eviction from supported housing | C40: =INDEX(A2R!$B$2:$BF$318, MATCH($C$6, A2R!$B$2:$B$318,0), MATCH(B40, A2R!$B$2:$BF$2, 0)) -> 25 | D40: =IF(OR(C40="..",C40="-",$C$15=0),"",C40/$C$15) -> 0.089928058 | F40: 18-24 | G40: =INDEX('A6'!$B$2:$X$319,MATCH($C$6,'A6'!$B$2:$B$319,0),MATCH(F40,'A6'!$B$2:$X$2,0)) -> 155 | H40: =IF(OR(G40="..",G40="-",$C$10=0),"",G40/$C$10) -> 0.19206939
B41: End of private rented tenancy - not assured shorthold | C41: =INDEX(A2R!$B$2:$BF$318, MATCH($C$6, A2R!$B$2:$B$318,0), MATCH(B41, A2R!$B$2:$BF$2, 0)) -> 5 | D41: =IF(OR(C41="..",C41="-",$C$15=0),"",C41/$C$15) -> 0.017985612 | F41: 25-34 | G41: =INDEX('A6'!$B$2:$X$319,MATCH($C$6,'A6'!$B$2:$B$319,0),MATCH(F41,'A6'!$B$2:$X$2,0)) -> 209 | H41: =IF(OR(G41="..",G41="-",$C$10=0),"",G41/$C$10) -> 0.25898389
B42: Other violence or harrassment | C42: =INDEX(A2R!$B$2:$BF$318, MATCH($C$6, A2R!$B$2:$B$318,0), MATCH(B42, A2R!$B$2:$BF$2, 0)) -> 6 | D42: =IF(OR(C42="..",C42="-",$C$15=0),"",C42/$C$15) -> 0.021582734 | F42: 35-44 | G42: =INDEX('A6'!$B$2:$X$319,MATCH($C$6,'A6'!$B$2:$B$319,0),MATCH(F42,'A6'!$B$2:$X$2,0)) -> 204 | H42: =IF(OR(G42="..",G42="-",$C$10=0),"",G42/$C$10) -> 0.2527881
B43: Left institution with no accommodation available | C43: =INDEX(A2R!$B$2:$BF$318, MATCH($C$6, A2R!$B$2:$B$318,0), MATCH(B43, A2R!$B$2:$BF$2, 0)) -> 11 | D43: =IF(OR(C43="..",C43="-",$C$15=0),"",C43/$C$15) -> 0.039568345 | F43: 45-54 | G43: =INDEX('A6'!$B$2:$X$319,MATCH($C$6,'A6'!$B$2:$B$319,0),MATCH(F43,'A6'!$B$2:$X$2,0)) -> 119 | H43: =IF(OR(G43="..",G43="-",$C$10=0),"",G43/$C$10) -> 0.14745973
B44: Required to leave accommodation provided by Home Office as asylum support | C44: =INDEX(A2R!$B$2:$BF$318, MATCH($C$6, A2R!$B$2:$B$318,0), MATCH(B44, A2R!$B$2:$BF$2, 0)) -> 4 | D44: =IF(OR(C44="..",C44="-",$C$15=0),"",C44/$C$15) -> 0.014388489 | F44: 55-64 | G44: =INDEX('A6'!$B$2:$X$319,MATCH($C$6,'A6'!$B$2:$B$319,0),MATCH(F44,'A6'!$B$2:$X$2,0)) -> 71 | H44: =IF(OR(G44="..",G44="-",$C$10=0),"",G44/$C$10) -> 0.087980173
B45: Home no longer suitable - disability / ill health | C45: =INDEX(A2R!$B$2:$BF$318, MATCH($C$6, A2R!$B$2:$B$318,0), MATCH(B45, A2R!$B$2:$BF$2, 0)) -> 0 | D45: =IF(OR(C45="..",C45="-",$C$13=0),"",C45/$C$13) -> 0 | F45: 65-74 | G45: =INDEX('A6'!$B$2:$X$319,MATCH($C$6,'A6'!$B$2:$B$319,0),MATCH(F45,'A6'!$B$2:$X$2,0)) -> 26 | H45: =IF(OR(G45="..",G45="-",$C$10=0),"",G45/$C$10) -> 0.032218092
B46: Other reasons / not known6 | C46: =INDEX(A2R!$B$2:$BF$318, MATCH($C$6, A2R!$B$2:$B$318,0), MATCH(B46, A2R!$B$2:$BF$2, 0)) -> 27 | D46: =IF(OR(C46="..",C46="-",$C$15=0),"",C46/$C$15) -> 0.097122302 | F46: 75+ | G46: =INDEX('A6'!$B$2:$X$319,MATCH($C$6,'A6'!$B$2:$B$319,0),MATCH(F46,'A6'!$B$2:$X$2,0)) -> 13 | H46: =IF(OR(G46="..",G46="-",$C$10=0),"",G46/$C$10) -> 0.016109046
F47: Not known8 | G47: =INDEX('A6'!$B$2:$X$319,MATCH($C$6,'A6'!$B$2:$B$319,0),MATCH(F47,'A6'!$B$2:$X$2,0)) -> 0 | H47: =IF(OR(G47="..",G47="-",$C$10=0),"",G47/$C$10) -> 0
B48: Accommodation at time of application for those owed a prevention duty:
B49: Private rented sector | C49: =INDEX(A4P!$B$2:$AK$323,MATCH($C$6,A4P!$B$2:$B$323,0),MATCH(B49,A4P!$B$2:$AK$2,0)) -> 177 | D49: =IF(OR(C49="..",C49="-",$C$13=0),"",C49/$C$13) -> 0.33459357 | F49: Accommodation at time of application for those owed a relief duty:
B50: Living with family | C50: =INDEX(A4P!$B$2:$AK$323,MATCH($C$6,A4P!$B$2:$B$323,0),MATCH(B50,A4P!$B$2:$AK$2,0)) -> 177 | D50: =IF(OR(C50="..",C50="-",$C$13=0),"",C50/$C$13) -> 0.33459357 | F50: Private rented sector | G50: =INDEX(A4R!$B$2:$AK$323,MATCH($C$6,A4R!$B$2:$B$323,0),MATCH(F50,A4R!$B$2:$AK$2,0)) -> 9 | H50: =IF(OR(G50="..",G50="-",$C$15=0),"",G50/$C$15) -> 0.032374101
B51: No fixed abode³ | C51: =INDEX(A4P!$B$2:$AK$323,MATCH($C$6,A4P!$B$2:$B$323,0),MATCH(B51,A4P!$B$2:$AK$2,0)) -> 0 | D51: =IF(OR(C51="..",C51="-",$C$13=0),"",C51/$C$13) -> 0 | F51: Living with family | G51: =INDEX(A4R!$B$2:$AK$323,MATCH($C$6,A4R!$B$2:$B$323,0),MATCH(F51,A4R!$B$2:$AK$2,0)) -> 58 | H51: =IF(OR(G51="..",G51="-",$C$15=0),"",G51/$C$15) -> 0.20863309
B52: Social rented sector | C52: =INDEX(A4P!$B$2:$AK$323,MATCH($C$6,A4P!$B$2:$B$323,0),MATCH(B52,A4P!$B$2:$AK$2,0)) -> 13 | D52: =IF(OR(C52="..",C52="-",$C$13=0),"",C52/$C$13) -> 0.024574669 | F52: No fixed abode³ | G52: =INDEX(A4R!$B$2:$AK$323,MATCH($C$6,A4R!$B$2:$B$323,0),MATCH(F52,A4R!$B$2:$AK$2,0)) -> 35 | H52: =IF(OR(G52="..",G52="-",$C$15=0),"",G52/$C$15) -> 0.12589928
B53: Living with friends | C53: =INDEX(A4P!$B$2:$AK$323,MATCH($C$6,A4P!$B$2:$B$323,0),MATCH(B53,A4P!$B$2:$AK$2,0)) -> 80 | D53: =IF(OR(C53="..",C53="-",$C$13=0),"",C53/$C$13) -> 0.15122873 | F53: Social rented sector | G53: =INDEX(A4R!$B$2:$AK$323,MATCH($C$6,A4R!$B$2:$B$323,0),MATCH(F53,A4R!$B$2:$AK$2,0)) -> 18 | H53: =IF(OR(G53="..",G53="-",$C$15=0),"",G53/$C$15) -> 0.064748201
B54: Homeless on departure from institution | C54: =INDEX(A4P!$B$2:$AK$323,MATCH($C$6,A4P!$B$2:$B$323,0),MATCH(B54,A4P!$B$2:$AK$2,0)) -> 31 | D54: =IF(OR(C54="..",C54="-",$C$13=0),"",C54/$C$13) -> 0.058601134 | F54: Living with friends | G54: =INDEX(A4R!$B$2:$AK$323,MATCH($C$6,A4R!$B$2:$B$323,0),MATCH(F54,A4R!$B$2:$AK$2,0)) -> 28 | H54: =IF(OR(G54="..",G54="-",$C$15=0),"",G54/$C$15) -> 0.10071942
B55: Rough sleeping | C55: =INDEX(A4P!$B$2:$AK$323,MATCH($C$6,A4P!$B$2:$B$323,0),MATCH(B55,A4P!$B$2:$AK$2,0)) -> 0 | D55: =IF(OR(C55="..",C55="-",$C$13=0),"",C55/$C$13) -> 0 | F55: Homeless on departure from institution | G55: =INDEX(A4R!$B$2:$AK$323,MATCH($C$6,A4R!$B$2:$B$323,0),MATCH(F55,A4R!$B$2:$AK$2,0)) -> 22 | H55: =IF(OR(G55="..",G55="-",$C$15=0),"",G55/$C$15) -> 0.079136691
B56: Owner-occupier / shared ownership | C56: =INDEX(A4P!$B$2:$AK$323,MATCH($C$6,A4P!$B$2:$B$323,0),MATCH(B56,A4P!$B$2:$AK$2,0)) -> 14 | D56: =IF(OR(C56="..",C56="-",$C$13=0),"",C56/$C$13) -> 0.026465028 | F56: Rough sleeping | G56: =INDEX(A4R!$B$2:$AK$323,MATCH($C$6,A4R!$B$2:$B$323,0),MATCH(F56,A4R!$B$2:$AK$2,0)) -> 85 | H56: =IF(OR(G56="..",G56="-",$C$15=0),"",G56/$C$15) -> 0.3057554
B57: Temporary accommodation | C57: =INDEX(A4P!$B$2:$AK$323,MATCH($C$6,A4P!$B$2:$B$323,0),MATCH(B57,A4P!$B$2:$AK$2,0)) -> 4 | D57: =IF(OR(C57="..",C57="-",$C$13=0),"",C57/$C$13) -> 0.0075614367 | F57: Owner-occupier / shared ownership | G57: =INDEX(A4R!$B$2:$AK$323,MATCH($C$6,A4R!$B$2:$B$323,0),MATCH(F57,A4R!$B$2:$AK$2,0)) -> 3 | H57: =IF(OR(G57="..",G57="-",$C$15=0),"",G57/$C$15) -> 0.010791367
B58: National Asylum Seeker Support (NASS) accommodation | C58: =INDEX(A4P!$B$2:$AK$323,MATCH($C$6,A4P!$B$2:$B$323,0),MATCH(B58,A4P!$B$2:$AK$2,0)) -> 19 | D58: =IF(OR(C58="..",C58="-",$C$13=0),"",C58/$C$13) -> 0.035916824 | F58: Temporary accommodation | G58: =INDEX(A4R!$B$2:$AK$323,MATCH($C$6,A4R!$B$2:$B$323,0),MATCH(F58,A4R!$B$2:$AK$2,0)) -> 6 | H58: =IF(OR(G58="..",G58="-",$C$15=0),"",G58/$C$15) -> 0.021582734
B59: Refuge | C59: =INDEX(A4P!$B$2:$AK$323,MATCH($C$6,A4P!$B$2:$B$323,0),MATCH(B59,A4P!$B$2:$AK$2,0)) -> 0 | D59: =IF(OR(C59="..",C59="-",$C$13=0),"",C59/$C$13) -> 0 | F59: National Asylum Seeker Support (NASS) accommodation | G59: =INDEX(A4R!$B$2:$AK$323,MATCH($C$6,A4R!$B$2:$B$323,0),MATCH(F59,A4R!$B$2:$AK$2,0)) -> 4 | H59: =IF(OR(G59="..",G59="-",$C$15=0),"",G59/$C$15) -> 0.014388489
B60: Other / not known⁴ | C60: =INDEX(A4P!$B$2:$AK$323,MATCH($C$6,A4P!$B$2:$B$323,0),MATCH(B60,A4P!$B$2:$AK$2,0)) -> 14 | D60: =IF(OR(C60="..",C60="-",$C$13=0),"",C60/$C$13) -> 0.026465028 | F60: Refuge | G60: =INDEX(A4R!$B$2:$AK$323,MATCH($C$6,A4R!$B$2:$B$323,0),MATCH(F60,A4R!$B$2:$AK$2,0)) -> 9 | H60: =IF(OR(G60="..",G60="-",$C$15=0),"",G60/$C$15) -> 0.032374101
F61: Other / not known⁴ | G61: =INDEX(A4R!$B$2:$AK$323,MATCH($C$6,A4R!$B$2:$B$323,0),MATCH(F61,A4R!$B$2:$AK$2,0)) -> 1 | H61: =IF(OR(G61="..",G61="-",$C$15=0),"",G61/$C$15) -> 0.0035971223
B62: Household type of households owed a prevention duty7:
B63: Households with children (Families) | C63: =SUM(C65:C67, C71,C73) -> 182 | D63: =IF(OR(C63="..",C63="-",$C$13=0),"",C63/$C$13) -> 0.34404537 | F63: Household type of households owed a relief duty7:
B64: Households without children (Single Households) | C64: =SUM(C68:C70, C72, C74) -> 347 | D64: =IF(OR(C64="..",C64="-",$C$13=0),"",C64/$C$13) -> 0.65595463 | F64: Households with children (Families) | G64: =SUM(G66:G68, G72,G74) -> 37 | H64: =IF(OR(G64="..",G64="-",$C$13=0),"",G64/$C$13) -> 0.069943289
A65: Single parent with dependent children - Male | B65: Single parent with dependent children - Male | C65: =INDEX(A5P!$B$2:$AE$316,MATCH($C$6,A5P!$B$2:$B$316,0),MATCH(A65,A5P!$B$2:$AE$2,0)) -> 11 | D65: =IF(OR(C65="..",C65="-",$C$13=0),"",C65/$C$13) -> 0.020793951 | F65: Households without children (Single Households) | G65: =SUM(G69:G71, G73, G75) -> 241 | H65: =IF(OR(G65="..",G65="-",$C$13=0),"",G65/$C$13) -> 0.45557656
A66: Single parent with dependent children - Female | B66: Single parent with dependent children - Female | C66: =INDEX(A5P!$B$2:$AE$316,MATCH($C$6,A5P!$B$2:$B$316,0),MATCH(A66,A5P!$B$2:$AE$2,0)) -> 111 | D66: =IF(OR(C66="..",C66="-",$C$13=0),"",C66/$C$13) -> 0.20982987 | F66: Single parent with dependent children - Male | G66: =INDEX(A5R!$B$2:$AE$321,MATCH($C$6,A5R!$B$2:$B$316,0),MATCH(A65,A5R!$B$2:$AE$2,0)) -> 2 | H66: =IF(OR(G66="..",G66="-",$C$15=0),"",G66/$C$15) -> 0.0071942446
A67: Single parent with dependent children - Other/gender not known | B67: Single parent with dependent children - Other / gender not known | C67: =INDEX(A5P!$B$2:$AE$316,MATCH($C$6,A5P!$B$2:$B$316,0),MATCH(A67,A5P!$B$2:$AE$2,0)) -> 0 | D67: =IF(OR(C67="..",C67="-",$C$13=0),"",C67/$C$13) -> 0 | F67: Single parent with dependent children - Female | G67: =INDEX(A5R!$B$2:$AE$321,MATCH($C$6,A5R!$B$2:$B$316,0),MATCH(A66,A5R!$B$2:$AE$2,0)) -> 23 | H67: =IF(OR(G67="..",G67="-",$C$15=0),"",G67/$C$15) -> 0.082733813
A68: Single adult - Male | B68: Single adult - Male | C68: =INDEX(A5P!$B$2:$AE$316,MATCH($C$6,A5P!$B$2:$B$316,0),MATCH(A68,A5P!$B$2:$AE$2,0)) -> 175 | D68: =IF(OR(C68="..",C68="-",$C$13=0),"",C68/$C$13) -> 0.33081285 | F68: Single parent with dependent children - Other / gender not known | G68: =INDEX(A5R!$B$2:$AE$321,MATCH($C$6,A5R!$B$2:$B$316,0),MATCH(A67,A5R!$B$2:$AE$2,0)) -> 0 | H68: =IF(OR(G68="..",G68="-",$C$15=0),"",G68/$C$15) -> 0
A69: Single adult - Female | B69: Single adult - Female | C69: =INDEX(A5P!$B$2:$AE$316,MATCH($C$6,A5P!$B$2:$B$316,0),MATCH(A69,A5P!$B$2:$AE$2,0)) -> 121 | D69: =IF(OR(C69="..",C69="-",$C$13=0),"",C69/$C$13) -> 0.22873346 | F69: Single adult - Male | G69: =INDEX(A5R!$B$2:$AE$321,MATCH($C$6,A5R!$B$2:$B$316,0),MATCH(A68,A5R!$B$2:$AE$2,0)) -> 179 | H69: =IF(OR(G69="..",G69="-",$C$15=0),"",G69/$C$15) -> 0.64388489
A70: Single adult - Other/gender not known | B70: Single adult - Other / gender not known | C70: =INDEX(A5P!$B$2:$AE$316,MATCH($C$6,A5P!$B$2:$B$316,0),MATCH(A70,A5P!$B$2:$AE$2,0)) -> 1 | D70: =IF(OR(C70="..",C70="-",$C$13=0),"",C70/$C$13) -> 0.0018903592 | F70: Single adult - Female | G70: =INDEX(A5R!$B$2:$AE$321,MATCH($C$6,A5R!$B$2:$B$316,0),MATCH(A69,A5R!$B$2:$AE$2,0)) -> 58 | H70: =IF(OR(G70="..",G70="-",$C$15=0),"",G70/$C$15) -> 0.20863309
A71: Couple with dependent children | B71: Couple with dependent children | C71: =INDEX(A5P!$B$2:$AE$316,MATCH($C$6,A5P!$B$2:$B$316,0),MATCH(A71,A5P!$B$2:$AE$2,0)) -> 51 | D71: =IF(OR(C71="..",C71="-",$C$13=0),"",C71/$C$13) -> 0.096408318 | F71: Single adult - Other / gender not known | G71: =INDEX(A5R!$B$2:$AE$321,MATCH($C$6,A5R!$B$2:$B$316,0),MATCH(A70,A5R!$B$2:$AE$2,0)) -> 0 | H71: =IF(OR(G71="..",G71="-",$C$15=0),"",G71/$C$15) -> 0
A72: Couple / two adults without dependent children | B72: Couple / two adults without dependent children | C72: =INDEX(A5P!$B$2:$AE$316,MATCH($C$6,A5P!$B$2:$B$316,0),MATCH(A72,A5P!$B$2:$AE$2,0)) -> 44 | D72: =IF(OR(C72="..",C72="-",$C$13=0),"",C72/$C$13) -> 0.083175803 | F72: Couple with dependent children | G72: =INDEX(A5R!$B$2:$AE$321,MATCH($C$6,A5R!$B$2:$B$316,0),MATCH(A71,A5R!$B$2:$AE$2,0)) -> 11 | H72: =IF(OR(G72="..",G72="-",$C$15=0),"",G72/$C$15) -> 0.039568345
A73: Three or more adults with dependent children | B73: Three or more adults with dependent children | C73: =INDEX(A5P!$B$2:$AE$316,MATCH($C$6,A5P!$B$2:$B$316,0),MATCH(A73,A5P!$B$2:$AE$2,0)) -> 9 | D73: =IF(OR(C73="..",C73="-",$C$13=0),"",C73/$C$13) -> 0.017013233 | F73: Couple / two adults without dependent children | G73: =INDEX(A5R!$B$2:$AE$321,MATCH($C$6,A5R!$B$2:$B$316,0),MATCH(A72,A5R!$B$2:$AE$2,0)) -> 4 | H73: =IF(OR(G73="..",G73="-",$C$15=0),"",G73/$C$15) -> 0.014388489
A74: Three or more adults without dependent children | B74: Three or more adults without dependent children | C74: =INDEX(A5P!$B$2:$AE$316,MATCH($C$6,A5P!$B$2:$B$316,0),MATCH(A74,A5P!$B$2:$AE$2,0)) -> 6 | D74: =IF(OR(C74="..",C74="-",$C$13=0),"",C74/$C$13) -> 0.011342155 | F74: Three or more adults with dependent children | G74: =INDEX(A5R!$B$2:$AE$321,MATCH($C$6,A5R!$B$2:$B$316,0),MATCH(A73,A5R!$B$2:$AE$2,0)) -> 1 | H74: =IF(OR(G74="..",G74="-",$C$15=0),"",G74/$C$15) -> 0.0035971223
A75: Not known8 | B75: Not known8 | C75: =INDEX(A5P!$B$2:$AE$316,MATCH($C$6,A5P!$B$2:$B$316,0),MATCH(A75,A5P!$B$2:$AE$2,0)) -> 0 | D75: =IF(OR(C75="..",C75="-",$C$13=0),"",C75/$C$13) -> 0 | F75: Three or more adults without dependent children | G75: =INDEX(A5R!$B$2:$AE$321,MATCH($C$6,A5R!$B$2:$B$316,0),MATCH(A74,A5R!$B$2:$AE$2,0)) -> 0 | H75: =IF(OR(G75="..",G75="-",$C$15=0),"",G75/$C$15) -> 0
F76: Not known8 | G76: =INDEX(A5R!$B$2:$AE$321,MATCH($C$6,A5R!$B$2:$B$316,0),MATCH(A75,A5R!$B$2:$AE$2,0)) -> 0 | H76: =IF(OR(G76="..",G76="-",$C$15=0),"",G76/$C$15) -> 0
B77: Households assessed as a result of a referral, including under the Duty to Refer
B78: Total households assessed as a result of a referral | C78: =INDEX('A7'!$B$2:$X$332,MATCH($C$6,'A7'!$B2:$B332,0),MATCH($B78,'A7'!B$2:X$2,0)) -> 78 | D78: =IF(OR(C78="..",C78="-",$C$13=0),"",C78/$C$78) -> 1 | F78: Employment status of main applicants owed a duty7:
B79: Total households referred under the Duty to Refer | C79: =INDEX('A7'!$B$2:$X$332,MATCH($C$6,'A7'!$B$2:$B$332,0),MATCH($B79,'A7'!B$2:X$2,0)) -> 59 | D79: =IF(OR(C79="..",C79="-",$C$13=0),"",C79/$C$78) -> 0.75641026 | F79: Registered unemployed | G79: =INDEX('A10'!$B$2:$U$321,MATCH($C$6,'A10'!$B$2:$B$321,0),MATCH(F79,'A10'!$B$2:$U$2,0)) -> 338 | H79: =IF(OR(G79="..",G79="-",$C$10=0),"",G79/$C$10) -> 0.41883519
B80: Adult Secure Estate (prison) | C80: =INDEX('A7'!$B$2:$X$332,MATCH($C$6,'A7'!$B$2:$B$332,0),MATCH($B80,'A7'!B$2:X$2,0)) -> 7 | D80: =IF(OR(C80="..",C80="-",$C$13=0),"",C80/$C$78) -> 0.08974359 | F80: Not working due to long-term illness / disability | G80: =INDEX('A10'!$B$2:$U$321,MATCH($C$6,'A10'!$B$2:$B$321,0),MATCH(F80,'A10'!$B$2:$U$2,0)) -> 85 | H80: =IF(OR(G80="..",G80="-",$C$10=0),"",G80/$C$10) -> 0.10532838
B81: Youth Secure Estate | C81: =INDEX('A7'!$B$2:$X$332,MATCH($C$6,'A7'!$B$2:$B$332,0),MATCH($B81,'A7'!B$2:X$2,0)) -> 0 | D81: =IF(OR(C81="..",C81="-",$C$13=0),"",C81/$C$78) -> 0 | F81: Full-time work | G81: =INDEX('A10'!$B$2:$U$321,MATCH($C$6,'A10'!$B$2:$B$321,0),MATCH(F81,'A10'!$B$2:$U$2,0)) -> 159 | H81: =IF(OR(G81="..",G81="-",$C$10=0),"",G81/$C$10) -> 0.19702602
B82: National Probation Service | C82: =INDEX('A7'!$B$2:$X$332,MATCH($C$6,'A7'!$B$2:$B$332,0),MATCH($B82,'A7'!B$2:X$2,0)) -> 30 | D82: =IF(OR(C82="..",C82="-",$C$13=0),"",C82/$C$78) -> 0.38461538 | F82: Part-time work | G82: =INDEX('A10'!$B$2:$U$321,MATCH($C$6,'A10'!$B$2:$B$321,0),MATCH(F82,'A10'!$B$2:$U$2,0)) -> 96 | H82: =IF(OR(G82="..",G82="-",$C$10=0),"",G82/$C$10) -> 0.11895911
B83: Community Rehabilitation Company | C83: =INDEX('A7'!$B$2:$X$332,MATCH($C$6,'A7'!$B$2:$B$332,0),MATCH($B83,'A7'!B$2:X$2,0)) -> 0 | D83: =IF(OR(C83="..",C83="-",$C$13=0),"",C83/$C$78) -> 0 | F83: Not seeking work / at home | G83: =INDEX('A10'!$B$2:$U$321,MATCH($C$6,'A10'!$B$2:$B$321,0),MATCH(F83,'A10'!$B$2:$U$2,0)) -> 21 | H83: =IF(OR(G83="..",G83="-",$C$10=0),"",G83/$C$10) -> 0.026022305
B84: Hospital A&E, Urgent Treatment Centres or in-patient care | C84: =INDEX('A7'!$B$2:$X$332,MATCH($C$6,'A7'!$B$2:$B$332,0),MATCH($B84,'A7'!B$2:X$2,0)) -> 0 | D84: =IF(OR(C84="..",C84="-",$C$13=0),"",C84/$C$78) -> 0 | F84: Not registered unemployed but seeking work | G84: =INDEX('A10'!$B$2:$U$321,MATCH($C$6,'A10'!$B$2:$B$321,0),MATCH(F84,'A10'!$B$2:$U$2,0)) -> 7 | H84: =IF(OR(G84="..",G84="-",$C$10=0),"",G84/$C$10) -> 0.0086741016
B85: Mental Health in-patient care | C85: =INDEX('A7'!$B$2:$X$332,MATCH($C$6,'A7'!$B$2:$B$332,0),MATCH($B85,'A7'!B$2:X$2,0)) -> 2 | D85: =IF(OR(C85="..",C85="-",$C$13=0),"",C85/$C$78) -> 0.025641026 | F85: Retired | G85: =INDEX('A10'!$B$2:$U$321,MATCH($C$6,'A10'!$B$2:$B$321,0),MATCH(F85,'A10'!$B$2:$U$2,0)) -> 32 | H85: =IF(OR(G85="..",G85="-",$C$10=0),"",G85/$C$10) -> 0.039653036
B86: Jobcentre Plus | C86: =INDEX('A7'!$B$2:$X$332,MATCH($C$6,'A7'!$B$2:$B$332,0),MATCH($B86,'A7'!B$2:X$2,0)) -> 5 | D86: =IF(OR(C86="..",C86="-",$C$13=0),"",C86/$C$78) -> 0.064102564 | F86: Student / training | G86: =INDEX('A10'!$B$2:$U$321,MATCH($C$6,'A10'!$B$2:$B$321,0),MATCH(F86,'A10'!$B$2:$U$2,0)) -> 10 | H86: =IF(OR(G86="..",G86="-",$C$10=0),"",G86/$C$10) -> 0.012391574
B87: Adult Social Services | C87: =INDEX('A7'!$B$2:$X$332,MATCH($C$6,'A7'!$B$2:$B$332,0),MATCH($B87,'A7'!B$2:X$2,0)) -> 6 | D87: =IF(OR(C87="..",C87="-",$C$13=0),"",C87/$C$78) -> 0.076923077 | F87: Registered employed off work | G87: =INDEX('A10'!$B$2:$U$321,MATCH($C$6,'A10'!$B$2:$B$321,0),MATCH(F87,'A10'!$B$2:$U$2,0)) -> 26 | H87: =IF(OR(G87="..",G87="-",$C$10=0),"",G87/$C$10) -> 0.032218092
B88: Children's Social Services | C88: =INDEX('A7'!$B$2:$X$332,MATCH($C$6,'A7'!$B$2:$B$332,0),MATCH($B88,'A7'!B$2:X$2,0)) -> 9 | D88: =IF(OR(C88="..",C88="-",$C$13=0),"",C88/$C$78) -> 0.11538462 | F88: Working irregular hours | G88: =INDEX('A10'!$B$2:$U$321,MATCH($C$6,'A10'!$B$2:$B$321,0),MATCH(F88,'A10'!$B$2:$U$2,0)) -> 18 | H88: =IF(OR(G88="..",G88="-",$C$10=0),"",G88/$C$10) -> 0.022304833
B89: Children's Early Help Services/Children's centres | C89: =INDEX('A7'!$B$2:$X$332,MATCH($C$6,'A7'!$B$2:$B$332,0),MATCH($B89,'A7'!B$2:X$2,0)) -> 0 | D89: =IF(OR(C89="..",C89="-",$C$13=0),"",C89/$C$78) -> 0 | F89: Other | G89: =INDEX('A10'!$B$2:$U$321,MATCH($C$6,'A10'!$B$2:$B$321,0),MATCH(F89,'A10'!$B$2:$U$2,0)) -> 8 | H89: =IF(OR(G89="..",G89="-",$C$10=0),"",G89/$C$10) -> 0.009913259
B90: Nil Recourse Team | C90: =INDEX('A7'!$B$2:$X$332,MATCH($C$6,'A7'!$B$2:$B$332,0),MATCH($B90,'A7'!B$2:X$2,0)) -> 0 | D90: =IF(OR(C90="..",C90="-",$C$13=0),"",C90/$C$78) -> 0 | F90: Not known8 | G90: =INDEX('A10'!$B$2:$U$321,MATCH($C$6,'A10'!$B$2:$B$321,0),MATCH(F90,'A10'!$B$2:$U$2,0)) -> 7 | H90: =IF(OR(G90="..",G90="-",$C$10=0),"",G90/$C$10) -> 0.0086741016
B91: Secretary of State for defence in relation to members of the armed forces | C91: =INDEX('A7'!$B$2:$X$332,MATCH($C$6,'A7'!$B$2:$B$332,0),MATCH($B91,'A7'!B$2:X$2,0)) -> 0 | D91: =IF(OR(C91="..",C91="-",$C$13=0),"",C91/$C$78) -> 0
B92: Not Known | C92: =INDEX('A7'!$B$2:$X$332,MATCH($C$6,'A7'!$B$2:$B$332,0),MATCH($B92,'A7'!B$2:X$2,0)) -> 0 | D92: =IF(OR(C92="..",C92="-",$C$13=0),"",C92/$C$78) -> 0 | F92: Sexual identification of main applicants owed a duty7:
B93: Households referred by an agency (not subject to the Duty to Refer) | C93: =INDEX('A7'!$B$2:$X$332,MATCH($C$6,'A7'!$B$2:$B$332,0),MATCH($B93,'A7'!B$2:X$2,0)) -> 19 | D93: =IF(OR(C93="..",C93="-",$C$13=0),"",C93/$C$78) -> 0.24358974 | F93: Heterosexual | G93: =INDEX('A12'!$B$2:$L$322,MATCH($C$6,'A12'!$B$2:$B$322,0),MATCH(F93,'A12'!$B$2:$L$2,0)) -> 536 | H93: =IF(OR(G93="..",G93="-",$C$10=0),"",G93/$C$10) -> 0.66418835
B94: Households referred by another local authority | C94: =INDEX('A7'!$B$2:$X$332,MATCH($C$6,'A7'!$B$2:$B$332,0),MATCH($B94,'A7'!B$2:X$2,0)) -> 0 | D94: =IF(OR(C94="..",C94="-",$C$13=0),"",C94/$C$78) -> 0 | F94: Homosexual (Gay/Lesbian) | G94: =INDEX('A12'!$B$2:$L$322,MATCH($C$6,'A12'!$B$2:$B$322,0),MATCH(F94,'A12'!$B$2:$L$2,0)) -> 10 | H94: =IF(OR(G94="..",G94="-",$C$10=0),"",G94/$C$10) -> 0.012391574
F95: Bisexual | G95: =INDEX('A12'!$B$2:$L$322,MATCH($C$6,'A12'!$B$2:$B$322,0),MATCH(F95,'A12'!$B$2:$L$2,0)) -> 4 | H95: =IF(OR(G95="..",G95="-",$C$10=0),"",G95/$C$10) -> 0.0049566295
B96: Ethnicity of main applicants owed a prevention or relief duty7: | F96: Other | G96: =INDEX('A12'!$B$2:$L$322,MATCH($C$6,'A12'!$B$2:$B$322,0),MATCH(F96,'A12'!$B$2:$L$2,0)) -> 4 | H96: =IF(OR(G96="..",G96="-",$C$10=0),"",G96/$C$10) -> 0.0049566295
B97: White | C97: =INDEX('A8'!$B$2:$BH$321,MATCH($C$6,'A8'!$B$2:$B$321,0),MATCH(B97,'A8'!$B$2:$BH$2,0)) -> 723 | D97: =IF(OR(C97="..",C97="-",$C$10=0),"",C97/$C$10) -> 0.89591078 | F97: Prefer not to say | G97: =INDEX('A12'!$B$2:$L$322,MATCH($C$6,'A12'!$B$2:$B$322,0),MATCH(F97,'A12'!$B$2:$L$2,0)) -> 28 | H97: =IF(OR(G97="..",G97="-",$C$10=0),"",G97/$C$10) -> 0.034696406
B98: Black / African / Caribbean / Black British | C98: =INDEX('A8'!$B$2:$BH$321,MATCH($C$6,'A8'!$B$2:$B$321,0),MATCH(B98,'A8'!$B$2:$BH$2,0)) -> 16 | D98: =IF(OR(C98="..",C98="-",$C$10=0),"",C98/$C$10) -> 0.019826518 | F98: Not known | G98: =INDEX('A12'!$B$2:$L$322,MATCH($C$6,'A12'!$B$2:$B$322,0),MATCH(F98,'A12'!$B$2:$L$2,0)) -> 225 | H98: =IF(OR(G98="..",G98="-",$C$10=0),"",G98/$C$10) -> 0.27881041
B99: Asian / Asian British | C99: =INDEX('A8'!$B$2:$BH$321,MATCH($C$6,'A8'!$B$2:$B$321,0),MATCH(B99,'A8'!$B$2:$BH$2,0)) -> 22 | D99: =IF(OR(C99="..",C99="-",$C$10=0),"",C99/$C$10) -> 0.027261462
B100: Mixed / Multiple ethnic groups | C100: =INDEX('A8'!$B$2:$BH$321,MATCH($C$6,'A8'!$B$2:$B$321,0),MATCH(B100,'A8'!$B$2:$BH$2,0)) -> 10 | D100: =IF(OR(C100="..",C100="-",$C$10=0),"",C100/$C$10) -> 0.012391574
B101: Other ethnic groups | C101: =INDEX('A8'!$B$2:$BH$321,MATCH($C$6,'A8'!$B$2:$B$321,0),MATCH(B101,'A8'!$B$2:$BH$2,0)) -> 28 | D101: =IF(OR(C101="..",C101="-",$C$10=0),"",C101/$C$10) -> 0.034696406
B102: Not known8 | C102: =INDEX('A8'!$B$2:$BH$321,MATCH($C$6,'A8'!$B$2:$B$321,0),MATCH(B102,'A8'!$B$2:$BH$2,0)) -> 8 | D102: =IF(OR(C102="..",C102="-",$C$10=0),"",C102/$C$10) -> 0.009913259
B106: Notes:
B107: 1. Only includes households assessed post the introduction of the HRA
B108: 2. Excludes data for local authorities who did not provide a H-CLIC return. England and regional totals include estimates for authorities with partial returns. See tables for more quarter-specific information.
...

Sheet A1
A1: Table A1 - Number of households by initial assessment of homelessness circumstances and needs England, April 2024 to March 2025
E2: Total number of households assessed1,2 | G2: Total households assessed as owed a duty | H2: Threatened with homelessness - Prevention duty owed | I2: Of which: due to service of valid Section 21 Notice | J2: Homeless - Relief duty owed | L2: Not threatened with homelessness within 56 days - no duty owed | M2: Withdrew application before assessment - no duty owed | N2: Not eligible / no longer eligible - no duty owed
E3: Grand Total | H3: Threatened with homelessness – Prevention Duty owed | I3: Threatened with homelessness due to service of valid Section 21 Notice – Prevention Duty owed | J3: Already homeless – Relief Duty owed (include accepted local connection referrals) | L3: Not threatened with homelessness within 56 days | M3: Withdrew application before assessment - no duty owed | N3: Not eligible / no longer eligible - no duty owed
L4: Number of households
E5: Total initial assessments 1,2,6 | G5: Assessed as owed a duty | L5: Not homeless nor threatened with homelessness within 56 days - no duty owed | M5: Withdrew application before assessment - no duty owed | N5: Not eligible / no longer eligible - no duty owed | P5: Number of households in area5 (000s) | Q5: Households assessed as threatened with homelessness per (000s) | R5: Households assessed as homeless per (000s)
G6: Total owed a prevention or relief duty | H6: Threatened with homelessness within 56 days - Prevention duty owed | I6: Of which: | J6: Homeless - Relief duty owed4
I7: due to service of valid Section 21 Notice3
A8: E92000001 | B8: ENGLAND | E8: 360050 | G8: 330410 | H8: 147870 | I8: 26660 | J8: 182540 | L8: 14060 | M8: 12950 | N8: 2640 | P8: 24367.038 | Q8: 6.0684438 | R8: 7.4912675
A9: E12000007 | B9: London | E9: 77500 | G9: 70740 | H9: 28240 | I9: 4630 | J9: 42500 | L9: 2450 | M9: 3710 | N9: 600 | P9: 3687.399 | Q9: 7.6585149 | R9: 11.525739
A10: - | B10: Rest of England | E10: 282560 | G10: 259670 | H10: 119630 | I10: 22030 | J10: 140040 | L10: 11610 | M10: 9240 | N10: 2040 | P10: 20679.639 | Q10: 5.7849172 | R10: 6.7718784
A12: E12000001 | B12: North East | E12: 20800 | G12: 19720 | H12: 8930 | I12: 1380 | J12: 10780 | L12: 340 | M12: 630 | N12: 120 | P12: 1201.034 | Q12: 7.43526 | R12: 8.9755994
A13: E12000002 | B13: North West | E13: 49230 | G13: 47430 | H13: 20570 | I13: 3970 | J13: 26860 | L13: 1310 | M13: 370 | N13: 110 | P13: 3247.558 | Q13: 6.33399 | R13: 8.27083
A14: E12000003 | B14: Yorkshire and The Humber | E14: 32750 | G14: 31280 | H14: 15100 | I14: 2300 | J14: 16180 | L14: 710 | M14: 470 | N14: 290 | P14: 2393.288 | Q14: 6.3093117 | R14: 6.7605737
A15: E12000004 | B15: East Midlands | E15: 25620 | G15: 24640 | H15: 10800 | I15: 1970 | J15: 13840 | L15: 440 | M15: 270 | N15: 260 | P15: 2125.887 | Q15: 5.0802324 | R15: 6.5102237
A16: E12000005 | B16: West Midlands | E16: 36470 | G16: 31660 | H16: 11810 | I16: 1760 | J16: 19850 | L16: 2710 | M16: 1780 | N16: 320 | P16: 2534.384 | Q16: 4.6599095 | R16: 7.832278
A17: E12000006 | B17: East of England | E17: 36840 | G17: 32630 | H17: 15450 | I17: 2880 | J17: 17170 | L17: 2210 | M17: 1760 | N17: 250 | P17: 2689.206 | Q17: 5.7451902 | R17: 6.3847842
A18: E12000007 | B18: London | E18: 77500 | G18: 70740 | H18: 28240 | I18: 4630 | J18: 42500 | L18: 2450 | M18: 3710 | N18: 600 | P18: 3687.399 | Q18: 7.6585149 | R18: 11.525739
A19: E12000008 | B19: South East | E19: 50270 | G19: 44030 | H19: 23080 | I19: 5310 | J19: 20950 | L19: 3140 | M19: 2620 | N19: 480 | P19: 3936.408 | Q19: 5.8632134 | R19: 5.3221109
A20: E12000009 | B20: South West | E20: 30580 | G20: 28280 | H20: 13880 | I20: 2450 | J20: 14400 | L20: 750 | M20: 1340 | N20: 210 | P20: 2551.874 | Q20: 5.43914 | R20: 5.6429118
... A48: E07000143 | B48: Breckland | E48: 753 | G48: 709 | H48: 199 | I48: 45 | J48: 510 | L48: 25 | M48: 18 | N48: 1 | P48: 63.19 | Q48: 3.1492325 | R48: 8.0708973
A49: E09000005 | B49: Brent | E49: .. | G49: .. | H49: .. | I49: .. | J49: .. | L49: .. | M49: .. | N49: .. | P49: 120.849 | Q49: .. | R49: ..
A50: E07000068 | B50: Brentwood | E50: 206 | G50: 205 | H50: 111 | I50: 22 | J50: 94 | L50: 0 | M50: 1 | N50: 0 | P50: 31.534 | Q50: 3.5200101 | R50: 2.9809095
A51: E06000043 | B51: Brighton & Hove | E51: 1433 | G51: 1387 | H51: 403 | I51: 52 | J51: 984 | L51: 26 | M51: 17 | N51: 3 | P51: 128.635 | Q51: 3.1328954 | R51: 7.6495511
A52: E06000023 | B52: Bristol | E52: 3500 | G52: 3143 | H52: 897 | I52: 80 | J52: 2246 | L52: 173 | M52: 105 | N52: 79 | P52: 202.001 | Q52: 4.4405721 | R52: 11.118757
A53: E07000144 | B53: Broadland | E53: 483 | G53: 469 | H53: 156 | I53: 39 | J53: 313 | L53: 10 | M53: 3 | N53: 1 | P53: 59.498 | Q53: 2.6219369 | R53: 5.260681
A54: E09000006 | B54: Bromley | E54: 1825 | G54: 1661 | H54: 577 | I54: 223 | J54: 1084 | L54: 49 | M54: 115 | N54: 0 | P54: 144.795 | Q54: 3.9849442 | R54: 7.4864464
A55: E07000234 | B55: Bromsgrove | E55: 365 | G55: 355 | H55: 183 | I55: 10 | J55: 172 | L55: 4 | M55: 4 | N55: 2 | P55: 43.48 | Q55: 4.2088316 | R55: 3.9558418
A56: E07000095 | B56: Broxbourne | E56: 644 | G56: 566 | H56: 240 | I56: 31 | J56: 326 | L56: 49 | M56: 27 | N56: 2 | P56: 39.638 | Q56: 6.0547959 | R56: 8.2244311
A57: E07000172 | B57: Broxtowe | E57: 269 | G57: 247 | H57: 133 | I57: 62 | J57: 114 | L57: 6 | M57: 12 | N57: 4 | P57: 50.665 | Q57: 2.6250864 | R57: 2.250074
A58: E06000060 | B58: Buckinghamshire | E58: 4221 | G58: 2518 | H58: 1777 | I58: 150 | J58: 741 | L58: 1100 | M58: 533 | N58: 70 | P58: 224.112 | Q58: 7.9290712 | R58: 3.3063825
A59: E07000117 | B59: Burnley | E59: 689 | G59: 687 | H59: 292 | I59: 86 | J59: 395 | L59: 0 | M59: 0 | N59: 2 | P59: 39.214 | Q59: 7.4463202 | R59: 10.072933
A60: E08000002 | B60: Bury | E60: .. | G60: .. | H60: .. | I60: .. | J60: .. | L60: .. | M60: .. | N60: .. | P60: 83.748 | Q60: .. | R60: ..
A61: E08000033 | B61: Calderdale | E61: 1253 | G61: 1227 | H61: 887 | I61: 84 | J61: 340 | L61: 17 | M61: 3 | N61: 6 | P61: 96.054 | Q61: 9.234389 | R61: 3.5396756
A62: E07000008 | B62: Cambridge | E62: 1073 | G62: 772 | H62: 285 | I62: 27 | J62: 487 | L62: 205 | M62: 77 | N62: 19 | P62: 43.742 | Q62: 6.5154771 | R62: 11.133464
A63: E09000007 | B63: Camden | E63: .. | G63: .. | H63: .. | I63: .. | J63: .. | L63: .. | M63: .. | N63: .. | P63: 120.624 | Q63: .. | R63: ..
A64: E07000192 | B64: Cannock Chase | E64: 171 | G64: 171 | H64: 65 | I64: 4 | J64: 106 | L64: 0 | M64: 0 | N64: 0 | P64: 46.059 | Q64: 1.4112334 | R64: 2.301396
A65: E07000106 | B65: Canterbury | E65: .. | G65: .. | H65: .. | I65: .. | J65: .. | L65: .. | M65: .. | N65: .. | P65: 69.303 | Q65: .. | R65: ..
A66: E07000069 | B66: Castle Point | E66: 261 | G66: 259 | H66: 130 | I66: 73 | J66: 129 | L66: 2 | M66: 0 | N66: 0 | P66: 37.969 | Q66: 3.4238458 | R66: 3.3975085
A67: E06000056 | B67: Central Bedfordshire | E67: 1267 | G67: 1133 | H67: 560 | I67: 94 | J67: 573 | L67: 54 | M67: 76 | N67: 4 | P67: 126.152 | Q67: 4.4390894 | R67: 4.5421396
A68: E07000130 | B68: Charnwood | E68: 638 | G68: 625 | H68: 199 | I68: 41 | J68: 426 | L68: 9 | M68: 4 | N68: 0 | P68: 79.371 | Q68: 2.507213 | R68: 5.3671996
A69: E07000070 | B69: Chelmsford | E69: 929 | G69: 885 | H69: 400 | I69: 61 | J69: 485 | L69: 41 | M69: 2 | N69: 1 | P69: 77.948 | Q69: 5.1316262 | R69: 6.2220968
A70: E07000078 | B70: Cheltenham | E70: 609 | G70: 608 | H70: 295 | I70: 104 | J70: 313 | L70: 0 | M70: 1 | N70: 0 | P70: 52.768 | Q70: 5.5905094 | R70: 5.9316252
A71: E07000177 | B71: Cherwell | E71: 563 | G71: 560 | H71: 311 | I71: 70 | J71: 249 | L71: 0 | M71: 1 | N71: 2 | P71: 64.615 | Q71: 4.8131239 | R71: 3.8535944
A72: E06000049 | B72: Cheshire East | E72: 1898 | G72: 1884 | H72: 1138 | I72: 325 | J72: 746 | L72: 8 | M72: 4 | N72: 2 | P72: 175.591 | Q72: 6.48097 | R72: 4.2485093
A73: E06000050 | B73: Cheshire West & Chester | E73: 1931 | G73: 1754 | H73: 924 | I73: 152 | J73: 830 | L73: 25 | M73: 144 | N73: 8 | P73: 156.693 | Q73: 5.8968812 | R73: 5.296982
A74: E07000034 | B74: Chesterfield | E74: 624 | G74: 573 | H74: 199 | I74: 58 | J74: 374 | L74: 27 | M74: 24 | N74: 0 | P74: 49.325 | Q74: 4.0344653 | R74: 7.5823619
A75: E07000225 | B75: Chichester | E75: 509 | G75: 485 | H75: 244 | I75: 2 | J75: 241 | L75: 11 | M75: 13 | N75: 0 | P75: 56.65 | Q75: 4.3071492 | R75: 4.2541924
A76: E07000118 | B76: Chorley | E76: 576 | G76: 567 | H76: 275 | I76: 60 | J76: 292 | L76: 3 | M76: 2 | N76: 4 | P76: 53.921 | Q76: 5.1000538 | R76: 5.4153298
A77: E09000001 | B77: City of London | E77: 30 | G77: 27 | H77: 1 | I77: 0 | J77: 26 | L77: 2 | M77: 1 | N77: 0 | P77: 4.369 | Q77: 0.22888533 | R77: 5.9510185
... A82: E07000226 | B82: Crawley | E82: 1248 | G82: 997 | H82: 416 | I82: 102 | J82: 581 | L82: 68 | M82: 32 | N82: 151 | P82: 46.673 | Q82: 8.9130761 | R82: 12.448311
A83: E09000008 | B83: Croydon | E83: .. | G83: .. | H83: .. | I83: .. | J83: .. | L83: .. | M83: .. | N83: .. | P83: 158.189 | Q83: .. | R83: ..
A84: E06000063 | B84: Cumberland Council | E84: 1699 | G84: 1658 | H84: 898 | I84: 68 | J84: 760 | L84: 25 | M84: 14 | N84: 2 | P84: 124.19 | Q84: 7.2308559 | R84: 6.1196554
A85: E07000096 | B85: Dacorum | E85: 934 | G85: 910 | H85: 486 | I85: 84 | J85: 424 | L85: 9 | M85: 6 | N85: 9 | P85: 66.679 | Q85: 7.2886516 | R85: 6.3588236
A86: E06000005 | B86: Darlington | E86: 1450 | G86: 1354 | H86: 759 | I86: 120 | J86: 595 | L86: 46 | M86: 13 | N86: 37 | P86: 49.104 | Q86: 15.456989 | R86: 12.117139
A87: E07000107 | B87: Dartford | E87: 735 | G87: 635 | H87: 325 | I87: 95 | J87: 310 | L87: 23 | M87: 71 | N87: 6 | P87: 49.506 | Q87: 6.5648608 | R87: 6.2618672
A88: E06000015 | B88: Derby | E88: 2408 | G88: 2314 | H88: 1145 | I88: 259 | J88: 1169 | L88: 27 | M88: 27 | N88: 40 | P88: 106.6 | Q88: 10.741088 | R88: 10.966229
A89: E07000035 | B89: Derbyshire Dales | E89: 224 | G89: 217 | H89: 141 | I89: 23 | J89: 76 | L89: 6 | M89: 1 | N89: 0 | P89: 33.591 | Q89: 4.1975529 | R89: 2.2625108
A90: E08000017 | B90: Doncaster | E90: 2371 | G90: 2364 | H90: 1437 | I90: 184 | J90: 927 | L90: 2 | M90: 4 | N90: 1 | P90: 136.807 | Q90: 10.503848 | R90: 6.7759691
A91: E06000059 | B91: Dorset | E91: 2614 | G91: 1550 | H91: 1139 | I91: 263 | J91: 411 | L91: 70 | M91: 990 | N91: 4 | P91: 176.152 | Q91: 6.4660066 | R91: 2.3332122
A92: E07000108 | B92: Dover | E92: 679 | G92: 501 | H92: 170 | I92: 85 | J92: 331 | L92: 99 | M92: 73 | N92: 6 | P92: 55.86 | Q92: 3.0433226 | R92: 5.9255281
A93: E08000027 | B93: Dudley | E93: 4698 | G93: 2366 | H93: 489 | I93: 150 | J93: 1877 | L93: 1458 | M93: 841 | N93: 33 | P93: 138.595 | Q93: 3.5282658 | R93: 13.543057
A94: E06000047 | B94: Durham | E94: 3781 | G94: 3769 | H94: 1585 | I94: 240 | J94: 2184 | L94: 1 | M94: 6 | N94: 5 | P94: 241.547 | Q94: 6.5618699 | R94: 9.0417186
A95: E09000009 | B95: Ealing | E95: 3159 | G95: 3059 | H95: 1560 | I95: 239 | J95: 1499 | L95: 24 | M95: 6 | N95: 70 | P95: 124.298 | Q95: 12.550484 | R95: 12.059727
... A101: E06000011 | B101: East Riding of Yorkshire | E101: 1221 | G101: 1185 | H101: 271 | I101: 148 | J101: 914 | L101: 36 | M101: 0 | N101: 0 | P101: 154.139 | Q101: 1.7581534 | R101: 5.9297128
A102: E07000193 | B102: East Staffordshire | E102: .. | G102: .. | H102: .. | I102: .. | J102: .. | L102: .. | M102: .. | N102: .. | P102: 53.003 | Q102: .. | R102: ..
A103: E07000244 | B103: East Suffolk | E103: 1242 | G103: 1221 | H103: 693 | I103: 167 | J103: 528 | L103: 5 | M103: 12 | N103: 4 | P103: 116.542 | Q103: 5.9463541 | R103: 4.5305555
A104: E07000061 | B104: Eastbourne | E104: 791 | G104: 737 | H104: 298 | I104: 46 | J104: 439 | L104: 36 | M104: 14 | N104: 4 | P104: 48.589 | Q104: 6.1330754 | R104: 9.0349668
A105: E07000086 | B105: Eastleigh | E105: 341 | G105: 335 | H105: 213 | I105: 19 | J105: 122 | L105: 1 | M105: 4 | N105: 1 | P105: 58.877 | Q105: 3.6177115 | R105: 2.0721164
A106: E07000207 | B106: Elmbridge | E106: 364 | G106: 357 | H106: 228 | I106: 37 | J106: 129 | L106: 4 | M106: 2 | N106: 1 | P106: 56.263 | Q106: 4.0523968 | R106: 2.2928034
A107: E09000010 | B107: Enfield | E107: 2405 | G107: 2268 | H107: 823 | I107: 227 | J107: 1445 | L107: 22 | M107: 77 | N107: 38 | P107: 133.082 | Q107: 6.1841571 | R107: 10.857967
A108: E07000072 | B108: Epping Forest | E108: .. | G108: .. | H108: .. | I108: .. | J108: .. | L108: .. | M108: .. | N108: .. | P108: 56.041 | Q108: .. | R108: ..
A109: E07000208 | B109: Epsom & Ewell | E109: 218 | G109: 210 | H109: 97 | I109: 40 | J109: 113 | L109: 2 | M109: 4 | N109: 2 | P109: 32.195 | Q109: 3.0128902 | R109: 3.5098618
A110: E07000036 | B110: Erewash | E110: 590 | G110: 584 | H110: 288 | I110: 34 | J110: 296 | L110: 4 | M110: 2 | N110: 0 | P110: 52.619 | Q110: 5.4733081 | R110: 5.6253445
A111: E07000041 | B111: Exeter | E111: 1003 | G111: 971 | H111: 432 | I111: 75 | J111: 539 | L111: 27 | M111: 5 | N111: 0 | P111: 56.57 | Q111: 7.6365565 | R111: 9.5280184
A112: E07000087 | B112: Fareham | E112: 358 | G112: 350 | H112: 147 | I112: 38 | J112: 203 | L112: 4 | M112: 4 | N112: 0 | P112: 51.048 | Q112: 2.8796427 | R112: 3.9766494
A113: E07000010 | B113: Fenland | E113: 630 | G113: 470 | H113: 192 | I113: 46 | J113: 278 | L113: 94 | M113: 34 | N113: 32 | P113: 46.482 | Q113: 4.1306312 | R113: 5.9808098
A114: E07000112 | B114: Folkestone & Hythe | E114: 615 | G114: 572 | H114: 308 | I114: 161 | J114: 264 | L114: 9 | M114: 33 | N114: 1 | P114: 54.909 | Q114: 5.6092808 | R114: 4.807955
A115: E07000080 | B115: Forest of Dean | E115: 360 | G115: 331 | H115: 199 | I115: 46 | J115: 132 | L115: 17 | M115: 12 | N115: 0 | P115: 38.744 | Q115: 5.1362792 | R115: 3.4069791
A116: E07000119 | B116: Fylde | E116: 302 | G116: 298 | H116: 122 | I116: 63 | J116: 176 | L116: 2 | M116: 1 | N116: 1 | P116: 41.049 | Q116: 2.9720578 | R116: 4.2875588
A117: E08000037 | B117: Gateshead | E117: 1535 | G117: 1477 | H117: 972 | I117: 133 | J117: 505 | L117: 53 | M117: 4 | N117: 1 | P117: 91.243 | Q117: 10.652872 | R117: 5.5346712
A118: E07000173 | B118: Gedling | E118: 361 | G118: 359 | H118: 195 | I118: 30 | J118: 164 | L118: 0 | M118: 0 | N118: 2 | P118: 54.35 | Q118: 3.5878565 | R118: 3.0174793
A119: E07000081 | B119: Gloucester | E119: 1311 | G119: 1300 | H119: 614 | I119: 102 | J119: 686 | L119: 7 | M119: 4 | N119: 0 | P119: 55.771 | Q119: 11.009306 | R119: 12.300299
A120: E07000088 | B120: Gosport | E120: 513 | G120: 508 | H120: 365 | I120: 40 | J120: 143 | L120: 2 | M120: 3 | N120: 0 | P120: 37.897 | Q120: 9.6313692 | R120: 3.7733858
... A136: E09000016 | B136: Havering | E136: 2285 | G136: 2039 | H136: 1061 | I136: 187 | J136: 978 | L136: 176 | M136: 47 | N136: 23 | P136: 109.066 | Q136: 9.7280546 | R136: 8.9670475
A137: E06000019 | B137: Herefordshire | E137: .. | G137: .. | H137: .. | I137: .. | J137: .. | L137: .. | M137: .. | N137: .. | P137: 87.956 | Q137: .. | R137: ..
A138: E07000098 | B138: Hertsmere | E138: 530 | G138: 524 | H138: 351 | I138: 25 | J138: 173 | L138: 5 | M138: 1 | N138: 0 | P138: 42.576 | Q138: 8.2440812 | R138: 4.0633221
A139: E07000037 | B139: High Peak | E139: 336 | G139: 327 | H139: 154 | I139: 85 | J139: 173 | L139: 4 | M139: 5 | N139: 0 | P139: 42.959 | Q139: 3.5848134 | R139: 4.0270956
A140: E09000017 | B140: Hillingdon | E140: 2175 | G140: 2098 | H140: 739 | I140: 174 | J140: 1359 | L140: 23 | M140: 49 | N140: 5 | P140: 113.74 | Q140: 6.4972745 | R140: 11.948303
A141: E07000132 | B141: Hinckley & Bosworth | E141: 617 | G141: 612 | H141: 149 | I141: 19 | J141: 463 | L141: 3 | M141: 0 | N141: 2 | P141: 54.205 | Q141: 2.7488239 | R141: 8.5416474
A142: E07000227 | B142: Horsham | E142: 430 | G142: 425 | H142: 223 | I142: 6 | J142: 202 | L142: 1 | M142: 0 | N142: 4 | P142: 65.507 | Q142: 3.4042163 | R142: 3.0836399
A143: E09000018 | B143: Hounslow | E143: 2444 | G143: 2314 | H143: 774 | I143: 239 | J143: 1540 | L143: 80 | M143: 3 | N143: 47 | P143: 103.324 | Q143: 7.4909992 | R143: 14.904572
A144: E07000011 | B144: Huntingdonshire | E144: 871 | G144: 865 | H144: 586 | I144: 76 | J144: 279 | L144: 4 | M144: 1 | N144: 1 | P144: 77.79 | Q144: 7.5331019 | R144: 3.5865793
A145: E07000120 | B145: Hyndburn | E145: 407 | G145: 407 | H145: 151 | I145: 68 | J145: 256 | L145: 0 | M145: 0 | N145: 0 | P145: 35.95 | Q145: 4.2002782 | R145: 7.1210014
A146: E07000202 | B146: Ipswich | E146: 2075 | G146: 1549 | H146: 1010 | I146: 108 | J146: 539 | L146: 163 | M146: 321 | N146: 42 | P146: 59.135 | Q146: 17.079564 | R146: 9.1147375
A147: E06000046 | B147: Isle of Wight | E147: 1202 | G147: 768 | H147: 433 | I147: 49 | J147: 335 | L147: 161 | M147: 261 | N147: 12 | P147: 68.821 | Q147: 6.2916842 | R147: 4.8677003
A148: E06000053 | B148: Isles of Scilly | E148: 7 | G148: 5 | H148: 5 | I148: 0 | J148: 0 | L148: 0 | M148: 1 | N148: 1 | P148: 0.779 | Q148: 6.4184852 | R148: 0
A149: E09000019 | B149: Islington | E149: 3084 | G149: 2959 | H149: 680 | I149: 45 | J149: 2279 | L149: 38 | M149: 33 | N149: 54 | P149: 110.076 | Q149: 6.1775501 | R149: 20.703877
... A152: E06000010 | B152: Kingston upon Hull | E152: 3805 | G152: 3462 | H152: 1590 | I152: 312 | J152: 1872 | L152: 202 | M152: 116 | N152: 25 | P152: 113.818 | Q152: 13.969671 | R152: 16.447311
A153: E09000021 | B153: Kingston upon Thames | E153: .. | G153: .. | H153: .. | I153: .. | J153: .. | L153: .. | M153: .. | N153: .. | P153: 71.18 | Q153: .. | R153: ..
A154: E08000034 | B154: Kirklees | E154: 1924 | G154: 1902 | H154: 1169 | I154: 172 | J154: 733 | L154: 17 | M154: 2 | N154: 3 | P154: 185.604 | Q154: 6.2983556 | R154: 3.9492683
...

Sheet A2P
A1: Table A2P - Number of households owed a prevention duty by reason for loss, or threat of loss, of last settled home England, April 2024 to March 2025
G2: End of private rented tenancy - assured shorthold | AA2: End of private rented tenancy - not assured shorthold | AB2: Family or friends no longer willing or able to accommodate | AC2: Non-violent relationship breakdown with partner | AE2: Domestic abuse | AJ2: Other violence or harrassment | AL2: End of social rented tenancy | AQ2: Eviction from supported housing | AV2: Left institution with no accommodation available | BC2: Required to leave accommodation provided by Home Office as asylum support | BD2: Home no longer suitable - disability / ill health | BF2: Other reasons / not known6
BF3: Number of households
E4: Total owed a prevention duty1 | G4: End of assured shorthold (AST) private rented tenancy, due to: | AA4: End of non-AST private rented tenancy | AB4: Family or friends no longer willing or able to accommodate | AC4: Non-violent relationship breakdown with partner | AE4: Domestic abuse | AJ4: Other violence or harrassment | AL4: End of social rented tenancy, due to: | AQ4: Eviction from supported housing, due to: | AV4: Departure from institution : | BC4: Required to leave accommodation provided by Home Office as asylum support | BD4: Home no longer suitable - disability / ill health 6 | BE4: Loss of placement or sponsorship provided through a resettlement scheme | BF4: Other reasons / not known5
G5: Total end of AST | I5: Of which: | Q5: Landlord wishing to sell or re-let the property | AE5: Total Domestic abuse | AF5: Of which: | AL5: Total end of social rented tenancy | AM5: Of which: | AQ5: Total evicted from supported housing | AR5: Of which: | AV5: Total Departure from institution | AW5: Of which:
I6: Rent arrears, due to: | R6: Of which:
I7: Tenant difficulty budgeting or making other payment(s) | J7: Increase | K7: Reduction in employment income | L7: Changes | M7: Change in personal circumstances | O7: Breach of tenancy, not related to rent arrears | Q7: Total Landlord wishing to sell or re-let the property | R7: sell the property | S7: re-let the property | T7: Retired "Landlord wishing to" option | V7: Tenant complained to the council / agent / landlord about disrepair | W7: Illegal eviction | X7: Tenant abandoned property | Y7: Other reasons / not known | AF7: Victim | AG7: Alleged perpetrator | AH7: Retired "Domestic abuse" option | AM7: Rent arrears2 | AN7: Breach of tenancy, not related to rent arrears | AO7: Other reasons / not known3 | AR7: Rent arrears | AS7: Breach of tenancy or licence, not related to rent arrears | AT7: Other reasons / not known4 | AW7: Custody | AX7: Hospital (psychiatric) | AY7: Hospital (general) | AZ7: Looked After Child Placement | BA7: Retired "Left institution" option
J8: in rent | L8: in benefit entitlement | S8: re-let the property | T8: Retired "Landlord wishing to" option
A9: E92000001 | B9: ENGLAND | E9: 147870 | G9: 57190 | I9: 2370 | J9: 1370 | K9: 940 | L9: 860 | M9: 2500 | O9: 810 | Q9: 37000 | R9: 26440 | S9: 10490 | T9: 70 | V9: 760 | W9: 280 | X9: 290 | Y9: 10020 | AA9: 6010 | AB9: 34980 | AC9: 5890 | AE9: 10610 | AF9: 9990 | AG9: 610 | AH9: 0 | AJ9: 1630 | AL9: 7350 | AM9: 5060 | AN9: 560 | AO9: 1720 | AQ9: 5550 | AR9: 670 | AS9: 1490 | AT9: 3390 | AV9: 4510 | AW9: 3100 | AX9: 240 | AY9: 180 | AZ9: 980 | BA9: 0 | BC9: 4920 | BD9: 2310 | BE9: 800 | BF9: 6110
A10: E12000007 | B10: London | E10: 28240 | G10: 12670 | I10: 430 | J10: 490 | K10: 150 | L10: 510 | M10: 380 | O10: 120 | Q10: 7640 | R10: 4130 | S10: 3450 | T10: 50 | V10: 160 | W10: 70 | X10: 30 | Y10: 2680 | AA10: 1310 | AB10: 6950 | AC10: 410 | AE10: 1240 | AF10: 1170 | AG10: 70 | AH10: 0 | AJ10: 330 | AL10: 1700 | AM10: 1410 | AN10: 40 | AO10: 250 | AQ10: 800 | AR10: 80 | AS10: 100 | AT10: 620 | AV10: 490 | AW10: 320 | AX10: 30 | AY10: 40 | AZ10: 100 | BA10: 0 | BC10: 450 | BD10: 710 | BE10: 90 | BF10: 1090
A11: - | B11: Rest of England | E11: 119630 | G11: 44520 | I11: 1940 | J11: 880 | K11: 780 | L11: 350 | M11: 2120 | O11: 690 | Q11: 29360 | R11: 22300 | S11: 7040 | T11: 20 | V11: 600 | W11: 210 | X11: 260 | Y11: 7340 | AA11: 4700 | AB11: 28040 | AC11: 5480 | AE11: 9370 | AF11: 8820 | AG11: 540 | AH11: 0 | AJ11: 1300 | AL11: 5650 | AM11: 3650 | AN11: 520 | AO11: 1470 | AQ11: 4750 | AR11: 590 | AS11: 1390 | AT11: 2770 | AV11: 4020 | AW11: 2780 | AX11: 220 | AY11: 140 | AZ11: 880 | BA11: 0 | BC11: 4470 | BD11: 1600 | BE11: 720 | BF11: 5020
A13: E12000001 | B13: North East | E13: 8930 | G13: 2890 | I13: 170 | J13: 40 | K13: 20 | L13: 10 | M13: 110 | O13: 40 | Q13: 1930 | R13: 1590 | S13: 340 | T13: 0 | V13: 30 | W13: 30 | X13: 20 | Y13: 500 | AA13: 170 | AB13: 2010 | AC13: 540 | AE13: 880 | AF13: 850 | AG13: 30 | AH13: 0 | AJ13: 190 | AL13: 410 | AM13: 220 | AN13: 50 | AO13: 140 | AQ13: 360 | AR13: 30 | AS13: 100 | AT13: 230 | AV13: 430 | AW13: 350 | AX13: 40 | AY13: 10 | AZ13: 30 | BA13: 0 | BC13: 470 | BD13: 80 | BE13: 20 | BF13: 490
A14: E12000002 | B14: North West | E14: 20570 | G14: 7980 | I14: 300 | J14: 200 | K14: 80 | L14: 50 | M14: 390 | O14: 110 | Q14: 5360 | R14: 4330 | S14: 1030 | T14: 0 | V14: 120 | W14: 30 | X14: 30 | Y14: 1310 | AA14: 740 | AB14: 4340 | AC14: 860 | AE14: 1770 | AF14: 1690 | AG14: 90 | AH14: 0 | AJ14: 150 | AL14: 1000 | AM14: 770 | AN14: 80 | AO14: 160 | AQ14: 480 | AR14: 50 | AS14: 150 | AT14: 290 | AV14: 850 | AW14: 580 | AX14: 40 | AY14: 30 | AZ14: 200 | BA14: 0 | BC14: 1220 | BD14: 260 | BE14: 50 | BF14: 860
A15: E12000003 | B15: Yorkshire and The Humber | E15: 15100 | G15: 4490 | I15: 270 | J15: 80 | K15: 100 | L15: 50 | M15: 240 | O15: 90 | Q15: 2730 | R15: 2200 | S15: 510 | T15: 20 | V15: 110 | W15: 30 | X15: 60 | Y15: 740 | AA15: 430 | AB15: 4240 | AC15: 730 | AE15: 1820 | AF15: 1730 | AG15: 90 | AH15: 0 | AJ15: 200 | AL15: 390 | AM15: 140 | AN15: 50 | AO15: 200 | AQ15: 660 | AR15: 50 | AS15: 190 | AT15: 420 | AV15: 700 | AW15: 590 | AX15: 20 | AY15: 20 | AZ15: 70 | BA15: 0 | BC15: 760 | BD15: 170 | BE15: 10 | BF15: 490
A16: E12000004 | B16: East Midlands | E16: 10800 | G16: 4760 | I16: 240 | J16: 90 | K16: 100 | L16: 40 | M16: 220 | O16: 70 | Q16: 3060 | R16: 2460 | S16: 600 | T16: 0 | V16: 80 | W16: 20 | X16: 30 | Y16: 830 | AA16: 270 | AB16: 2380 | AC16: 490 | AE16: 680 | AF16: 640 | AG16: 40 | AH16: 0 | AJ16: 100 | AL16: 410 | AM16: 210 | AN16: 40 | AO16: 160 | AQ16: 570 | AR16: 60 | AS16: 140 | AT16: 370 | AV16: 200 | AW16: 150 | AX16: 10 | AY16: 0 | AZ16: 30 | BA16: 0 | BC16: 470 | BD16: 100 | BE16: 40 | BF16: 320
A17: E12000005 | B17: West Midlands | E17: 11810 | G17: 3990 | I17: 100 | J17: 90 | K17: 70 | L17: 30 | M17: 190 | O17: 30 | Q17: 2580 | R17: 2050 | S17: 530 | T17: 0 | V17: 60 | W17: 20 | X17: 20 | Y17: 800 | AA17: 550 | AB17: 2800 | AC17: 430 | AE17: 880 | AF17: 840 | AG17: 40 | AH17: 0 | AJ17: 170 | AL17: 660 | AM17: 430 | AN17: 60 | AO17: 170 | AQ17: 780 | AR17: 70 | AS17: 270 | AT17: 430 | AV17: 430 | AW17: 180 | AX17: 20 | AY17: 30 | AZ17: 200 | BA17: 0 | BC17: 430 | BD17: 150 | BE17: 60 | BF17: 480
A18: E12000006 | B18: East of England | E18: 15450 | G18: 5790 | I18: 240 | J18: 110 | K18: 110 | L18: 40 | M18: 260 | O18: 70 | Q18: 4000 | R18: 3040 | S18: 960 | T18: 0 | V18: 60 | W18: 20 | X18: 20 | Y18: 870 | AA18: 730 | AB18: 3680 | AC18: 710 | AE18: 1120 | AF18: 1040 | AG18: 80 | AH18: 0 | AJ18: 170 | AL18: 1020 | AM18: 720 | AN18: 70 | AO18: 230 | AQ18: 600 | AR18: 80 | AS18: 110 | AT18: 410 | AV18: 410 | AW18: 260 | AX18: 20 | AY18: 20 | AZ18: 120 | BA18: 0 | BC18: 310 | BD18: 270 | BE18: 90 | BF18: 540
A19: E12000007 | B19: London | E19: 28240 | G19: 12670 | I19: 430 | J19: 490 | K19: 150 | L19: 510 | M19: 380 | O19: 120 | Q19: 7640 | R19: 4130 | S19: 3450 | T19: 50 | V19: 160 | W19: 70 | X19: 30 | Y19: 2680 | AA19: 1310 | AB19: 6950 | AC19: 410 | AE19: 1240 | AF19: 1170 | AG19: 70 | AH19: 0 | AJ19: 330 | AL19: 1700 | AM19: 1410 | AN19: 40 | AO19: 250 | AQ19: 800 | AR19: 80 | AS19: 100 | AT19: 620 | AV19: 490 | AW19: 320 | AX19: 30 | AY19: 40 | AZ19: 100 | BA19: 0 | BC19: 450 | BD19: 710 | BE19: 90 | BF19: 1090
A20: E12000008 | B20: South East | E20: 23080 | G20: 9210 | I20: 460 | J20: 190 | K20: 210 | L20: 90 | M20: 490 | O20: 180 | Q20: 5980 | R20: 3830 | S20: 2140 | T20: 0 | V20: 100 | W20: 30 | X20: 50 | Y20: 1430 | AA20: 1160 | AB20: 5500 | AC20: 1090 | AE20: 1240 | AF20: 1130 | AG20: 110 | AH20: 0 | AJ20: 220 | AL20: 1090 | AM20: 770 | AN20: 110 | AO20: 220 | AQ20: 740 | AR20: 150 | AS20: 210 | AT20: 380 | AV20: 540 | AW20: 380 | AX20: 30 | AY20: 20 | AZ20: 110 | BA20: 0 | BC20: 520 | BD20: 360 | BE20: 270 | BF20: 1140
A21: E12000009 | B21: South West | E21: 13880 | G21: 5410 | I21: 170 | J21: 70 | K21: 90 | L21: 40 | M21: 220 | O21: 100 | Q21: 3720 | R21: 2790 | S21: 930 | T21: 0 | V21: 60 | W21: 30 | X21: 30 | Y21: 880 | AA21: 650 | AB21: 3080 | AC21: 620 | AE21: 980 | AF21: 910 | AG21: 70 | AH21: 0 | AJ21: 100 | AL21: 650 | AM21: 390 | AN21: 60 | AO21: 200 | AQ21: 560 | AR21: 100 | AS21: 220 | AT21: 250 | AV21: 440 | AW21: 270 | AX21: 30 | AY21: 20 | AZ21: 120 | BA21: 0 | BC21: 290 | BD21: 200 | BE21: 170 | BF21: 700
... A49: E07000143 | B49: Breckland | E49: 199 | G49: 91 | I49: 4 | J49: 0 | K49: 0 | L49: 1 | M49: 2 | O49: 2 | Q49: 70 | R49: 60 | S49: 10 | T49: 0 | V49: 0 | W49: 0 | X49: 2 | Y49: 10 | AA49: 1 | AB49: 43 | AC49: 5 | AE49: 12 | AF49: 11 | AG49: 1 | AH49: 0 | AJ49: 1 | AL49: 8 | AM49: 8 | AN49: 0 | AO49: 0 | AQ49: 8 | AR49: 2 | AS49: 5 | AT49: 1 | AV49: 3 | AW49: 3 | AX49: 0 | AY49: 0 | AZ49: 0 | BA49: 0 | BC49: 0 | BD49: 12 | BE49: 5 | BF49: 10
A50: E09000005 | B50: Brent | E50: .. | G50: .. | I50: .. | J50: .. | K50: .. | L50: .. | M50: .. | O50: .. | Q50: .. | R50: .. | S50: .. | T50: .. | V50: .. | W50: .. | X50: .. | Y50: .. | AA50: .. | AB50: .. | AC50: .. | AE50: .. | AF50: .. | AG50: .. | AH50: .. | AJ50: .. | AL50: .. | AM50: .. | AN50: .. | AO50: .. | AQ50: .. | AR50: .. | AS50: .. | AT50: .. | AV50: .. | AW50: .. | AX50: .. | AY50: .. | AZ50: .. | BA50: .. | BC50: .. | BD50: .. | BE50: .. | BF50: ..
A51: E07000068 | B51: Brentwood | E51: 111 | G51: 49 | I51: 0 | J51: 0 | K51: 0 | L51: 0 | M51: 3 | O51: 0 | Q51: 41 | R51: 28 | S51: 13 | T51: 0 | V51: 1 | W51: 0 | X51: 0 | Y51: 4 | AA51: 13 | AB51: 20 | AC51: 7 | AE51: 8 | AF51: 6 | AG51: 2 | AH51: 0 | AJ51: 0 | AL51: 1 | AM51: 1 | AN51: 0 | AO51: 0 | AQ51: 2 | AR51: 0 | AS51: 0 | AT51: 2 | AV51: 2 | AW51: 2 | AX51: 0 | AY51: 0 | AZ51: 0 | BA51: 0 | BC51: 0 | BD51: 3 | BE51: 1 | BF51: 5
A52: E06000043 | B52: Brighton & Hove | E52: 403 | G52: 192 | I52: 17 | J52: 19 | K52: 4 | L52: 8 | M52: 5 | O52: 14 | Q52: 90 | R52: 64 | S52: 25 | T52: 1 | V52: 4 | W52: 1 | X52: 0 | Y52: 30 | AA52: 24 | AB52: 51 | AC52: 7 | AE52: 10 | AF52: 10 | AG52: 0 | AH52: 0 | AJ52: 15 | AL52: 5 | AM52: 0 | AN52: 1 | AO52: 4 | AQ52: 32 | AR52: 0 | AS52: 7 | AT52: 25 | AV52: 4 | AW52: 2 | AX52: 0 | AY52: 0 | AZ52: 2 | BA52: 0 | BC52: 24 | BD52: 6 | BE52: 6 | BF52: 27
A53: E06000023 | B53: Bristol | E53: 897 | G53: 290 | I53: 23 | J53: 10 | K53: 2 | L53: 7 | M53: 7 | O53: 5 | Q53: 162 | R53: 117 | S53: 45 | T53: 0 | V53: 4 | W53: 5 | X53: 2 | Y53: 63 | AA53: 34 | AB53: 193 | AC53: 22 | AE53: 33 | AF53: 25 | AG53: 8 | AH53: 0 | AJ53: 8 | AL53: 147 | AM53: 130 | AN53: 6 | AO53: 11 | AQ53: 50 | AR53: 10 | AS53: 28 | AT53: 12 | AV53: 51 | AW53: 47 | AX53: 0 | AY53: 0 | AZ53: 4 | BA53: 0 | BC53: 26 | BD53: 2 | BE53: 2 | BF53: 39
A54: E07000144 | B54: Broadland | E54: 156 | G54: 71 | I54: 0 | J54: 0 | K54: 0 | L54: 0 | M54: 2 | O54: 0 | Q54: 62 | R54: 46 | S54: 16 | T54: 0 | V54: 0 | W54: 0 | X54: 0 | Y54: 7 | AA54: 6 | AB54: 47 | AC54: 10 | AE54: 1 | AF54: 1 | AG54: 0 | AH54: 0 | AJ54: 0 | AL54: 4 | AM54: 2 | AN54: 2 | AO54: 0 | AQ54: 3 | AR54: 0 | AS54: 0 | AT54: 3 | AV54: 10 | AW54: 0 | AX54: 0 | AY54: 0 | AZ54: 10 | BA54: 0 | BC54: 1 | BD54: 0 | BE54: 1 | BF54: 2
A55: E09000006 | B55: Bromley | E55: 577 | G55: 300 | I55: 18 | J55: 6 | K55: 11 | L55: 2 | M55: 5 | O55: 2 | Q55: 213 | R55: 139 | S55: 74 | T55: 0 | V55: 3 | W55: 2 | X55: 1 | Y55: 37 | AA55: 12 | AB55: 163 | AC55: 12 | AE55: 19 | AF55: 19 | AG55: 0 | AH55: 0 | AJ55: 12 | AL55: 25 | AM55: 19 | AN55: 0 | AO55: 6 | AQ55: 2 | AR55: 2 | AS55: 0 | AT55: 0 | AV55: 3 | AW55: 3 | AX55: 0 | AY55: 0 | AZ55: 0 | BA55: 0 | BC55: 0 | BD55: 11 | BE55: 4 | BF55: 14
A56: E07000234 | B56: Bromsgrove | E56: 183 | G56: 37 | I56: 0 | J56: 1 | K56: 1 | L56: 0 | M56: 2 | O56: 0 | Q56: 25 | R56: 21 | S56: 4 | T56: 0 | V56: 1 | W56: 1 | X56: 0 | Y56: 6 | AA56: 17 | AB56: 72 | AC56: 7 | AE56: 24 | AF56: 23 | AG56: 1 | AH56: 0 | AJ56: 4 | AL56: 3 | AM56: 0 | AN56: 1 | AO56: 2 | AQ56: 1 | AR56: 0 | AS56: 0 | AT56: 1 | AV56: 5 | AW56: 2 | AX56: 0 | AY56: 0 | AZ56: 3 | BA56: 0 | BC56: 0 | BD56: 5 | BE56: 0 | BF56: 8
A57: E07000095 | B57: Broxbourne | E57: 240 | G57: 100 | I57: 4 | J57: 5 | K57: 2 | L57: 0 | M57: 1 | O57: 1 | Q57: 65 | R57: 45 | S57: 20 | T57: 0 | V57: 0 | W57: 1 | X57: 0 | Y57: 21 | AA57: 18 | AB57: 63 | AC57: 5 | AE57: 11 | AF57: 10 | AG57: 1 | AH57: 0 | AJ57: 1 | AL57: 12 | AM57: 8 | AN57: 0 | AO57: 4 | AQ57: 2 | AR57: 1 | AS57: 0 | AT57: 1 | AV57: 4 | AW57: 2 | AX57: 1 | AY57: 1 | AZ57: 0 | BA57: 0 | BC57: 8 | BD57: 7 | BE57: 0 | BF57: 9
A58: E07000172 | B58: Broxtowe | E58: 133 | G58: 70 | I58: 1 | J58: 1 | K58: 0 | L58: 0 | M58: 1 | O58: 0 | Q58: 57 | R58: 8 | S58: 49 | T58: 0 | V58: 2 | W58: 1 | X58: 0 | Y58: 7 | AA58: 2 | AB58: 30 | AC58: 6 | AE58: 10 | AF58: 9 | AG58: 1 | AH58: 0 | AJ58: 2 | AL58: 1 | AM58: 0 | AN58: 0 | AO58: 1 | AQ58: 2 | AR58: 0 | AS58: 1 | AT58: 1 | AV58: 1 | AW58: 0 | AX58: 0 | AY58: 0 | AZ58: 1 | BA58: 0 | BC58: 5 | BD58: 0 | BE58: 0 | BF58: 4
A59: E06000060 | B59: Buckinghamshire | E59: 1777 | G59: 564 | I59: 37 | J59: 18 | K59: 17 | L59: 10 | M59: 43 | O59: 5 | Q59: 341 | R59: 238 | S59: 103 | T59: 0 | V59: 5 | W59: 5 | X59: 5 | Y59: 78 | AA59: 100 | AB59: 452 | AC59: 92 | AE59: 119 | AF59: 104 | AG59: 15 | AH59: 0 | AJ59: 32 | AL59: 144 | AM59: 113 | AN59: 13 | AO59: 18 | AQ59: 44 | AR59: 14 | AS59: 12 | AT59: 18 | AV59: 52 | AW59: 42 | AX59: 3 | AY59: 3 | AZ59: 4 | BA59: 0 | BC59: 7 | BD59: 43 | BE59: 17 | BF59: 111
A60: E07000117 | B60: Burnley | E60: 292 | G60: 141 | I60: 10 | J60: 4 | K60: 1 | L60: 2 | M60: 4 | O60: 3 | Q60: 85 | R60: 72 | S60: 13 | T60: 0 | V60: 2 | W60: 0 | X60: 0 | Y60: 30 | AA60: 13 | AB60: 55 | AC60: 13 | AE60: 9 | AF60: 9 | AG60: 0 | AH60: 0 | AJ60: 3 | AL60: 5 | AM60: 0 | AN60: 2 | AO60: 3 | AQ60: 9 | AR60: 0 | AS60: 3 | AT60: 6 | AV60: 1 | AW60: 0 | AX60: 0 | AY60: 0 | AZ60: 1 | BA60: 0 | BC60: 24 | BD60: 3 | BE60: 1 | BF60: 15
A61: E08000002 | B61: Bury | E61: .. | G61: .. | I61: .. | J61: .. | K61: .. | L61: .. | M61: .. | O61: .. | Q61: .. | R61: .. | S61: .. | T61: .. | V61: .. | W61: .. | X61: .. | Y61: .. | AA61: .. | AB61: .. | AC61: .. | AE61: .. | AF61: .. | AG61: .. | AH61: .. | AJ61: .. | AL61: .. | AM61: .. | AN61: .. | AO61: .. | AQ61: .. | AR61: .. | AS61: .. | AT61: .. | AV61: .. | AW61: .. | AX61: .. | AY61: .. | AZ61: .. | BA61: .. | BC61: .. | BD61: .. | BE61: .. | BF61: ..
A62: E08000033 | B62: Calderdale | E62: 887 | G62: 193 | I62: 13 | J62: 2 | K62: 3 | L62: 1 | M62: 12 | O62: 9 | Q62: 118 | R62: 99 | S62: 19 | T62: 0 | V62: 4 | W62: 3 | X62: 5 | Y62: 23 | AA62: 39 | AB62: 224 | AC62: 39 | AE62: 74 | AF62: 65 | AG62: 9 | AH62: 0 | AJ62: 4 | AL62: 19 | AM62: 8 | AN62: 1 | AO62: 10 | AQ62: 36 | AR62: 3 | AS62: 14 | AT62: 19 | AV62: 88 | AW62: 59 | AX62: 1 | AY62: 1 | AZ62: 27 | BA62: 0 | BC62: 70 | BD62: 48 | BE62: 1 | BF62: 52
A63: E07000008 | B63: Cambridge | E63: 285 | G63: 73 | I63: 3 | J63: 1 | K63: 0 | L63: 1 | M63: 4 | O63: 2 | Q63: 42 | R63: 28 | S63: 14 | T63: 0 | V63: 1 | W63: 1 | X63: 0 | Y63: 18 | AA63: 19 | AB63: 81 | AC63: 10 | AE63: 15 | AF63: 14 | AG63: 1 | AH63: 0 | AJ63: 1 | AL63: 22 | AM63: 7 | AN63: 2 | AO63: 13 | AQ63: 16 | AR63: 2 | AS63: 5 | AT63: 9 | AV63: 24 | AW63: 7 | AX63: 1 | AY63: 0 | AZ63: 16 | BA63: 0 | BC63: 0 | BD63: 3 | BE63: 2 | BF63: 19
A64: E09000007 | B64: Camden | E64: .. | G64: .. | I64: .. | J64: .. | K64: .. | L64: .. | M64: .. | O64: .. | Q64: .. | R64: .. | S64: .. | T64: .. | V64: .. | W64: .. | X64: .. | Y64: .. | AA64: .. | AB64: .. | AC64: .. | AE64: .. | AF64: .. | AG64: .. | AH64: .. | AJ64: .. | AL64: .. | AM64: .. | AN64: .. | AO64: .. | AQ64: .. | AR64: .. | AS64: .. | AT64: .. | AV64: .. | AW64: .. | AX64: .. | AY64: .. | AZ64: .. | BA64: .. | BC64: .. | BD64: .. | BE64: .. | BF64: ..
A65: E07000192 | B65: Cannock Chase | E65: 65 | G65: 34 | I65: 0 | J65: 0 | K65: 1 | L65: 0 | M65: 1 | O65: 0 | Q65: 29 | R65: 27 | S65: 2 | T65: 0 | V65: 0 | W65: 0 | X65: 0 | Y65: 3 | AA65: 3 | AB65: 16 | AC65: 2 | AE65: 4 | AF65: 4 | AG65: 0 | AH65: 0 | AJ65: 0 | AL65: 2 | AM65: 1 | AN65: 0 | AO65: 1 | AQ65: 1 | AR65: 0 | AS65: 0 | AT65: 1 | AV65: 1 | AW65: 1 | AX65: 0 | AY65: 0 | AZ65: 0 | BA65: 0 | BC65: 1 | BD65: 1 | BE65: 0 | BF65: 0
A66: E07000106 | B66: Canterbury | E66: .. | G66: .. | I66: .. | J66: .. | K66: .. | L66: .. | M66: .. | O66: .. | Q66: .. | R66: .. | S66: .. | T66: .. | V66: .. | W66: .. | X66: .. | Y66: .. | AA66: .. | AB66: .. | AC66: .. | AE66: .. | AF66: .. | AG66: .. | AH66: .. | AJ66: .. | AL66: .. | AM66: .. | AN66: .. | AO66: .. | AQ66: .. | AR66: .. | AS66: .. | AT66: .. | AV66: .. | AW66: .. | AX66: .. | AY66: .. | AZ66: .. | BA66: .. | BC66: .. | BD66: .. | BE66: .. | BF66: ..
A67: E07000069 | B67: Castle Point | E67: 130 | G67: 89 | I67: 3 | J67: 0 | K67: 2 | L67: 0 | M67: 2 | O67: 0 | Q67: 71 | R67: 67 | S67: 4 | T67: 0 | V67: 0 | W67: 0 | X67: 1 | Y67: 10 | AA67: 0 | AB67: 26 | AC67: 3 | AE67: 6 | AF67: 4 | AG67: 2 | AH67: 0 | AJ67: 0 | AL67: 1 | AM67: 1 | AN67: 0 | AO67: 0 | AQ67: 0 | AR67: 0 | AS67: 0 | AT67: 0 | AV67: 0 | AW67: 0 | AX67: 0 | AY67: 0 | AZ67: 0 | BA67: 0 | BC67: 0 | BD67: 2 | BE67: 0 | BF67: 3
A68: E06000056 | B68: Central Bedfordshire | E68: 560 | G68: 196 | I68: 6 | J68: 3 | K68: 5 | L68: 1 | M68: 8 | O68: 0 | Q68: 149 | R68: 120 | S68: 29 | T68: 0 | V68: 1 | W68: 0 | X68: 0 | Y68: 23 | AA68: 37 | AB68: 120 | AC68: 50 | AE68: 88 | AF68: 81 | AG68: 7 | AH68: 0 | AJ68: 6 | AL68: 16 | AM68: 6 | AN68: 1 | AO68: 9 | AQ68: 7 | AR68: 0 | AS68: 0 | AT68: 7 | AV68: 3 | AW68: 1 | AX68: 0 | AY68: 0 | AZ68: 2 | BA68: 0 | BC68: 4 | BD68: 13 | BE68: 3 | BF68: 17
A69: E07000130 | B69: Charnwood | E69: 199 | G69: 97 | I69: 6 | J69: 0 | K69: 2 | L69: 0 | M69: 7 | O69: 0 | Q69: 74 | R69: 58 | S69: 16 | T69: 0 | V69: 1 | W69: 2 | X69: 1 | Y69: 4 | AA69: 4 | AB69: 51 | AC69: 14 | AE69: 8 | AF69: 8 | AG69: 0 | AH69: 0 | AJ69: 2 | AL69: 3 | AM69: 0 | AN69: 1 | AO69: 2 | AQ69: 2 | AR69: 0 | AS69: 0 | AT69: 2 | AV69: 1 | AW69: 1 | AX69: 0 | AY69: 0 | AZ69: 0 | BA69: 0 | BC69: 8 | BD69: 1 | BE69: 3 | BF69: 5
A70: E07000070 | B70: Chelmsford | E70: 400 | G70: 118 | I70: 5 | J70: 6 | K70: 1 | L70: 0 | M70: 3 | O70: 2 | Q70: 86 | R70: 62 | S70: 24 | T70: 0 | V70: 1 | W70: 2 | X70: 0 | Y70: 12 | AA70: 33 | AB70: 110 | AC70: 28 | AE70: 36 | AF70: 32 | AG70: 4 | AH70: 0 | AJ70: 6 | AL70: 15 | AM70: 8 | AN70: 3 | AO70: 4 | AQ70: 10 | AR70: 0 | AS70: 2 | AT70: 8 | AV70: 14 | AW70: 11 | AX70: 1 | AY70: 0 | AZ70: 2 | BA70: 0 | BC70: 6 | BD70: 9 | BE70: 0 | BF70: 15
A71: E07000078 | B71: Cheltenham | E71: 295 | G71: 126 | I71: 1 | J71: 0 | K71: 2 | L71: 1 | M71: 8 | O71: 5 | Q71: 81 | R71: 67 | S71: 14 | T71: 0 | V71: 1 | W71: 0 | X71: 1 | Y71: 26 | AA71: 8 | AB71: 66 | AC71: 0 | AE71: 57 | AF71: 57 | AG71: 0 | AH71: 0 | AJ71: 1 | AL71: 6 | AM71: 1 | AN71: 2 | AO71: 3 | AQ71: 13 | AR71: 1 | AS71: 9 | AT71: 3 | AV71: 1 | AW71: 0 | AX71: 0 | AY71: 0 | AZ71: 1 | BA71: 0 | BC71: 0 | BD71: 0 | BE71: 10 | BF71: 7
A72: E07000177 | B72: Cherwell | E72: 311 | G72: 174 | I72: 3 | J72: 4 | K72: 6 | L72: 1 | M72: 11 | O72: 3 | Q72: 117 | R72: 96 | S72: 21 | T72: 0 | V72: 0 | W72: 2 | X72: 1 | Y72: 26 | AA72: 7 | AB72: 49 | AC72: 10 | AE72: 9 | AF72: 8 | AG72: 1 | AH72: 0 | AJ72: 1 | AL72: 12 | AM72: 5 | AN72: 2 | AO72: 5 | AQ72: 7 | AR72: 0 | AS72: 6 | AT72: 1 | AV72: 2 | AW72: 2 | AX72: 0 | AY72: 0 | AZ72: 0 | BA72: 0 | BC72: 15 | BD72: 0 | BE72: 10 | BF72: 15
A73: E06000049 | B73: Cheshire East | E73: 1138 | G73: 453 | I73: 6 | J73: 3 | K73: 2 | L73: 0 | M73: 15 | O73: 6 | Q73: 362 | R73: 302 | S73: 60 | T73: 0 | V73: 2 | W73: 0 | X73: 0 | Y73: 57 | AA73: 32 | AB73: 229 | AC73: 36 | AE73: 48 | AF73: 41 | AG73: 7 | AH73: 0 | AJ73: 2 | AL73: 179 | AM73: 161 | AN73: 7 | AO73: 11 | AQ73: 63 | AR73: 3 | AS73: 13 | AT73: 47 | AV73: 38 | AW73: 16 | AX73: 1 | AY73: 2 | AZ73: 19 | BA73: 0 | BC73: 7 | BD73: 3 | BE73: 0 | BF73: 48
A74: E06000050 | B74: Cheshire West & Chester | E74: 924 | G74: 286 | I74: 18 | J74: 6 | K74: 5 | L74: 0 | M74: 4 | O74: 4 | Q74: 188 | R74: 166 | S74: 22 | T74: 0 | V74: 5 | W74: 3 | X74: 6 | Y74: 47 | AA74: 23 | AB74: 278 | AC74: 36 | AE74: 55 | AF74: 51 | AG74: 4 | AH74: 0 | AJ74: 6 | AL74: 32 | AM74: 16 | AN74: 5 | AO74: 11 | AQ74: 17 | AR74: 0 | AS74: 7 | AT74: 10 | AV74: 16 | AW74: 13 | AX74: 0 | AY74: 0 | AZ74: 3 | BA74: 0 | BC74: 102 | BD74: 12 | BE74: 11 | BF74: 50
A75: E07000034 | B75: Chesterfield | E75: 199 | G75: 93 | I75: 5 | J75: 0 | K75: 2 | L75: 1 | M75: 7 | O75: 3 | Q75: 70 | R75: 61 | S75: 9 | T75: 0 | V75: 0 | W75: 1 | X75: 1 | Y75: 3 | AA75: 6 | AB75: 54 | AC75: 12 | AE75: 5 | AF75: 4 | AG75: 1 | AH75: 0 | AJ75: 0 | AL75: 3 | AM75: 1 | AN75: 2 | AO75: 0 | AQ75: 15 | AR75: 2 | AS75: 5 | AT75: 8 | AV75: 2 | AW75: 2 | AX75: 0 | AY75: 0 | AZ75: 0 | BA75: 0 | BC75: 4 | BD75: 0 | BE75: 0 | BF75: 5
A76: E07000225 | B76: Chichester | E76: 244 | G76: 88 | I76: 3 | J76: 0 | K76: 5 | L76: 1 | M76: 2 | O76: 0 | Q76: 62 | R76: 50 | S76: 12 | T76: 0 | V76: 3 | W76: 0 | X76: 0 | Y76: 12 | AA76: 8 | AB76: 54 | AC76: 16 | AE76: 9 | AF76: 8 | AG76: 1 | AH76: 0 | AJ76: 3 | AL76: 22 | AM76: 18 | AN76: 2 | AO76: 2 | AQ76: 11 | AR76: 8 | AS76: 1 | AT76: 2 | AV76: 5 | AW76: 1 | AX76: 1 | AY76: 0 | AZ76: 3 | BA76: 0 | BC76: 8 | BD76: 1 | BE76: 0 | BF76: 19
A77: E07000118 | B77: Chorley | E77: 275 | G77: 98 | I77: 4 | J77: 1 | K77: 2 | L77: 1 | M77: 9 | O77: 0 | Q77: 66 | R77: 51 | S77: 15 | T77: 0 | V77: 1 | W77: 1 | X77: 0 | Y77: 13 | AA77: 3 | AB77: 45 | AC77: 12 | AE77: 69 | AF77: 66 | AG77: 3 | AH77: 0 | AJ77: 0 | AL77: 8 | AM77: 6 | AN77: 1 | AO77: 1 | AQ77: 6 | AR77: 0 | AS77: 4 | AT77: 2 | AV77: 5 | AW77: 3 | AX77: 1 | AY77: 0 | AZ77: 1 | BA77: 0 | BC77: 9 | BD77: 5 | BE77: 2 | BF77: 13
A78: E09000001 | B78: City of London | E78: 1 | G78: 0 | I78: 0 | J78: 0 | K78: 0 | L78: 0 | M78: 0 | O78: 0 | Q78: 0 | R78: 0 | S78: 0 | T78: 0 | V78: 0 | W78: 0 | X78: 0 | Y78: 0 | AA78: 0 | AB78: 0 | AC78: 0 | AE78: 0 | AF78: 0 | AG78: 0 | AH78: 0 | AJ78: 0 | AL78: 0 | AM78: 0 | AN78: 0 | AO78: 0 | AQ78: 0 | AR78: 0 | AS78: 0 | AT78: 0 | AV78: 0 | AW78: 0 | AX78: 0 | AY78: 0 | AZ78: 0 | BA78: 0 | BC78: 1 | BD78: 0 | BE78: 0 | BF78: 0
... A83: E07000226 | B83: Crawley | E83: 416 | G83: 169 | I83: 5 | J83: 3 | K83: 1 | L83: 1 | M83: 12 | O83: 3 | Q83: 123 | R83: 98 | S83: 25 | T83: 0 | V83: 2 | W83: 0 | X83: 2 | Y83: 17 | AA83: 18 | AB83: 115 | AC83: 8 | AE83: 28 | AF83: 24 | AG83: 4 | AH83: 0 | AJ83: 1 | AL83: 9 | AM83: 2 | AN83: 2 | AO83: 5 | AQ83: 9 | AR83: 0 | AS83: 1 | AT83: 8 | AV83: 4 | AW83: 2 | AX83: 0 | AY83: 0 | AZ83: 2 | BA83: 0 | BC83: 24 | BD83: 3 | BE83: 0 | BF83: 28
A84: E09000008 | B84: Croydon | E84: .. | G84: .. | I84: .. | J84: .. | K84: .. | L84: .. | M84: .. | O84: .. | Q84: .. | R84: .. | S84: .. | T84: .. | V84: .. | W84: .. | X84: .. | Y84: .. | AA84: .. | AB84: .. | AC84: .. | AE84: .. | AF84: .. | AG84: .. | AH84: .. | AJ84: .. | AL84: .. | AM84: .. | AN84: .. | AO84: .. | AQ84: .. | AR84: .. | AS84: .. | AT84: .. | AV84: .. | AW84: .. | AX84: .. | AY84: .. | AZ84: .. | BA84: .. | BC84: .. | BD84: .. | BE84: .. | BF84: ..
A85: E06000063 | B85: Cumberland Council | E85: 898 | G85: 211 | I85: 6 | J85: 2 | K85: 4 | L85: 0 | M85: 6 | O85: 2 | Q85: 166 | R85: 134 | S85: 32 | T85: 0 | V85: 4 | W85: 0 | X85: 4 | Y85: 17 | AA85: 16 | AB85: 205 | AC85: 120 | AE85: 121 | AF85: 115 | AG85: 6 | AH85: 0 | AJ85: 7 | AL85: 34 | AM85: 12 | AN85: 13 | AO85: 9 | AQ85: 14 | AR85: 2 | AS85: 8 | AT85: 4 | AV85: 60 | AW85: 49 | AX85: 1 | AY85: 3 | AZ85: 7 | BA85: 0 | BC85: 28 | BD85: 5 | BE85: 8 | BF85: 69
A86: E07000096 | B86: Dacorum | E86: 486 | G86: 172 | I86: 7 | J86: 5 | K86: 3 | L86: 1 | M86: 10 | O86: 0 | Q86: 122 | R86: 102 | S86: 20 | T86: 0 | V86: 3 | W86: 1 | X86: 0 | Y86: 20 | AA86: 4 | AB86: 167 | AC86: 21 | AE86: 20 | AF86: 18 | AG86: 2 | AH86: 0 | AJ86: 1 | AL86: 18 | AM86: 6 | AN86: 3 | AO86: 9 | AQ86: 4 | AR86: 0 | AS86: 1 | AT86: 3 | AV86: 4 | AW86: 3 | AX86: 0 | AY86: 0 | AZ86: 1 | BA86: 0 | BC86: 54 | BD86: 13 | BE86: 0 | BF86: 8
A87: E06000005 | B87: Darlington | E87: 759 | G87: 186 | I87: 5 | J87: 2 | K87: 5 | L87: 0 | M87: 2 | O87: 1 | Q87: 120 | R87: 103 | S87: 17 | T87: 0 | V87: 1 | W87: 0 | X87: 0 | Y87: 50 | AA87: 7 | AB87: 155 | AC87: 25 | AE87: 75 | AF87: 73 | AG87: 2 | AH87: 0 | AJ87: 7 | AL87: 44 | AM87: 27 | AN87: 3 | AO87: 14 | AQ87: 41 | AR87: 4 | AS87: 5 | AT87: 32 | AV87: 137 | AW87: 108 | AX87: 19 | AY87: 4 | AZ87: 6 | BA87: 0 | BC87: 38 | BD87: 1 | BE87: 1 | BF87: 42
A88: E07000107 | B88: Dartford | E88: 325 | G88: 100 | I88: 2 | J88: 5 | K88: 4 | L88: 0 | M88: 10 | O88: 2 | Q88: 52 | R88: 25 | S88: 27 | T88: 0 | V88: 1 | W88: 1 | X88: 1 | Y88: 22 | AA88: 32 | AB88: 71 | AC88: 18 | AE88: 43 | AF88: 42 | AG88: 1 | AH88: 0 | AJ88: 2 | AL88: 32 | AM88: 27 | AN88: 0 | AO88: 5 | AQ88: 2 | AR88: 2 | AS88: 0 | AT88: 0 | AV88: 3 | AW88: 1 | AX88: 0 | AY88: 0 | AZ88: 2 | BA88: 0 | BC88: 0 | BD88: 11 | BE88: 1 | BF88: 10
A89: E06000015 | B89: Derby | E89: 1145 | G89: 364 | I89: 30 | J89: 14 | K89: 19 | L89: 8 | M89: 17 | O89: 5 | Q89: 205 | R89: 161 | S89: 44 | T89: 0 | V89: 7 | W89: 3 | X89: 7 | Y89: 49 | AA89: 14 | AB89: 314 | AC89: 63 | AE89: 95 | AF89: 89 | AG89: 6 | AH89: 0 | AJ89: 15 | AL89: 18 | AM89: 7 | AN89: 0 | AO89: 11 | AQ89: 68 | AR89: 12 | AS89: 27 | AT89: 29 | AV89: 35 | AW89: 26 | AX89: 2 | AY89: 2 | AZ89: 5 | BA89: 0 | BC89: 123 | BD89: 14 | BE89: 1 | BF89: 21
A90: E07000035 | B90: Derbyshire Dales | E90: 141 | G90: 41 | I90: 2 | J90: 0 | K90: 0 | L90: 0 | M90: 3 | O90: 0 | Q90: 31 | R90: 27 | S90: 4 | T90: 0 | V90: 0 | W90: 0 | X90: 0 | Y90: 5 | AA90: 1 | AB90: 43 | AC90: 19 | AE90: 6 | AF90: 6 | AG90: 0 | AH90: 0 | AJ90: 0 | AL90: 11 | AM90: 9 | AN90: 0 | AO90: 2 | AQ90: 4 | AR90: 0 | AS90: 3 | AT90: 1 | AV90: 4 | AW90: 3 | AX90: 1 | AY90: 0 | AZ90: 0 | BA90: 0 | BC90: 0 | BD90: 4 | BE90: 2 | BF90: 6
A91: E08000017 | B91: Doncaster | E91: 1437 | G91: 360 | I91: 43 | J91: 6 | K91: 11 | L91: 2 | M91: 18 | O91: 11 | Q91: 218 | R91: 168 | S91: 50 | T91: 0 | V91: 1 | W91: 2 | X91: 18 | Y91: 30 | AA91: 45 | AB91: 413 | AC91: 78 | AE91: 211 | AF91: 192 | AG91: 19 | AH91: 0 | AJ91: 33 | AL91: 17 | AM91: 2 | AN91: 3 | AO91: 12 | AQ91: 78 | AR91: 6 | AS91: 31 | AT91: 41 | AV91: 50 | AW91: 40 | AX91: 2 | AY91: 5 | AZ91: 3 | BA91: 0 | BC91: 105 | BD91: 19 | BE91: 0 | BF91: 28
A92: E06000059 | B92: Dorset | E92: 1139 | G92: 424 | I92: 6 | J92: 4 | K92: 3 | L92: 0 | M92: 16 | O92: 5 | Q92: 324 | R92: 75 | S92: 249 | T92: 0 | V92: 3 | W92: 4 | X92: 1 | Y92: 58 | AA92: 74 | AB92: 258 | AC92: 94 | AE92: 84 | AF92: 74 | AG92: 10 | AH92: 0 | AJ92: 6 | AL92: 61 | AM92: 50 | AN92: 5 | AO92: 6 | AQ92: 17 | AR92: 0 | AS92: 9 | AT92: 8 | AV92: 2 | AW92: 1 | AX92: 0 | AY92: 0 | AZ92: 1 | BA92: 0 | BC92: 0 | BD92: 20 | BE92: 18 | BF92: 81
A93: E07000108 | B93: Dover | E93: 170 | G93: 58 | I93: 2 | J93: 2 | K93: 1 | L93: 0 | M93: 2 | O93: 3 | Q93: 32 | R93: 6 | S93: 26 | T93: 0 | V93: 1 | W93: 0 | X93: 0 | Y93: 15 | AA93: 35 | AB93: 30 | AC93: 9 | AE93: 9 | AF93: 8 | AG93: 1 | AH93: 0 | AJ93: 1 | AL93: 2 | AM93: 0 | AN93: 0 | AO93: 2 | AQ93: 4 | AR93: 1 | AS93: 1 | AT93: 2 | AV93: 0 | AW93: 0 | AX93: 0 | AY93: 0 | AZ93: 0 | BA93: 0 | BC93: 0 | BD93: 7 | BE93: 1 | BF93: 14
A94: E08000027 | B94: Dudley | E94: 489 | G94: 162 | I94: 1 | J94: 5 | K94: 0 | L94: 0 | M94: 8 | O94: 0 | Q94: 49 | R94: 15 | S94: 34 | T94: 0 | V94: 1 | W94: 0 | X94: 0 | Y94: 98 | AA94: 39 | AB94: 90 | AC94: 20 | AE94: 31 | AF94: 31 | AG94: 0 | AH94: 0 | AJ94: 9 | AL94: 56 | AM94: 38 | AN94: 1 | AO94: 17 | AQ94: 3 | AR94: 1 | AS94: 0 | AT94: 2 | AV94: 9 | AW94: 7 | AX94: 0 | AY94: 0 | AZ94: 2 | BA94: 0 | BC94: 14 | BD94: 6 | BE94: 2 | BF94: 48
A95: E06000047 | B95: Durham | E95: 1585 | G95: 454 | I95: 31 | J95: 4 | K95: 0 | L95: 0 | M95: 30 | O95: 14 | Q95: 328 | R95: 306 | S95: 22 | T95: 0 | V95: 4 | W95: 2 | X95: 0 | Y95: 41 | AA95: 53 | AB95: 344 | AC95: 86 | AE95: 130 | AF95: 126 | AG95: 4 | AH95: 0 | AJ95: 24 | AL95: 86 | AM95: 62 | AN95: 8 | AO95: 16 | AQ95: 66 | AR95: 5 | AS95: 24 | AT95: 37 | AV95: 114 | AW95: 102 | AX95: 9 | AY95: 3 | AZ95: 0 | BA95: 0 | BC95: 77 | BD95: 28 | BE95: 7 | BF95: 116
A96: E09000009 | B96: Ealing | E96: 1560 | G96: 796 | I96: 18 | J96: 26 | K96: 9 | L96: 9 | M96: 26 | O96: 15 | Q96: 561 | R96: 267 | S96: 294 | T96: 0 | V96: 25 | W96: 6 | X96: 4 | Y96: 97 | AA96: 64 | AB96: 431 | AC96: 10 | AE96: 45 | AF96: 42 | AG96: 3 | AH96: 0 | AJ96: 19 | AL96: 38 | AM96: 31 | AN96: 1 | AO96: 6 | AQ96: 17 | AR96: 5 | AS96: 4 | AT96: 8 | AV96: 17 | AW96: 12 | AX96: 1 | AY96: 4 | AZ96: 0 | BA96: 0 | BC96: 58 | BD96: 33 | BE96: 4 | BF96: 28
... A102: E06000011 | B102: East Riding of Yorkshire | E102: 271 | G102: 170 | I102: 5 | J102: 2 | K102: 3 | L102: 2 | M102: 0 | O102: 1 | Q102: 127 | R102: 115 | S102: 12 | T102: 0 | V102: 8 | W102: 0 | X102: 0 | Y102: 22 | AA102: 24 | AB102: 25 | AC102: 11 | AE102: 8 | AF102: 7 | AG102: 1 | AH102: 0 | AJ102: 0 | AL102: 10 | AM102: 3 | AN102: 1 | AO102: 6 | AQ102: 5 | AR102: 3 | AS102: 1 | AT102: 1 | AV102: 3 | AW102: 3 | AX102: 0 | AY102: 0 | AZ102: 0 | BA102: 0 | BC102: 2 | BD102: 2 | BE102: 0 | BF102: 11
A103: E07000193 | B103: East Staffordshire | E103: .. | G103: .. | I103: .. | J103: .. | K103: .. | L103: .. | M103: .. | O103: .. | Q103: .. | R103: .. | S103: .. | T103: .. | V103: .. | W103: .. | X103: .. | Y103: .. | AA103: .. | AB103: .. | AC103: .. | AE103: .. | AF103: .. | AG103: .. | AH103: .. | AJ103: .. | AL103: .. | AM103: .. | AN103: .. | AO103: .. | AQ103: .. | AR103: .. | AS103: .. | AT103: .. | AV103: .. | AW103: .. | AX103: .. | AY103: .. | AZ103: .. | BA103: .. | BC103: .. | BD103: .. | BE103: .. | BF103: ..
A104: E07000244 | B104: East Suffolk | E104: 693 | G104: 278 | I104: 2 | J104: 2 | K104: 1 | L104: 0 | M104: 19 | O104: 6 | Q104: 230 | R104: 186 | S104: 44 | T104: 0 | V104: 2 | W104: 0 | X104: 1 | Y104: 15 | AA104: 11 | AB104: 163 | AC104: 29 | AE104: 51 | AF104: 44 | AG104: 7 | AH104: 0 | AJ104: 7 | AL104: 35 | AM104: 23 | AN104: 4 | AO104: 8 | AQ104: 49 | AR104: 5 | AS104: 8 | AT104: 36 | AV104: 21 | AW104: 21 | AX104: 0 | AY104: 0 | AZ104: 0 | BA104: 0 | BC104: 1 | BD104: 10 | BE104: 0 | BF104: 38
A105: E07000061 | B105: Eastbourne | E105: 298 | G105: 141 | I105: 1 | J105: 2 | K105: 3 | L105: 1 | M105: 6 | O105: 3 | Q105: 100 | R105: 79 | S105: 21 | T105: 0 | V105: 0 | W105: 0 | X105: 0 | Y105: 25 | AA105: 13 | AB105: 63 | AC105: 12 | AE105: 18 | AF105: 15 | AG105: 3 | AH105: 0 | AJ105: 2 | AL105: 8 | AM105: 1 | AN105: 1 | AO105: 6 | AQ105: 9 | AR105: 0 | AS105: 1 | AT105: 8 | AV105: 5 | AW105: 1 | AX105: 1 | AY105: 0 | AZ105: 3 | BA105: 0 | BC105: 2 | BD105: 12 | BE105: 3 | BF105: 10
A106: E07000086 | B106: Eastleigh | E106: 213 | G106: 83 | I106: 7 | J106: 1 | K106: 4 | L106: 1 | M106: 3 | O106: 1 | Q106: 51 | R106: 37 | S106: 14 | T106: 0 | V106: 0 | W106: 0 | X106: 1 | Y106: 14 | AA106: 8 | AB106: 53 | AC106: 20 | AE106: 18 | AF106: 18 | AG106: 0 | AH106: 0 | AJ106: 1 | AL106: 7 | AM106: 7 | AN106: 0 | AO106: 0 | AQ106: 6 | AR106: 0 | AS106: 4 | AT106: 2 | AV106: 4 | AW106: 2 | AX106: 1 | AY106: 0 | AZ106: 1 | BA106: 0 | BC106: 0 | BD106: 3 | BE106: 1 | BF106: 9
A107: E07000207 | B107: Elmbridge | E107: 228 | G107: 97 | I107: 0 | J107: 2 | K107: 2 | L107: 0 | M107: 6 | O107: 1 | Q107: 70 | R107: 57 | S107: 13 | T107: 0 | V107: 1 | W107: 0 | X107: 0 | Y107: 15 | AA107: 10 | AB107: 71 | AC107: 3 | AE107: 13 | AF107: 12 | AG107: 1 | AH107: 0 | AJ107: 2 | AL107: 11 | AM107: 9 | AN107: 0 | AO107: 2 | AQ107: 3 | AR107: 0 | AS107: 0 | AT107: 3 | AV107: 6 | AW107: 1 | AX107: 1 | AY107: 0 | AZ107: 4 | BA107: 0 | BC107: 1 | BD107: 1 | BE107: 5 | BF107: 5
A108: E09000010 | B108: Enfield | E108: 823 | G108: 589 | I108: 68 | J108: 48 | K108: 5 | L108: 9 | M108: 17 | O108: 1 | Q108: 208 | R108: 116 | S108: 92 | T108: 0 | V108: 6 | W108: 1 | X108: 0 | Y108: 226 | AA108: 21 | AB108: 121 | AC108: 4 | AE108: 5 | AF108: 4 | AG108: 1 | AH108: 0 | AJ108: 3 | AL108: 3 | AM108: 1 | AN108: 0 | AO108: 2 | AQ108: 41 | AR108: 17 | AS108: 0 | AT108: 24 | AV108: 0 | AW108: 0 | AX108: 0 | AY108: 0 | AZ108: 0 | BA108: 0 | BC108: 2 | BD108: 15 | BE108: 0 | BF108: 19
A109: E07000072 | B109: Epping Forest | E109: .. | G109: .. | I109: .. | J109: .. | K109: .. | L109: .. | M109: .. | O109: .. | Q109: .. | R109: .. | S109: .. | T109: .. | V109: .. | W109: .. | X109: .. | Y109: .. | AA109: .. | AB109: .. | AC109: .. | AE109: .. | AF109: .. | AG109: .. | AH109: .. | AJ109: .. | AL109: .. | AM109: .. | AN109: .. | AO109: .. | AQ109: .. | AR109: .. | AS109: .. | AT109: .. | AV109: .. | AW109: .. | AX109: .. | AY109: .. | AZ109: .. | BA109: .. | BC109: .. | BD109: .. | BE109: .. | BF109: ..
A110: E07000208 | B110: Epsom & Ewell | E110: 97 | G110: 61 | I110: 2 | J110: 0 | K110: 0 | L110: 0 | M110: 2 | O110: 0 | Q110: 51 | R110: 32 | S110: 19 | T110: 0 | V110: 1 | W110: 0 | X110: 0 | Y110: 5 | AA110: 4 | AB110: 18 | AC110: 1 | AE110: 0 | AF110: 0 | AG110: 0 | AH110: 0 | AJ110: 0 | AL110: 3 | AM110: 1 | AN110: 0 | AO110: 2 | AQ110: 1 | AR110: 0 | AS110: 0 | AT110: 1 | AV110: 4 | AW110: 2 | AX110: 0 | AY110: 0 | AZ110: 2 | BA110: 0 | BC110: 0 | BD110: 1 | BE110: 1 | BF110: 3
A111: E07000036 | B111: Erewash | E111: 288 | G111: 93 | I111: 8 | J111: 0 | K111: 1 | L111: 0 | M111: 9 | O111: 2 | Q111: 62 | R111: 60 | S111: 2 | T111: 0 | V111: 0 | W111: 0 | X111: 0 | Y111: 11 | AA111: 6 | AB111: 72 | AC111: 20 | AE111: 15 | AF111: 12 | AG111: 3 | AH111: 0 | AJ111: 2 | AL111: 5 | AM111: 3 | AN111: 1 | AO111: 1 | AQ111: 17 | AR111: 2 | AS111: 8 | AT111: 7 | AV111: 12 | AW111: 10 | AX111: 1 | AY111: 0 | AZ111: 1 | BA111: 0 | BC111: 39 | BD111: 2 | BE111: 0 | BF111: 5
A112: E07000041 | B112: Exeter | E112: 432 | G112: 125 | I112: 2 | J112: 2 | K112: 6 | L112: 1 | M112: 7 | O112: 4 | Q112: 73 | R112: 54 | S112: 19 | T112: 0 | V112: 2 | W112: 0 | X112: 0 | Y112: 28 | AA112: 16 | AB112: 103 | AC112: 8 | AE112: 21 | AF112: 18 | AG112: 3 | AH112: 0 | AJ112: 6 | AL112: 18 | AM112: 7 | AN112: 2 | AO112: 9 | AQ112: 66 | AR112: 28 | AS112: 24 | AT112: 14 | AV112: 41 | AW112: 7 | AX112: 0 | AY112: 1 | AZ112: 33 | BA112: 0 | BC112: 4 | BD112: 4 | BE112: 0 | BF112: 20
A113: E07000087 | B113: Fareham | E113: 147 | G113: 83 | I113: 0 | J113: 0 | K113: 2 | L113: 0 | M113: 5 | O113: 0 | Q113: 65 | R113: 57 | S113: 8 | T113: 0 | V113: 0 | W113: 0 | X113: 0 | Y113: 11 | AA113: 5 | AB113: 37 | AC113: 3 | AE113: 2 | AF113: 2 | AG113: 0 | AH113: 0 | AJ113: 0 | AL113: 3 | AM113: 0 | AN113: 0 | AO113: 3 | AQ113: 4 | AR113: 0 | AS113: 0 | AT113: 4 | AV113: 5 | AW113: 4 | AX113: 0 | AY113: 0 | AZ113: 1 | BA113: 0 | BC113: 0 | BD113: 2 | BE113: 0 | BF113: 3
A114: E07000010 | B114: Fenland | E114: 192 | G114: 77 | I114: 3 | J114: 1 | K114: 1 | L114: 0 | M114: 9 | O114: 2 | Q114: 47 | R114: 36 | S114: 11 | T114: 0 | V114: 3 | W114: 0 | X114: 0 | Y114: 11 | AA114: 14 | AB114: 55 | AC114: 14 | AE114: 14 | AF114: 14 | AG114: 0 | AH114: 0 | AJ114: 0 | AL114: 2 | AM114: 1 | AN114: 0 | AO114: 1 | AQ114: 3 | AR114: 1 | AS114: 0 | AT114: 2 | AV114: 3 | AW114: 0 | AX114: 0 | AY114: 0 | AZ114: 3 | BA114: 0 | BC114: 0 | BD114: 1 | BE114: 0 | BF114: 9
A115: E07000112 | B115: Folkestone & Hythe | E115: 308 | G115: 116 | I115: 0 | J115: 2 | K115: 4 | L115: 0 | M115: 5 | O115: 0 | Q115: 73 | R115: 7 | S115: 66 | T115: 0 | V115: 1 | W115: 0 | X115: 2 | Y115: 29 | AA115: 49 | AB115: 48 | AC115: 18 | AE115: 16 | AF115: 14 | AG115: 2 | AH115: 0 | AJ115: 1 | AL115: 3 | AM115: 1 | AN115: 0 | AO115: 2 | AQ115: 5 | AR115: 1 | AS115: 2 | AT115: 2 | AV115: 14 | AW115: 9 | AX115: 3 | AY115: 0 | AZ115: 2 | BA115: 0 | BC115: 1 | BD115: 11 | BE115: 1 | BF115: 25
A116: E07000080 | B116: Forest of Dean | E116: 199 | G116: 55 | I116: 1 | J116: 0 | K116: 3 | L116: 0 | M116: 2 | O116: 0 | Q116: 44 | R116: 43 | S116: 1 | T116: 0 | V116: 0 | W116: 0 | X116: 1 | Y116: 4 | AA116: 10 | AB116: 56 | AC116: 20 | AE116: 13 | AF116: 12 | AG116: 1 | AH116: 0 | AJ116: 1 | AL116: 7 | AM116: 2 | AN116: 1 | AO116: 4 | AQ116: 0 | AR116: 0 | AS116: 0 | AT116: 0 | AV116: 12 | AW116: 8 | AX116: 1 | AY116: 2 | AZ116: 1 | BA116: 0 | BC116: 0 | BD116: 9 | BE116: 7 | BF116: 9
A117: E07000119 | B117: Fylde | E117: 122 | G117: 96 | I117: 4 | J117: 1 | K117: 0 | L117: 1 | M117: 8 | O117: 1 | Q117: 65 | R117: 54 | S117: 11 | T117: 0 | V117: 0 | W117: 0 | X117: 0 | Y117: 16 | AA117: 4 | AB117: 5 | AC117: 1 | AE117: 2 | AF117: 2 | AG117: 0 | AH117: 0 | AJ117: 1 | AL117: 6 | AM117: 3 | AN117: 0 | AO117: 3 | AQ117: 1 | AR117: 0 | AS117: 1 | AT117: 0 | AV117: 1 | AW117: 0 | AX117: 0 | AY117: 0 | AZ117: 1 | BA117: 0 | BC117: 0 | BD117: 0 | BE117: 0 | BF117: 5
A118: E08000037 | B118: Gateshead | E118: 972 | G118: 198 | I118: 7 | J118: 3 | K118: 2 | L118: 3 | M118: 7 | O118: 2 | Q118: 114 | R118: 106 | S118: 8 | T118: 0 | V118: 5 | W118: 0 | X118: 1 | Y118: 54 | AA118: 16 | AB118: 193 | AC118: 90 | AE118: 208 | AF118: 203 | AG118: 5 | AH118: 0 | AJ118: 25 | AL118: 30 | AM118: 12 | AN118: 1 | AO118: 17 | AQ118: 63 | AR118: 2 | AS118: 10 | AT118: 51 | AV118: 22 | AW118: 21 | AX118: 0 | AY118: 0 | AZ118: 1 | BA118: 0 | BC118: 82 | BD118: 10 | BE118: 1 | BF118: 34
A119: E07000173 | B119: Gedling | E119: 195 | G119: 100 | I119: 1 | J119: 0 | K119: 2 | L119: 1 | M119: 4 | O119: 2 | Q119: 73 | R119: 67 | S119: 6 | T119: 0 | V119: 1 | W119: 0 | X119: 0 | Y119: 16 | AA119: 3 | AB119: 41 | AC119: 13 | AE119: 8 | AF119: 8 | AG119: 0 | AH119: 0 | AJ119: 0 | AL119: 3 | AM119: 1 | AN119: 1 | AO119: 1 | AQ119: 6 | AR119: 1 | AS119: 5 | AT119: 0 | AV119: 5 | AW119: 3 | AX119: 0 | AY119: 0 | AZ119: 2 | BA119: 0 | BC119: 11 | BD119: 2 | BE119: 1 | BF119: 2
A120: E07000081 | B120: Gloucester | E120: 614 | G120: 221 | I120: 6 | J120: 4 | K120: 0 | L120: 1 | M120: 11 | O120: 4 | Q120: 155 | R120: 116 | S120: 39 | T120: 0 | V120: 4 | W120: 0 | X120: 0 | Y120: 36 | AA120: 14 | AB120: 113 | AC120: 21 | AE120: 127 | AF120: 124 | AG120: 3 | AH120: 0 | AJ120: 6 | AL120: 6 | AM120: 2 | AN120: 0 | AO120: 4 | AQ120: 19 | AR120: 2 | AS120: 10 | AT120: 7 | AV120: 28 | AW120: 21 | AX120: 2 | AY120: 1 | AZ120: 4 | BA120: 0 | BC120: 46 | BD120: 3 | BE120: 3 | BF120: 7
A121: E07000088 | B121: Gosport | E121: 365 | G121: 171 | I121: 9 | J121: 3 | K121: 1 | L121: 6 | M121: 11 | O121: 8 | Q121: 102 | R121: 74 | S121: 28 | T121: 0 | V121: 1 | W121: 0 | X121: 0 | Y121: 30 | AA121: 13 | AB121: 99 | AC121: 16 | AE121: 4 | AF121: 4 | AG121: 0 | AH121: 0 | AJ121: 0 | AL121: 16 | AM121: 10 | AN121: 3 | AO121: 3 | AQ121: 7 | AR121: 1 | AS121: 2 | AT121: 4 | AV121: 19 | AW121: 18 | AX121: 1 | AY121: 0 | AZ121: 0 | BA121: 0 | BC121: 3 | BD121: 0 | BE121: 6 | BF121: 11
... A137: E09000016 | B137: Havering | E137: 1061 | G137: 497 | I137: 18 | J137: 5 | K137: 11 | L137: 16 | M137: 12 | O137: 7 | Q137: 373 | R137: 293 | S137: 80 | T137: 0 | V137: 18 | W137: 3 | X137: 3 | Y137: 31 | AA137: 42 | AB137: 351 | AC137: 36 | AE137: 9 | AF137: 8 | AG137: 1 | AH137: 0 | AJ137: 25 | AL137: 28 | AM137: 19 | AN137: 2 | AO137: 7 | AQ137: 9 | AR137: 2 | AS137: 5 | AT137: 2 | AV137: 17 | AW137: 13 | AX137: 1 | AY137: 3 | AZ137: 0 | BA137: 0 | BC137: 7 | BD137: 12 | BE137: 0 | BF137: 28
A138: E06000019 | B138: Herefordshire | E138: .. | G138: .. | I138: .. | J138: .. | K138: .. | L138: .. | M138: .. | O138: .. | Q138: .. | R138: .. | S138: .. | T138: .. | V138: .. | W138: .. | X138: .. | Y138: .. | AA138: .. | AB138: .. | AC138: .. | AE138: .. | AF138: .. | AG138: .. | AH138: .. | AJ138: .. | AL138: .. | AM138: .. | AN138: .. | AO138: .. | AQ138: .. | AR138: .. | AS138: .. | AT138: .. | AV138: .. | AW138: .. | AX138: .. | AY138: .. | AZ138: .. | BA138: .. | BC138: .. | BD138: .. | BE138: .. | BF138: ..
A139: E07000098 | B139: Hertsmere | E139: 351 | G139: 98 | I139: 5 | J139: 4 | K139: 3 | L139: 3 | M139: 5 | O139: 0 | Q139: 60 | R139: 37 | S139: 23 | T139: 0 | V139: 0 | W139: 0 | X139: 0 | Y139: 18 | AA139: 19 | AB139: 104 | AC139: 21 | AE139: 21 | AF139: 21 | AG139: 0 | AH139: 0 | AJ139: 1 | AL139: 33 | AM139: 25 | AN139: 0 | AO139: 8 | AQ139: 7 | AR139: 3 | AS139: 2 | AT139: 2 | AV139: 5 | AW139: 0 | AX139: 3 | AY139: 1 | AZ139: 1 | BA139: 0 | BC139: 1 | BD139: 17 | BE139: 2 | BF139: 22
A140: E07000037 | B140: High Peak | E140: 154 | G140: 84 | I140: 3 | J140: 0 | K140: 1 | L140: 0 | M140: 0 | O140: 2 | Q140: 69 | R140: 60 | S140: 9 | T140: 0 | V140: 0 | W140: 1 | X140: 0 | Y140: 8 | AA140: 15 | AB140: 21 | AC140: 9 | AE140: 4 | AF140: 4 | AG140: 0 | AH140: 0 | AJ140: 1 | AL140: 5 | AM140: 3 | AN140: 1 | AO140: 1 | AQ140: 3 | AR140: 0 | AS140: 3 | AT140: 0 | AV140: 6 | AW140: 4 | AX140: 1 | AY140: 0 | AZ140: 1 | BA140: 0 | BC140: 0 | BD140: 0 | BE140: 2 | BF140: 4
A141: E09000017 | B141: Hillingdon | E141: 739 | G141: 337 | I141: 3 | J141: 12 | K141: 2 | L141: 0 | M141: 3 | O141: 1 | Q141: 228 | R141: 171 | S141: 57 | T141: 0 | V141: 2 | W141: 0 | X141: 0 | Y141: 86 | AA141: 54 | AB141: 151 | AC141: 11 | AE141: 55 | AF141: 53 | AG141: 2 | AH141: 0 | AJ141: 7 | AL141: 5 | AM141: 0 | AN141: 0 | AO141: 5 | AQ141: 34 | AR141: 2 | AS141: 2 | AT141: 30 | AV141: 10 | AW141: 4 | AX141: 0 | AY141: 1 | AZ141: 5 | BA141: 0 | BC141: 24 | BD141: 12 | BE141: 1 | BF141: 38
A142: E07000132 | B142: Hinckley & Bosworth | E142: 149 | G142: 68 | I142: 3 | J142: 0 | K142: 2 | L142: 0 | M142: 3 | O142: 0 | Q142: 52 | R142: 48 | S142: 4 | T142: 0 | V142: 0 | W142: 0 | X142: 0 | Y142: 8 | AA142: 3 | AB142: 34 | AC142: 7 | AE142: 3 | AF142: 3 | AG142: 0 | AH142: 0 | AJ142: 1 | AL142: 5 | AM142: 1 | AN142: 1 | AO142: 3 | AQ142: 10 | AR142: 0 | AS142: 2 | AT142: 8 | AV142: 7 | AW142: 7 | AX142: 0 | AY142: 0 | AZ142: 0 | BA142: 0 | BC142: 0 | BD142: 0 | BE142: 3 | BF142: 8
A143: E07000227 | B143: Horsham | E143: 223 | G143: 94 | I143: 1 | J143: 4 | K143: 5 | L143: 0 | M143: 3 | O143: 0 | Q143: 62 | R143: 41 | S143: 21 | T143: 0 | V143: 0 | W143: 1 | X143: 0 | Y143: 18 | AA143: 8 | AB143: 43 | AC143: 3 | AE143: 6 | AF143: 6 | AG143: 0 | AH143: 0 | AJ143: 0 | AL143: 29 | AM143: 27 | AN143: 0 | AO143: 2 | AQ143: 10 | AR143: 1 | AS143: 1 | AT143: 8 | AV143: 4 | AW143: 3 | AX143: 0 | AY143: 0 | AZ143: 1 | BA143: 0 | BC143: 13 | BD143: 2 | BE143: 0 | BF143: 11
A144: E09000018 | B144: Hounslow | E144: 774 | G144: 437 | I144: 11 | J144: 7 | K144: 6 | L144: 2 | M144: 7 | O144: 0 | Q144: 219 | R144: 131 | S144: 87 | T144: 1 | V144: 2 | W144: 0 | X144: 0 | Y144: 183 | AA144: 48 | AB144: 192 | AC144: 12 | AE144: 12 | AF144: 11 | AG144: 1 | AH144: 0 | AJ144: 9 | AL144: 9 | AM144: 2 | AN144: 0 | AO144: 7 | AQ144: 5 | AR144: 0 | AS144: 0 | AT144: 5 | AV144: 5 | AW144: 4 | AX144: 1 | AY144: 0 | AZ144: 0 | BA144: 0 | BC144: 3 | BD144: 15 | BE144: 0 | BF144: 27
A145: E07000011 | B145: Huntingdonshire | E145: 586 | G145: 128 | I145: 7 | J145: 0 | K145: 1 | L145: 2 | M145: 3 | O145: 2 | Q145: 103 | R145: 67 | S145: 36 | T145: 0 | V145: 0 | W145: 0 | X145: 0 | Y145: 10 | AA145: 27 | AB145: 122 | AC145: 26 | AE145: 76 | AF145: 73 | AG145: 3 | AH145: 0 | AJ145: 15 | AL145: 130 | AM145: 118 | AN145: 8 | AO145: 4 | AQ145: 28 | AR145: 10 | AS145: 11 | AT145: 7 | AV145: 8 | AW145: 5 | AX145: 0 | AY145: 0 | AZ145: 3 | BA145: 0 | BC145: 1 | BD145: 6 | BE145: 3 | BF145: 16
A146: E07000120 | B146: Hyndburn | E146: 151 | G146: 90 | I146: 7 | J146: 0 | K146: 2 | L146: 1 | M146: 2 | O146: 1 | Q146: 63 | R146: 61 | S146: 2 | T146: 0 | V146: 1 | W146: 0 | X146: 0 | Y146: 13 | AA146: 12 | AB146: 31 | AC146: 4 | AE146: 4 | AF146: 3 | AG146: 1 | AH146: 0 | AJ146: 1 | AL146: 1 | AM146: 0 | AN146: 0 | AO146: 1 | AQ146: 1 | AR146: 0 | AS146: 1 | AT146: 0 | AV146: 0 | AW146: 0 | AX146: 0 | AY146: 0 | AZ146: 0 | BA146: 0 | BC146: 5 | BD146: 0 | BE146: 0 | BF146: 2
A147: E07000202 | B147: Ipswich | E147: 1010 | G147: 239 | I147: 9 | J147: 3 | K147: 5 | L147: 7 | M147: 16 | O147: 6 | Q147: 160 | R147: 127 | S147: 33 | T147: 0 | V147: 4 | W147: 2 | X147: 0 | Y147: 27 | AA147: 30 | AB147: 277 | AC147: 37 | AE147: 26 | AF147: 22 | AG147: 4 | AH147: 0 | AJ147: 8 | AL147: 132 | AM147: 104 | AN147: 6 | AO147: 22 | AQ147: 175 | AR147: 26 | AS147: 21 | AT147: 128 | AV147: 31 | AW147: 23 | AX147: 0 | AY147: 1 | AZ147: 7 | BA147: 0 | BC147: 9 | BD147: 4 | BE147: 4 | BF147: 38
A148: E06000046 | B148: Isle of Wight | E148: 433 | G148: 180 | I148: 8 | J148: 3 | K148: 1 | L148: 1 | M148: 13 | O148: 5 | Q148: 94 | R148: 82 | S148: 12 | T148: 0 | V148: 0 | W148: 0 | X148: 1 | Y148: 54 | AA148: 27 | AB148: 92 | AC148: 40 | AE148: 14 | AF148: 13 | AG148: 1 | AH148: 0 | AJ148: 1 | AL148: 7 | AM148: 2 | AN148: 2 | AO148: 3 | AQ148: 23 | AR148: 2 | AS148: 18 | AT148: 3 | AV148: 3 | AW148: 3 | AX148: 0 | AY148: 0 | AZ148: 0 | BA148: 0 | BC148: 0 | BD148: 7 | BE148: 0 | BF148: 39
A149: E06000053 | B149: Isles of Scilly | E149: 5 | G149: 3 | I149: 0 | J149: 0 | K149: 0 | L149: 0 | M149: 0 | O149: 0 | Q149: 3 | R149: 3 | S149: 0 | T149: 0 | V149: 0 | W149: 0 | X149: 0 | Y149: 0 | AA149: 0 | AB149: 0 | AC149: 2 | AE149: 0 | AF149: 0 | AG149: 0 | AH149: 0 | AJ149: 0 | AL149: 0 | AM149: 0 | AN149: 0 | AO149: 0 | AQ149: 0 | AR149: 0 | AS149: 0 | AT149: 0 | AV149: 0 | AW149: 0 | AX149: 0 | AY149: 0 | AZ149: 0 | BA149: 0 | BC149: 0 | BD149: 0 | BE149: 0 | BF149: 0
A150: E09000019 | B150: Islington | E150: 680 | G150: 143 | I150: 3 | J150: 6 | K150: 1 | L150: 2 | M150: 2 | O150: 1 | Q150: 30 | R150: 17 | S150: 13 | T150: 0 | V150: 1 | W150: 9 | X150: 1 | Y150: 87 | AA150: 15 | AB150: 226 | AC150: 9 | AE150: 29 | AF150: 28 | AG150: 1 | AH150: 0 | AJ150: 11 | AL150: 18 | AM150: 0 | AN150: 9 | AO150: 9 | AQ150: 175 | AR150: 0 | AS150: 12 | AT150: 163 | AV150: 23 | AW150: 9 | AX150: 2 | AY150: 0 | AZ150: 12 | BA150: 0 | BC150: 4 | BD150: 17 | BE150: 0 | BF150: 10
... A153: E06000010 | B153: Kingston upon Hull | E153: 1590 | G153: 510 | I153: 10 | J153: 12 | K153: 25 | L153: 17 | M153: 50 | O153: 10 | Q153: 226 | R153: 191 | S153: 35 | T153: 0 | V153: 16 | W153: 1 | X153: 4 | Y153: 139 | AA153: 18 | AB153: 294 | AC153: 64 | AE153: 338 | AF153: 333 | AG153: 5 | AH153: 0 | AJ153: 12 | AL153: 37 | AM153: 7 | AN153: 10 | AO153: 20 | AQ153: 89 | AR153: 15 | AS153: 33 | AT153: 41 | AV153: 87 | AW153: 79 | AX153: 4 | AY153: 2 | AZ153: 2 | BA153: 0 | BC153: 86 | BD153: 7 | BE153: 4 | BF153: 44
A154: E09000021 | B154: Kingston upon Thames | E154: .. | G154: .. | I154: .. | J154: .. | K154: .. | L154: .. | M154: .. | O154: .. | Q154: .. | R154: .. | S154: .. | T154: .. | V154: .. | W154: .. | X154: .. | Y154: .. | AA154: .. | AB154: .. | AC154: .. | AE154: .. | AF154: .. | AG154: .. | AH154: .. | AJ154: .. | AL154: .. | AM154: .. | AN154: .. | AO154: .. | AQ154: .. | AR154: .. | AS154: .. | AT154: .. | AV154: .. | AW154: .. | AX154: .. | AY154: .. | AZ154: .. | BA154: .. | BC154: .. | BD154: .. | BE154: .. | BF154: ..
...

Sheet A2R
A1: Table A2R - Number of households owed a relief duty by reason for loss, or threat of loss, of last settled home England, April 2024 to March 2025
G2: End of private rented tenancy - assured shorthold | AA2: End of private rented tenancy - not assured shorthold | AB2: Family or friends no longer willing or able to accommodate | AC2: Non-violent relationship breakdown with partner | AE2: Domestic abuse | AJ2: Other violence or harrassment | AL2: End of social rented tenancy | AQ2: Eviction from supported housing | AV2: Left institution with no accommodation available | BC2: Required to leave accommodation provided by Home Office as asylum support | BE2: Home no longer suitable - disability / ill health | BF2: Other reasons / not known6
BF3: Number of households
E4: Total owed a relief duty1 | G4: End of assured shorthold (AST) private rented tenancy, due to: | AA4: End of non-AST private rented tenancy | AB4: Family or friends no longer willing or able to accommodate | AC4: Non-violent relationship breakdown with partner | AE4: Domestic abuse | AJ4: Other violence or harrassment | AL4: End of social rented tenancy, due to: | AQ4: Eviction from supported housing, due to: | AV4: Departure from institution : | BC4: Required to leave accommodation provided by Home Office as asylum support | BD4: Home no longer suitable - disability / ill health 6 | BE4: Loss of placement or sponsorship provided through a resettlement scheme | BF4: Other reasons / not known5
G5: Total end of AST | I5: Of which: | Q5: Landlord wishing to sell or re-let the property | AE5: Total Domestic abuse | AF5: Of which: | AL5: Total end of social rented tenancy | AM5: Of which: | AQ5: Total evicted from supported housing | AR5: Of which: | AV5: Total Departure from institution | AW5: Of which:
I6: Rent arrears, due to: | R6: Of which:
I7: Tenant difficulty budgeting or making other payment(s) | J7: Increase | K7: Reduction in employment income | L7: Changes | M7: Change in personal circumstances | O7: Breach of tenancy, not related to rent arrears | Q7: Total Landlord wishing to sell or re-let the property | R7: sell the property | S7: re-let the property | T7: Retired "Landlord wishing to" option | V7: Tenant complained to the council / agent / landlord about disrepair | W7: Illegal eviction | X7: Tenant abandoned property | Y7: Other reasons / not known | AF7: Victim | AG7: Alleged perpetrator | AH7: Retired "Domestic abuse" option | AM7: Rent arrears2 | AN7: Breach of tenancy, not related to rent arrears | AO7: Other reasons / not known3 | AR7: Rent arrears | AS7: Breach of tenancy or licence, not related to rent arrears | AT7: Other reasons / not known4 | AW7: Custody | AX7: Hospital (psychiatric) | AY7: Hospital (general) | AZ7: Looked After Child Placement | BA7: Retired "Left institution" option
J8: in rent | L8: in benefit entitlement | S8: re-let the property | T8: Retired "Landlord wishing to" option
A9: E92000001 | B9: ENGLAND | E9: 182540 | G9: 22230 | I9: 1440 | J9: 520 | K9: 590 | L9: 350 | M9: 1610 | O9: 800 | Q9: 8520 | R9: 5540 | S9: 2950 | T9: 30 | V9: 280 | W9: 880 | X9: 1240 | Y9: 6000 | AA9: 5310 | AB9: 54300 | AC9: 12070 | AE9: 28800 | AF9: 25990 | AG9: 2790 | AH9: 10 | AJ9: 5130 | AL9: 4950 | AM9: 1520 | AN9: 1090 | AO9: 2330 | AQ9: 11450 | AR9: 1020 | AS9: 6180 | AT9: 4250 | AV9: 10860 | AW9: 7910 | AX9: 1020 | AY9: 1020 | AZ9: 910 | BA9: 0 | BC9: 13630 | BD9: 2210 | BE9: 360 | BF9: 11260
A10: E12000007 | B10: London | E10: 42500 | G10: 7230 | I10: 370 | J10: 230 | K10: 150 | L10: 180 | M10: 370 | O10: 170 | Q10: 3210 | R10: 1820 | S10: 1370 | T10: 30 | V10: 90 | W10: 240 | X10: 160 | Y10: 2050 | AA10: 1530 | AB10: 13520 | AC10: 1110 | AE10: 5700 | AF10: 5370 | AG10: 330 | AH10: 10 | AJ10: 1210 | AL10: 800 | AM10: 280 | AN10: 130 | AO10: 380 | AQ10: 1780 | AR10: 220 | AS10: 460 | AT10: 1090 | AV10: 2020 | AW10: 1300 | AX10: 310 | AY10: 310 | AZ10: 110 | BA10: 0 | BC10: 4670 | BD10: 700 | BE10: 50 | BF10: 2190
A11: - | B11: Rest of England | E11: 140040 | G11: 14990 | I11: 1070 | J11: 280 | K11: 430 | L11: 170 | M11: 1240 | O11: 630 | Q11: 5310 | R11: 3720 | S11: 1580 | T11: 0 | V11: 190 | W11: 640 | X11: 1080 | Y11: 3940 | AA11: 3790 | AB11: 40790 | AC11: 10960 | AE11: 23100 | AF11: 20620 | AG11: 2470 | AH11: 10 | AJ11: 3920 | AL11: 4150 | AM11: 1240 | AN11: 960 | AO11: 1950 | AQ11: 9670 | AR11: 790 | AS11: 5720 | AT11: 3160 | AV11: 8840 | AW11: 6610 | AX11: 710 | AY11: 710 | AZ11: 800 | BA11: 0 | BC11: 8950 | BD11: 1500 | BE11: 310 | BF11: 9070
A13: E12000001 | B13: North East | E13: 10780 | G13: 1030 | I13: 110 | J13: 10 | K13: 20 | L13: 0 | M13: 70 | O13: 70 | Q13: 320 | R13: 260 | S13: 60 | T13: 0 | V13: 20 | W13: 80 | X13: 70 | Y13: 250 | AA13: 140 | AB13: 3410 | AC13: 1020 | AE13: 1500 | AF13: 1350 | AG13: 150 | AH13: 0 | AJ13: 380 | AL13: 420 | AM13: 150 | AN13: 100 | AO13: 170 | AQ13: 830 | AR13: 60 | AS13: 510 | AT13: 260 | AV13: 690 | AW13: 570 | AX13: 50 | AY13: 50 | AZ13: 20 | BA13: 0 | BC13: 690 | BD13: 40 | BE13: 20 | BF13: 610
A14: E12000002 | B14: North West | E14: 26860 | G14: 2740 | I14: 160 | J14: 70 | K14: 50 | L14: 20 | M14: 220 | O14: 120 | Q14: 920 | R14: 640 | S14: 280 | T14: 0 | V14: 40 | W14: 110 | X14: 290 | Y14: 730 | AA14: 610 | AB14: 8150 | AC14: 1940 | AE14: 3460 | AF14: 2980 | AG14: 490 | AH14: 0 | AJ14: 590 | AL14: 720 | AM14: 220 | AN14: 150 | AO14: 340 | AQ14: 1370 | AR14: 110 | AS14: 820 | AT14: 430 | AV14: 2290 | AW14: 1850 | AX14: 160 | AY14: 170 | AZ14: 110 | BA14: 0 | BC14: 2980 | BD14: 220 | BE14: 40 | BF14: 1740
A15: E12000003 | B15: Yorkshire and The Humber | E15: 16180 | G15: 1660 | I15: 150 | J15: 40 | K15: 60 | L15: 30 | M15: 110 | O15: 60 | Q15: 530 | R15: 370 | S15: 160 | T15: 0 | V15: 30 | W15: 100 | X15: 180 | Y15: 380 | AA15: 250 | AB15: 4500 | AC15: 1210 | AE15: 2940 | AF15: 2670 | AG15: 270 | AH15: 10 | AJ15: 510 | AL15: 480 | AM15: 120 | AN15: 80 | AO15: 280 | AQ15: 1310 | AR15: 80 | AS15: 770 | AT15: 470 | AV15: 1160 | AW15: 1010 | AX15: 50 | AY15: 60 | AZ15: 30 | BA15: 0 | BC15: 1180 | BD15: 150 | BE15: 10 | BF15: 820
A16: E12000004 | B16: East Midlands | E16: 13840 | G16: 1510 | I16: 150 | J16: 30 | K16: 70 | L16: 20 | M16: 110 | O16: 60 | Q16: 430 | R16: 310 | S16: 120 | T16: 0 | V16: 20 | W16: 60 | X16: 100 | Y16: 460 | AA16: 310 | AB16: 4030 | AC16: 1160 | AE16: 2530 | AF16: 2300 | AG16: 220 | AH16: 0 | AJ16: 400 | AL16: 510 | AM16: 140 | AN16: 100 | AO16: 260 | AQ16: 1040 | AR16: 100 | AS16: 570 | AT16: 370 | AV16: 650 | AW16: 470 | AX16: 60 | AY16: 60 | AZ16: 50 | BA16: 0 | BC16: 780 | BD16: 130 | BE16: 20 | BF16: 770
A17: E12000005 | B17: West Midlands | E17: 19850 | G17: 2220 | I17: 100 | J17: 50 | K17: 50 | L17: 30 | M17: 170 | O17: 60 | Q17: 950 | R17: 680 | S17: 270 | T17: 0 | V17: 30 | W17: 80 | X17: 80 | Y17: 640 | AA17: 530 | AB17: 6010 | AC17: 1540 | AE17: 3270 | AF17: 3030 | AG17: 230 | AH17: 0 | AJ17: 500 | AL17: 580 | AM17: 150 | AN17: 150 | AO17: 270 | AQ17: 1520 | AR17: 100 | AS17: 770 | AT17: 650 | AV17: 1000 | AW17: 600 | AX17: 100 | AY17: 130 | AZ17: 170 | BA17: 0 | BC17: 1300 | BD17: 200 | BE17: 60 | BF17: 1110
A18: E12000006 | B18: East of England | E18: 17170 | G18: 1850 | I18: 160 | J18: 40 | K18: 70 | L18: 20 | M18: 170 | O18: 80 | Q18: 720 | R18: 520 | S18: 200 | T18: 0 | V18: 30 | W18: 50 | X18: 100 | Y18: 420 | AA18: 630 | AB18: 4870 | AC18: 1360 | AE18: 3160 | AF18: 2870 | AG18: 290 | AH18: 0 | AJ18: 510 | AL18: 520 | AM18: 170 | AN18: 140 | AO18: 210 | AQ18: 1110 | AR18: 130 | AS18: 660 | AT18: 320 | AV18: 990 | AW18: 680 | AX18: 100 | AY18: 60 | AZ18: 150 | BA18: 0 | BC18: 810 | BD18: 310 | BE18: 40 | BF18: 1020
A19: E12000007 | B19: London | E19: 42500 | G19: 7230 | I19: 370 | J19: 230 | K19: 150 | L19: 180 | M19: 370 | O19: 170 | Q19: 3210 | R19: 1820 | S19: 1370 | T19: 30 | V19: 90 | W19: 240 | X19: 160 | Y19: 2050 | AA19: 1530 | AB19: 13520 | AC19: 1110 | AE19: 5700 | AF19: 5370 | AG19: 330 | AH19: 10 | AJ19: 1210 | AL19: 800 | AM19: 280 | AN19: 130 | AO19: 380 | AQ19: 1780 | AR19: 220 | AS19: 460 | AT19: 1090 | AV19: 2020 | AW19: 1300 | AX19: 310 | AY19: 310 | AZ19: 110 | BA19: 0 | BC19: 4670 | BD19: 700 | BE19: 50 | BF19: 2190
A20: E12000008 | B20: South East | E20: 20950 | G20: 2360 | I20: 170 | J20: 40 | K20: 80 | L20: 30 | M20: 240 | O20: 100 | Q20: 860 | R20: 530 | S20: 330 | T20: 0 | V20: 20 | W20: 90 | X20: 150 | Y20: 600 | AA20: 770 | AB20: 5960 | AC20: 1550 | AE20: 3860 | AF20: 3350 | AG20: 520 | AH20: 0 | AJ20: 670 | AL20: 530 | AM20: 190 | AN20: 130 | AO20: 210 | AQ20: 1110 | AR20: 120 | AS20: 670 | AT20: 320 | AV20: 1190 | AW20: 820 | AX20: 100 | AY20: 100 | AZ20: 180 | BA20: 0 | BC20: 720 | BD20: 280 | BE20: 70 | BF20: 1880
A21: E12000009 | B21: South West | E21: 14400 | G21: 1610 | I21: 80 | J21: 20 | K21: 40 | L21: 10 | M21: 140 | O21: 80 | Q21: 570 | R21: 410 | S21: 160 | T21: 0 | V21: 20 | W21: 60 | X21: 120 | Y21: 470 | AA21: 550 | AB21: 3860 | AC21: 1180 | AE21: 2380 | AF21: 2080 | AG21: 300 | AH21: 0 | AJ21: 360 | AL21: 400 | AM21: 100 | AN21: 100 | AO21: 200 | AQ21: 1380 | AR21: 100 | AS21: 950 | AT21: 330 | AV21: 860 | AW21: 610 | AX21: 90 | AY21: 70 | AZ21: 90 | BA21: 0 | BC21: 490 | BD21: 180 | BE21: 40 | BF21: 1120
... A49: E07000143 | B49: Breckland | E49: 510 | G49: 43 | I49: 2 | J49: 0 | K49: 1 | L49: 0 | M49: 8 | O49: 0 | Q49: 19 | R49: 15 | S49: 4 | T49: 0 | V49: 1 | W49: 1 | X49: 1 | Y49: 10 | AA49: 15 | AB49: 104 | AC49: 37 | AE49: 156 | AF49: 144 | AG49: 12 | AH49: 0 | AJ49: 17 | AL49: 12 | AM49: 2 | AN49: 3 | AO49: 7 | AQ49: 16 | AR49: 3 | AS49: 10 | AT49: 3 | AV49: 28 | AW49: 23 | AX49: 0 | AY49: 2 | AZ49: 3 | BA49: 0 | BC49: 0 | BD49: 56 | BE49: 2 | BF49: 24
A50: E09000005 | B50: Brent | E50: .. | G50: .. | I50: .. | J50: .. | K50: .. | L50: .. | M50: .. | O50: .. | Q50: .. | R50: .. | S50: .. | T50: .. | V50: .. | W50: .. | X50: .. | Y50: .. | AA50: .. | AB50: .. | AC50: .. | AE50: .. | AF50: .. | AG50: .. | AH50: .. | AJ50: .. | AL50: .. | AM50: .. | AN50: .. | AO50: .. | AQ50: .. | AR50: .. | AS50: .. | AT50: .. | AV50: .. | AW50: .. | AX50: .. | AY50: .. | AZ50: .. | BA50: .. | BC50: .. | BD50: .. | BE50: .. | BF50: ..
A51: E07000068 | B51: Brentwood | E51: 94 | G51: 16 | I51: 2 | J51: 0 | K51: 1 | L51: 0 | M51: 2 | O51: 0 | Q51: 7 | R51: 7 | S51: 0 | T51: 0 | V51: 0 | W51: 0 | X51: 1 | Y51: 3 | AA51: 5 | AB51: 23 | AC51: 10 | AE51: 19 | AF51: 17 | AG51: 2 | AH51: 0 | AJ51: 2 | AL51: 4 | AM51: 2 | AN51: 0 | AO51: 2 | AQ51: 1 | AR51: 0 | AS51: 1 | AT51: 0 | AV51: 4 | AW51: 4 | AX51: 0 | AY51: 0 | AZ51: 0 | BA51: 0 | BC51: 0 | BD51: 2 | BE51: 0 | BF51: 8
A52: E06000043 | B52: Brighton & Hove | E52: 984 | G52: 109 | I52: 10 | J52: 5 | K52: 3 | L52: 1 | M52: 7 | O52: 4 | Q52: 30 | R52: 19 | S52: 11 | T52: 0 | V52: 1 | W52: 3 | X52: 3 | Y52: 42 | AA52: 50 | AB52: 222 | AC52: 48 | AE52: 145 | AF52: 131 | AG52: 14 | AH52: 0 | AJ52: 61 | AL52: 14 | AM52: 4 | AN52: 5 | AO52: 5 | AQ52: 95 | AR52: 4 | AS52: 59 | AT52: 32 | AV52: 49 | AW52: 39 | AX52: 6 | AY52: 2 | AZ52: 2 | BA52: 0 | BC52: 39 | BD52: 12 | BE52: 4 | BF52: 136
A53: E06000023 | B53: Bristol | E53: 2246 | G53: 296 | I53: 10 | J53: 6 | K53: 9 | L53: 0 | M53: 16 | O53: 8 | Q53: 112 | R53: 77 | S53: 35 | T53: 0 | V53: 3 | W53: 16 | X53: 17 | Y53: 99 | AA53: 66 | AB53: 708 | AC53: 102 | AE53: 320 | AF53: 298 | AG53: 22 | AH53: 0 | AJ53: 75 | AL53: 46 | AM53: 11 | AN53: 4 | AO53: 31 | AQ53: 166 | AR53: 11 | AS53: 109 | AT53: 46 | AV53: 99 | AW53: 77 | AX53: 3 | AY53: 5 | AZ53: 14 | BA53: 0 | BC53: 160 | BD53: 11 | BE53: 5 | BF53: 192
A54: E07000144 | B54: Broadland | E54: 313 | G54: 22 | I54: 1 | J54: 0 | K54: 1 | L54: 0 | M54: 1 | O54: 0 | Q54: 12 | R54: 6 | S54: 6 | T54: 0 | V54: 1 | W54: 1 | X54: 0 | Y54: 5 | AA54: 8 | AB54: 60 | AC54: 23 | AE54: 115 | AF54: 111 | AG54: 4 | AH54: 0 | AJ54: 10 | AL54: 9 | AM54: 1 | AN54: 3 | AO54: 5 | AQ54: 15 | AR54: 3 | AS54: 11 | AT54: 1 | AV54: 16 | AW54: 2 | AX54: 1 | AY54: 2 | AZ54: 11 | BA54: 0 | BC54: 10 | BD54: 10 | BE54: 0 | BF54: 15
A55: E09000006 | B55: Bromley | E55: 1084 | G55: 160 | I55: 15 | J55: 4 | K55: 6 | L55: 5 | M55: 8 | O55: 5 | Q55: 79 | R55: 54 | S55: 25 | T55: 0 | V55: 6 | W55: 4 | X55: 2 | Y55: 26 | AA55: 29 | AB55: 342 | AC55: 50 | AE55: 227 | AF55: 216 | AG55: 11 | AH55: 0 | AJ55: 93 | AL55: 32 | AM55: 17 | AN55: 3 | AO55: 12 | AQ55: 21 | AR55: 6 | AS55: 6 | AT55: 9 | AV55: 28 | AW55: 24 | AX55: 3 | AY55: 0 | AZ55: 1 | BA55: 0 | BC55: 39 | BD55: 10 | BE55: 0 | BF55: 53
A56: E07000234 | B56: Bromsgrove | E56: 172 | G56: 8 | I56: 0 | J56: 0 | K56: 0 | L56: 0 | M56: 0 | O56: 0 | Q56: 7 | R56: 4 | S56: 3 | T56: 0 | V56: 0 | W56: 0 | X56: 0 | Y56: 1 | AA56: 3 | AB56: 56 | AC56: 15 | AE56: 62 | AF56: 61 | AG56: 1 | AH56: 0 | AJ56: 3 | AL56: 5 | AM56: 0 | AN56: 4 | AO56: 1 | AQ56: 3 | AR56: 0 | AS56: 2 | AT56: 1 | AV56: 10 | AW56: 4 | AX56: 0 | AY56: 0 | AZ56: 6 | BA56: 0 | BC56: 0 | BD56: 3 | BE56: 0 | BF56: 4
A57: E07000095 | B57: Broxbourne | E57: 326 | G57: 23 | I57: 0 | J57: 1 | K57: 1 | L57: 0 | M57: 1 | O57: 0 | Q57: 15 | R57: 14 | S57: 1 | T57: 0 | V57: 0 | W57: 0 | X57: 0 | Y57: 5 | AA57: 8 | AB57: 114 | AC57: 20 | AE57: 46 | AF57: 42 | AG57: 4 | AH57: 0 | AJ57: 10 | AL57: 1 | AM57: 0 | AN57: 0 | AO57: 1 | AQ57: 6 | AR57: 0 | AS57: 4 | AT57: 2 | AV57: 25 | AW57: 11 | AX57: 6 | AY57: 3 | AZ57: 5 | BA57: 0 | BC57: 48 | BD57: 10 | BE57: 0 | BF57: 15
A58: E07000172 | B58: Broxtowe | E58: 114 | G58: 19 | I58: 2 | J58: 1 | K58: 0 | L58: 0 | M58: 3 | O58: 2 | Q58: 5 | R58: 0 | S58: 5 | T58: 0 | V58: 0 | W58: 0 | X58: 0 | Y58: 6 | AA58: 1 | AB58: 30 | AC58: 10 | AE58: 22 | AF58: 19 | AG58: 3 | AH58: 0 | AJ58: 2 | AL58: 4 | AM58: 0 | AN58: 1 | AO58: 3 | AQ58: 7 | AR58: 0 | AS58: 4 | AT58: 3 | AV58: 4 | AW58: 2 | AX58: 0 | AY58: 1 | AZ58: 1 | BA58: 0 | BC58: 6 | BD58: 1 | BE58: 0 | BF58: 8
A59: E06000060 | B59: Buckinghamshire | E59: 741 | G59: 54 | I59: 3 | J59: 1 | K59: 0 | L59: 0 | M59: 9 | O59: 2 | Q59: 18 | R59: 9 | S59: 9 | T59: 0 | V59: 2 | W59: 4 | X59: 6 | Y59: 9 | AA59: 29 | AB59: 226 | AC59: 43 | AE59: 126 | AF59: 106 | AG59: 20 | AH59: 0 | AJ59: 29 | AL59: 22 | AM59: 9 | AN59: 8 | AO59: 5 | AQ59: 47 | AR59: 12 | AS59: 25 | AT59: 10 | AV59: 71 | AW59: 53 | AX59: 8 | AY59: 8 | AZ59: 2 | BA59: 0 | BC59: 11 | BD59: 12 | BE59: 2 | BF59: 69
A60: E07000117 | B60: Burnley | E60: 395 | G60: 25 | I60: 7 | J60: 2 | K60: 0 | L60: 0 | M60: 1 | O60: 1 | Q60: 7 | R60: 6 | S60: 1 | T60: 0 | V60: 0 | W60: 0 | X60: 3 | Y60: 4 | AA60: 8 | AB60: 128 | AC60: 59 | AE60: 26 | AF60: 21 | AG60: 5 | AH60: 0 | AJ60: 2 | AL60: 10 | AM60: 1 | AN60: 5 | AO60: 4 | AQ60: 22 | AR60: 1 | AS60: 14 | AT60: 7 | AV60: 46 | AW60: 39 | AX60: 2 | AY60: 4 | AZ60: 1 | BA60: 0 | BC60: 47 | BD60: 3 | BE60: 1 | BF60: 18
A61: E08000002 | B61: Bury | E61: .. | G61: .. | I61: .. | J61: .. | K61: .. | L61: .. | M61: .. | O61: .. | Q61: .. | R61: .. | S61: .. | T61: .. | V61: .. | W61: .. | X61: .. | Y61: .. | AA61: .. | AB61: .. | AC61: .. | AE61: .. | AF61: .. | AG61: .. | AH61: .. | AJ61: .. | AL61: .. | AM61: .. | AN61: .. | AO61: .. | AQ61: .. | AR61: .. | AS61: .. | AT61: .. | AV61: .. | AW61: .. | AX61: .. | AY61: .. | AZ61: .. | BA61: .. | BC61: .. | BD61: .. | BE61: .. | BF61: ..
A62: E08000033 | B62: Calderdale | E62: 340 | G62: 32 | I62: 1 | J62: 0 | K62: 1 | L62: 0 | M62: 3 | O62: 5 | Q62: 7 | R62: 3 | S62: 4 | T62: 0 | V62: 1 | W62: 4 | X62: 6 | Y62: 4 | AA62: 12 | AB62: 89 | AC62: 22 | AE62: 73 | AF62: 73 | AG62: 0 | AH62: 0 | AJ62: 14 | AL62: 7 | AM62: 3 | AN62: 1 | AO62: 3 | AQ62: 13 | AR62: 0 | AS62: 11 | AT62: 2 | AV62: 25 | AW62: 21 | AX62: 2 | AY62: 2 | AZ62: 0 | BA62: 0 | BC62: 25 | BD62: 5 | BE62: 0 | BF62: 23
A63: E07000008 | B63: Cambridge | E63: 487 | G63: 32 | I63: 5 | J63: 0 | K63: 1 | L63: 0 | M63: 2 | O63: 0 | Q63: 15 | R63: 8 | S63: 7 | T63: 0 | V63: 2 | W63: 0 | X63: 1 | Y63: 6 | AA63: 17 | AB63: 103 | AC63: 30 | AE63: 95 | AF63: 90 | AG63: 5 | AH63: 0 | AJ63: 19 | AL63: 10 | AM63: 1 | AN63: 4 | AO63: 5 | AQ63: 49 | AR63: 10 | AS63: 34 | AT63: 5 | AV63: 47 | AW63: 38 | AX63: 2 | AY63: 2 | AZ63: 5 | BA63: 0 | BC63: 9 | BD63: 11 | BE63: 1 | BF63: 64
A64: E09000007 | B64: Camden | E64: .. | G64: .. | I64: .. | J64: .. | K64: .. | L64: .. | M64: .. | O64: .. | Q64: .. | R64: .. | S64: .. | T64: .. | V64: .. | W64: .. | X64: .. | Y64: .. | AA64: .. | AB64: .. | AC64: .. | AE64: .. | AF64: .. | AG64: .. | AH64: .. | AJ64: .. | AL64: .. | AM64: .. | AN64: .. | AO64: .. | AQ64: .. | AR64: .. | AS64: .. | AT64: .. | AV64: .. | AW64: .. | AX64: .. | AY64: .. | AZ64: .. | BA64: .. | BC64: .. | BD64: .. | BE64: .. | BF64: ..
A65: E07000192 | B65: Cannock Chase | E65: 106 | G65: 18 | I65: 0 | J65: 0 | K65: 0 | L65: 0 | M65: 0 | O65: 0 | Q65: 13 | R65: 12 | S65: 1 | T65: 0 | V65: 2 | W65: 0 | X65: 1 | Y65: 2 | AA65: 5 | AB65: 32 | AC65: 11 | AE65: 22 | AF65: 18 | AG65: 4 | AH65: 0 | AJ65: 3 | AL65: 4 | AM65: 2 | AN65: 2 | AO65: 0 | AQ65: 3 | AR65: 0 | AS65: 1 | AT65: 2 | AV65: 5 | AW65: 5 | AX65: 0 | AY65: 0 | AZ65: 0 | BA65: 0 | BC65: 0 | BD65: 1 | BE65: 0 | BF65: 2
A66: E07000106 | B66: Canterbury | E66: .. | G66: .. | I66: .. | J66: .. | K66: .. | L66: .. | M66: .. | O66: .. | Q66: .. | R66: .. | S66: .. | T66: .. | V66: .. | W66: .. | X66: .. | Y66: .. | AA66: .. | AB66: .. | AC66: .. | AE66: .. | AF66: .. | AG66: .. | AH66: .. | AJ66: .. | AL66: .. | AM66: .. | AN66: .. | AO66: .. | AQ66: .. | AR66: .. | AS66: .. | AT66: .. | AV66: .. | AW66: .. | AX66: .. | AY66: .. | AZ66: .. | BA66: .. | BC66: .. | BD66: .. | BE66: .. | BF66: ..
A67: E07000069 | B67: Castle Point | E67: 129 | G67: 25 | I67: 2 | J67: 0 | K67: 3 | L67: 0 | M67: 2 | O67: 0 | Q67: 14 | R67: 10 | S67: 4 | T67: 0 | V67: 0 | W67: 0 | X67: 1 | Y67: 3 | AA67: 2 | AB67: 49 | AC67: 10 | AE67: 13 | AF67: 9 | AG67: 4 | AH67: 0 | AJ67: 2 | AL67: 4 | AM67: 2 | AN67: 1 | AO67: 1 | AQ67: 4 | AR67: 0 | AS67: 2 | AT67: 2 | AV67: 7 | AW67: 6 | AX67: 0 | AY67: 0 | AZ67: 1 | BA67: 0 | BC67: 0 | BD67: 2 | BE67: 1 | BF67: 10
A68: E06000056 | B68: Central Bedfordshire | E68: 573 | G68: 40 | I68: 3 | J68: 1 | K68: 1 | L68: 0 | M68: 7 | O68: 5 | Q68: 14 | R68: 10 | S68: 4 | T68: 0 | V68: 0 | W68: 1 | X68: 1 | Y68: 7 | AA68: 21 | AB68: 155 | AC68: 65 | AE68: 138 | AF68: 124 | AG68: 14 | AH68: 0 | AJ68: 28 | AL68: 15 | AM68: 8 | AN68: 3 | AO68: 4 | AQ68: 23 | AR68: 2 | AS68: 13 | AT68: 8 | AV68: 30 | AW68: 21 | AX68: 2 | AY68: 1 | AZ68: 6 | BA68: 0 | BC68: 23 | BD68: 6 | BE68: 2 | BF68: 27
A69: E07000130 | B69: Charnwood | E69: 426 | G69: 67 | I69: 6 | J69: 2 | K69: 2 | L69: 0 | M69: 7 | O69: 2 | Q69: 29 | R69: 25 | S69: 4 | T69: 0 | V69: 0 | W69: 0 | X69: 2 | Y69: 17 | AA69: 9 | AB69: 116 | AC69: 36 | AE69: 42 | AF69: 37 | AG69: 5 | AH69: 0 | AJ69: 17 | AL69: 12 | AM69: 3 | AN69: 2 | AO69: 7 | AQ69: 34 | AR69: 3 | AS69: 22 | AT69: 9 | AV69: 26 | AW69: 15 | AX69: 4 | AY69: 3 | AZ69: 4 | BA69: 0 | BC69: 25 | BD69: 5 | BE69: 0 | BF69: 37
A70: E07000070 | B70: Chelmsford | E70: 485 | G70: 27 | I70: 3 | J70: 1 | K70: 0 | L70: 0 | M70: 1 | O70: 0 | Q70: 14 | R70: 11 | S70: 3 | T70: 0 | V70: 0 | W70: 2 | X70: 0 | Y70: 6 | AA70: 13 | AB70: 104 | AC70: 49 | AE70: 128 | AF70: 123 | AG70: 5 | AH70: 0 | AJ70: 25 | AL70: 13 | AM70: 2 | AN70: 4 | AO70: 7 | AQ70: 19 | AR70: 4 | AS70: 9 | AT70: 6 | AV70: 33 | AW70: 28 | AX70: 2 | AY70: 2 | AZ70: 1 | BA70: 0 | BC70: 44 | BD70: 7 | BE70: 1 | BF70: 22
A71: E07000078 | B71: Cheltenham | E71: 313 | G71: 28 | I71: 4 | J71: 0 | K71: 0 | L71: 0 | M71: 0 | O71: 1 | Q71: 6 | R71: 5 | S71: 1 | T71: 0 | V71: 0 | W71: 0 | X71: 7 | Y71: 10 | AA71: 8 | AB71: 65 | AC71: 21 | AE71: 39 | AF71: 32 | AG71: 7 | AH71: 0 | AJ71: 7 | AL71: 17 | AM71: 4 | AN71: 2 | AO71: 11 | AQ71: 53 | AR71: 4 | AS71: 43 | AT71: 6 | AV71: 26 | AW71: 22 | AX71: 1 | AY71: 3 | AZ71: 0 | BA71: 0 | BC71: 28 | BD71: 5 | BE71: 0 | BF71: 16
A72: E07000177 | B72: Cherwell | E72: 249 | G72: 20 | I72: 1 | J72: 0 | K72: 0 | L72: 0 | M72: 4 | O72: 2 | Q72: 5 | R72: 1 | S72: 4 | T72: 0 | V72: 0 | W72: 0 | X72: 2 | Y72: 6 | AA72: 7 | AB72: 81 | AC72: 14 | AE72: 48 | AF72: 46 | AG72: 2 | AH72: 0 | AJ72: 11 | AL72: 6 | AM72: 4 | AN72: 1 | AO72: 1 | AQ72: 9 | AR72: 1 | AS72: 6 | AT72: 2 | AV72: 7 | AW72: 7 | AX72: 0 | AY72: 0 | AZ72: 0 | BA72: 0 | BC72: 14 | BD72: 3 | BE72: 3 | BF72: 26
A73: E06000049 | B73: Cheshire East | E73: 746 | G73: 51 | I73: 1 | J73: 0 | K73: 6 | L73: 1 | M73: 5 | O73: 0 | Q73: 25 | R73: 15 | S73: 10 | T73: 0 | V73: 0 | W73: 3 | X73: 4 | Y73: 6 | AA73: 26 | AB73: 220 | AC73: 36 | AE73: 92 | AF73: 53 | AG73: 39 | AH73: 0 | AJ73: 8 | AL73: 20 | AM73: 7 | AN73: 3 | AO73: 10 | AQ73: 97 | AR73: 7 | AS73: 71 | AT73: 19 | AV73: 83 | AW73: 72 | AX73: 3 | AY73: 7 | AZ73: 1 | BA73: 0 | BC73: 57 | BD73: 1 | BE73: 4 | BF73: 51
A74: E06000050 | B74: Cheshire West & Chester | E74: 830 | G74: 70 | I74: 5 | J74: 2 | K74: 4 | L74: 0 | M74: 3 | O74: 7 | Q74: 13 | R74: 11 | S74: 2 | T74: 0 | V74: 0 | W74: 3 | X74: 13 | Y74: 20 | AA74: 12 | AB74: 209 | AC74: 74 | AE74: 153 | AF74: 131 | AG74: 22 | AH74: 0 | AJ74: 35 | AL74: 46 | AM74: 13 | AN74: 8 | AO74: 25 | AQ74: 56 | AR74: 2 | AS74: 36 | AT74: 18 | AV74: 59 | AW74: 49 | AX74: 6 | AY74: 3 | AZ74: 1 | BA74: 0 | BC74: 61 | BD74: 4 | BE74: 5 | BF74: 46
A75: E07000034 | B75: Chesterfield | E75: 374 | G75: 26 | I75: 4 | J75: 2 | K75: 0 | L75: 0 | M75: 1 | O75: 0 | Q75: 11 | R75: 8 | S75: 3 | T75: 0 | V75: 1 | W75: 0 | X75: 4 | Y75: 3 | AA75: 2 | AB75: 131 | AC75: 34 | AE75: 67 | AF75: 55 | AG75: 12 | AH75: 0 | AJ75: 16 | AL75: 17 | AM75: 4 | AN75: 8 | AO75: 5 | AQ75: 37 | AR75: 3 | AS75: 32 | AT75: 2 | AV75: 18 | AW75: 14 | AX75: 2 | AY75: 2 | AZ75: 0 | BA75: 0 | BC75: 8 | BD75: 3 | BE75: 0 | BF75: 15
A76: E07000225 | B76: Chichester | E76: 241 | G76: 15 | I76: 1 | J76: 1 | K76: 0 | L76: 0 | M76: 0 | O76: 3 | Q76: 4 | R76: 2 | S76: 2 | T76: 0 | V76: 0 | W76: 1 | X76: 2 | Y76: 3 | AA76: 14 | AB76: 64 | AC76: 19 | AE76: 52 | AF76: 43 | AG76: 9 | AH76: 0 | AJ76: 9 | AL76: 11 | AM76: 4 | AN76: 3 | AO76: 4 | AQ76: 11 | AR76: 0 | AS76: 11 | AT76: 0 | AV76: 15 | AW76: 9 | AX76: 1 | AY76: 1 | AZ76: 4 | BA76: 0 | BC76: 9 | BD76: 1 | BE76: 0 | BF76: 21
A77: E07000118 | B77: Chorley | E77: 292 | G77: 13 | I77: 1 | J77: 1 | K77: 0 | L77: 0 | M77: 2 | O77: 1 | Q77: 2 | R77: 2 | S77: 0 | T77: 0 | V77: 0 | W77: 1 | X77: 1 | Y77: 4 | AA77: 3 | AB77: 86 | AC77: 32 | AE77: 39 | AF77: 27 | AG77: 12 | AH77: 0 | AJ77: 0 | AL77: 11 | AM77: 2 | AN77: 2 | AO77: 7 | AQ77: 26 | AR77: 0 | AS77: 26 | AT77: 0 | AV77: 29 | AW77: 25 | AX77: 1 | AY77: 1 | AZ77: 2 | BA77: 0 | BC77: 24 | BD77: 4 | BE77: 0 | BF77: 25
A78: E09000001 | B78: City of London | E78: 26 | G78: 2 | I78: 1 | J78: 0 | K78: 0 | L78: 0 | M78: 0 | O78: 0 | Q78: 1 | R78: 1 | S78: 0 | T78: 0 | V78: 0 | W78: 0 | X78: 0 | Y78: 0 | AA78: 2 | AB78: 5 | AC78: 1 | AE78: 7 | AF78: 6 | AG78: 1 | AH78: 0 | AJ78: 0 | AL78: 1 | AM78: 1 | AN78: 0 | AO78: 0 | AQ78: 4 | AR78: 0 | AS78: 3 | AT78: 1 | AV78: 2 | AW78: 2 | AX78: 0 | AY78: 0 | AZ78: 0 | BA78: 0 | BC78: 1 | BD78: 0 | BE78: 0 | BF78: 1
... A83: E07000226 | B83: Crawley | E83: 581 | G83: 48 | I83: 2 | J83: 0 | K83: 1 | L83: 2 | M83: 6 | O83: 3 | Q83: 15 | R83: 6 | S83: 9 | T83: 0 | V83: 0 | W83: 3 | X83: 4 | Y83: 12 | AA83: 24 | AB83: 170 | AC83: 26 | AE83: 78 | AF83: 72 | AG83: 6 | AH83: 0 | AJ83: 15 | AL83: 14 | AM83: 4 | AN83: 3 | AO83: 7 | AQ83: 12 | AR83: 2 | AS83: 6 | AT83: 4 | AV83: 13 | AW83: 5 | AX83: 2 | AY83: 0 | AZ83: 6 | BA83: 0 | BC83: 48 | BD83: 1 | BE83: 0 | BF83: 132
A84: E09000008 | B84: Croydon | E84: .. | G84: .. | I84: .. | J84: .. | K84: .. | L84: .. | M84: .. | O84: .. | Q84: .. | R84: .. | S84: .. | T84: .. | V84: .. | W84: .. | X84: .. | Y84: .. | AA84: .. | AB84: .. | AC84: .. | AE84: .. | AF84: .. | AG84: .. | AH84: .. | AJ84: .. | AL84: .. | AM84: .. | AN84: .. | AO84: .. | AQ84: .. | AR84: .. | AS84: .. | AT84: .. | AV84: .. | AW84: .. | AX84: .. | AY84: .. | AZ84: .. | BA84: .. | BC84: .. | BD84: .. | BE84: .. | BF84: ..
A85: E06000063 | B85: Cumberland Council | E85: 760 | G85: 56 | I85: 3 | J85: 0 | K85: 0 | L85: 0 | M85: 5 | O85: 3 | Q85: 21 | R85: 17 | S85: 4 | T85: 0 | V85: 3 | W85: 4 | X85: 3 | Y85: 14 | AA85: 17 | AB85: 236 | AC85: 107 | AE85: 103 | AF85: 79 | AG85: 24 | AH85: 0 | AJ85: 7 | AL85: 31 | AM85: 4 | AN85: 6 | AO85: 21 | AQ85: 39 | AR85: 3 | AS85: 29 | AT85: 7 | AV85: 63 | AW85: 56 | AX85: 1 | AY85: 1 | AZ85: 5 | BA85: 0 | BC85: 23 | BD85: 5 | BE85: 4 | BF85: 69
A86: E07000096 | B86: Dacorum | E86: 424 | G86: 29 | I86: 2 | J86: 3 | K86: 0 | L86: 0 | M86: 4 | O86: 1 | Q86: 12 | R86: 10 | S86: 2 | T86: 0 | V86: 0 | W86: 2 | X86: 0 | Y86: 5 | AA86: 8 | AB86: 121 | AC86: 23 | AE86: 109 | AF86: 99 | AG86: 10 | AH86: 0 | AJ86: 6 | AL86: 14 | AM86: 4 | AN86: 6 | AO86: 4 | AQ86: 10 | AR86: 2 | AS86: 7 | AT86: 1 | AV86: 14 | AW86: 8 | AX86: 1 | AY86: 2 | AZ86: 3 | BA86: 0 | BC86: 62 | BD86: 5 | BE86: 0 | BF86: 23
A87: E06000005 | B87: Darlington | E87: 595 | G87: 76 | I87: 10 | J87: 0 | K87: 3 | L87: 0 | M87: 2 | O87: 4 | Q87: 14 | R87: 11 | S87: 3 | T87: 0 | V87: 0 | W87: 4 | X87: 8 | Y87: 31 | AA87: 11 | AB87: 204 | AC87: 71 | AE87: 74 | AF87: 63 | AG87: 11 | AH87: 0 | AJ87: 9 | AL87: 24 | AM87: 12 | AN87: 5 | AO87: 7 | AQ87: 36 | AR87: 5 | AS87: 13 | AT87: 18 | AV87: 37 | AW87: 34 | AX87: 1 | AY87: 1 | AZ87: 1 | BA87: 0 | BC87: 2 | BD87: 1 | BE87: 1 | BF87: 49
A88: E07000107 | B88: Dartford | E88: 310 | G88: 40 | I88: 2 | J88: 0 | K88: 1 | L88: 1 | M88: 7 | O88: 2 | Q88: 12 | R88: 8 | S88: 4 | T88: 0 | V88: 0 | W88: 2 | X88: 1 | Y88: 12 | AA88: 11 | AB88: 79 | AC88: 22 | AE88: 80 | AF88: 73 | AG88: 7 | AH88: 0 | AJ88: 10 | AL88: 9 | AM88: 4 | AN88: 0 | AO88: 5 | AQ88: 7 | AR88: 2 | AS88: 2 | AT88: 3 | AV88: 16 | AW88: 12 | AX88: 1 | AY88: 0 | AZ88: 3 | BA88: 0 | BC88: 1 | BD88: 5 | BE88: 0 | BF88: 30
A89: E06000015 | B89: Derby | E89: 1169 | G89: 103 | I89: 16 | J89: 3 | K89: 5 | L89: 0 | M89: 6 | O89: 4 | Q89: 26 | R89: 16 | S89: 10 | T89: 0 | V89: 1 | W89: 4 | X89: 17 | Y89: 21 | AA89: 8 | AB89: 329 | AC89: 71 | AE89: 145 | AF89: 128 | AG89: 17 | AH89: 0 | AJ89: 23 | AL89: 22 | AM89: 5 | AN89: 6 | AO89: 11 | AQ89: 147 | AR89: 14 | AS89: 91 | AT89: 42 | AV89: 107 | AW89: 85 | AX89: 10 | AY89: 5 | AZ89: 7 | BA89: 0 | BC89: 172 | BD89: 6 | BE89: 1 | BF89: 35
A90: E07000035 | B90: Derbyshire Dales | E90: 76 | G90: 4 | I90: 1 | J90: 0 | K90: 0 | L90: 0 | M90: 0 | O90: 0 | Q90: 0 | R90: 0 | S90: 0 | T90: 0 | V90: 0 | W90: 0 | X90: 0 | Y90: 3 | AA90: 3 | AB90: 17 | AC90: 16 | AE90: 16 | AF90: 15 | AG90: 1 | AH90: 0 | AJ90: 0 | AL90: 3 | AM90: 0 | AN90: 1 | AO90: 2 | AQ90: 4 | AR90: 0 | AS90: 3 | AT90: 1 | AV90: 5 | AW90: 5 | AX90: 0 | AY90: 0 | AZ90: 0 | BA90: 0 | BC90: 0 | BD90: 2 | BE90: 0 | BF90: 6
A91: E08000017 | B91: Doncaster | E91: 927 | G91: 92 | I91: 10 | J91: 3 | K91: 4 | L91: 1 | M91: 3 | O91: 5 | Q91: 26 | R91: 19 | S91: 7 | T91: 0 | V91: 0 | W91: 3 | X91: 18 | Y91: 19 | AA91: 15 | AB91: 217 | AC91: 68 | AE91: 211 | AF91: 185 | AG91: 26 | AH91: 0 | AJ91: 88 | AL91: 28 | AM91: 4 | AN91: 2 | AO91: 22 | AQ91: 84 | AR91: 1 | AS91: 49 | AT91: 34 | AV91: 46 | AW91: 43 | AX91: 3 | AY91: 0 | AZ91: 0 | BA91: 0 | BC91: 51 | BD91: 3 | BE91: 0 | BF91: 24
A92: E06000059 | B92: Dorset | E92: 411 | G92: 44 | I92: 3 | J92: 0 | K92: 0 | L92: 0 | M92: 8 | O92: 2 | Q92: 19 | R92: 7 | S92: 12 | T92: 0 | V92: 0 | W92: 2 | X92: 4 | Y92: 6 | AA92: 17 | AB92: 122 | AC92: 30 | AE92: 77 | AF92: 51 | AG92: 26 | AH92: 0 | AJ92: 7 | AL92: 8 | AM92: 4 | AN92: 1 | AO92: 3 | AQ92: 18 | AR92: 0 | AS92: 13 | AT92: 5 | AV92: 31 | AW92: 22 | AX92: 7 | AY92: 1 | AZ92: 1 | BA92: 0 | BC92: 0 | BD92: 9 | BE92: 1 | BF92: 47
A93: E07000108 | B93: Dover | E93: 331 | G93: 33 | I93: 0 | J93: 0 | K93: 1 | L93: 0 | M93: 6 | O93: 2 | Q93: 14 | R93: 4 | S93: 10 | T93: 0 | V93: 0 | W93: 1 | X93: 2 | Y93: 7 | AA93: 17 | AB93: 104 | AC93: 36 | AE93: 53 | AF93: 47 | AG93: 6 | AH93: 0 | AJ93: 10 | AL93: 7 | AM93: 3 | AN93: 1 | AO93: 3 | AQ93: 5 | AR93: 0 | AS93: 3 | AT93: 2 | AV93: 23 | AW93: 15 | AX93: 1 | AY93: 3 | AZ93: 4 | BA93: 0 | BC93: 0 | BD93: 12 | BE93: 2 | BF93: 29
A94: E08000027 | B94: Dudley | E94: 1877 | G94: 167 | I94: 4 | J94: 0 | K94: 2 | L94: 0 | M94: 13 | O94: 2 | Q94: 43 | R94: 13 | S94: 30 | T94: 0 | V94: 3 | W94: 4 | X94: 0 | Y94: 96 | AA94: 63 | AB94: 728 | AC94: 177 | AE94: 154 | AF94: 132 | AG94: 22 | AH94: 0 | AJ94: 35 | AL94: 39 | AM94: 11 | AN94: 2 | AO94: 26 | AQ94: 66 | AR94: 3 | AS94: 19 | AT94: 44 | AV94: 104 | AW94: 66 | AX94: 16 | AY94: 17 | AZ94: 5 | BA94: 0 | BC94: 82 | BD94: 12 | BE94: 24 | BF94: 226
A95: E06000047 | B95: Durham | E95: 2184 | G95: 196 | I95: 25 | J95: 1 | K95: 1 | L95: 1 | M95: 23 | O95: 11 | Q95: 84 | R95: 72 | S95: 12 | T95: 0 | V95: 3 | W95: 6 | X95: 10 | Y95: 31 | AA95: 28 | AB95: 841 | AC95: 252 | AE95: 275 | AF95: 248 | AG95: 27 | AH95: 0 | AJ95: 97 | AL95: 58 | AM95: 27 | AN95: 15 | AO95: 16 | AQ95: 160 | AR95: 9 | AS95: 99 | AT95: 52 | AV95: 184 | AW95: 132 | AX95: 31 | AY95: 21 | AZ95: 0 | BA95: 0 | BC95: 5 | BD95: 10 | BE95: 1 | BF95: 77
A96: E09000009 | B96: Ealing | E96: 1499 | G96: 371 | I96: 12 | J96: 17 | K96: 8 | L96: 8 | M96: 11 | O96: 7 | Q96: 206 | R96: 86 | S96: 120 | T96: 0 | V96: 4 | W96: 22 | X96: 15 | Y96: 61 | AA96: 81 | AB96: 433 | AC96: 19 | AE96: 111 | AF96: 101 | AG96: 10 | AH96: 0 | AJ96: 28 | AL96: 18 | AM96: 9 | AN96: 7 | AO96: 2 | AQ96: 35 | AR96: 2 | AS96: 11 | AT96: 22 | AV96: 82 | AW96: 46 | AX96: 14 | AY96: 20 | AZ96: 2 | BA96: 0 | BC96: 255 | BD96: 18 | BE96: 1 | BF96: 47
... A102: E06000011 | B102: East Riding of Yorkshire | E102: 914 | G102: 151 | I102: 14 | J102: 3 | K102: 5 | L102: 3 | M102: 5 | O102: 2 | Q102: 78 | R102: 66 | S102: 12 | T102: 0 | V102: 3 | W102: 3 | X102: 4 | Y102: 31 | AA102: 29 | AB102: 204 | AC102: 132 | AE102: 210 | AF102: 194 | AG102: 16 | AH102: 0 | AJ102: 18 | AL102: 38 | AM102: 13 | AN102: 6 | AO102: 19 | AQ102: 14 | AR102: 2 | AS102: 3 | AT102: 9 | AV102: 31 | AW102: 24 | AX102: 4 | AY102: 1 | AZ102: 2 | BA102: 0 | BC102: 6 | BD102: 16 | BE102: 3 | BF102: 62
A103: E07000193 | B103: East Staffordshire | E103: .. | G103: .. | I103: .. | J103: .. | K103: .. | L103: .. | M103: .. | O103: .. | Q103: .. | R103: .. | S103: .. | T103: .. | V103: .. | W103: .. | X103: .. | Y103: .. | AA103: .. | AB103: .. | AC103: .. | AE103: .. | AF103: .. | AG103: .. | AH103: .. | AJ103: .. | AL103: .. | AM103: .. | AN103: .. | AO103: .. | AQ103: .. | AR103: .. | AS103: .. | AT103: .. | AV103: .. | AW103: .. | AX103: .. | AY103: .. | AZ103: .. | BA103: .. | BC103: .. | BD103: .. | BE103: .. | BF103: ..
A104: E07000244 | B104: East Suffolk | E104: 528 | G104: 54 | I104: 2 | J104: 1 | K104: 4 | L104: 2 | M104: 4 | O104: 5 | Q104: 11 | R104: 8 | S104: 3 | T104: 0 | V104: 1 | W104: 0 | X104: 5 | Y104: 19 | AA104: 18 | AB104: 136 | AC104: 61 | AE104: 98 | AF104: 83 | AG104: 15 | AH104: 0 | AJ104: 19 | AL104: 16 | AM104: 3 | AN104: 3 | AO104: 10 | AQ104: 60 | AR104: 1 | AS104: 45 | AT104: 14 | AV104: 14 | AW104: 9 | AX104: 3 | AY104: 2 | AZ104: 0 | BA104: 0 | BC104: 3 | BD104: 8 | BE104: 0 | BF104: 41
A105: E07000061 | B105: Eastbourne | E105: 439 | G105: 57 | I105: 1 | J105: 1 | K105: 1 | L105: 1 | M105: 3 | O105: 2 | Q105: 16 | R105: 13 | S105: 3 | T105: 0 | V105: 2 | W105: 6 | X105: 2 | Y105: 22 | AA105: 26 | AB105: 97 | AC105: 34 | AE105: 82 | AF105: 70 | AG105: 12 | AH105: 0 | AJ105: 9 | AL105: 14 | AM105: 4 | AN105: 3 | AO105: 7 | AQ105: 15 | AR105: 1 | AS105: 8 | AT105: 6 | AV105: 20 | AW105: 8 | AX105: 2 | AY105: 2 | AZ105: 8 | BA105: 0 | BC105: 9 | BD105: 4 | BE105: 7 | BF105: 65
A106: E07000086 | B106: Eastleigh | E106: 122 | G106: 14 | I106: 1 | J106: 0 | K106: 0 | L106: 0 | M106: 2 | O106: 2 | Q106: 2 | R106: 0 | S106: 2 | T106: 0 | V106: 0 | W106: 0 | X106: 2 | Y106: 5 | AA106: 3 | AB106: 30 | AC106: 13 | AE106: 22 | AF106: 19 | AG106: 3 | AH106: 0 | AJ106: 0 | AL106: 4 | AM106: 1 | AN106: 0 | AO106: 3 | AQ106: 15 | AR106: 0 | AS106: 11 | AT106: 4 | AV106: 13 | AW106: 6 | AX106: 2 | AY106: 0 | AZ106: 5 | BA106: 0 | BC106: 0 | BD106: 0 | BE106: 0 | BF106: 8
A107: E07000207 | B107: Elmbridge | E107: 129 | G107: 13 | I107: 1 | J107: 0 | K107: 0 | L107: 1 | M107: 4 | O107: 0 | Q107: 5 | R107: 4 | S107: 1 | T107: 0 | V107: 0 | W107: 0 | X107: 0 | Y107: 2 | AA107: 4 | AB107: 36 | AC107: 2 | AE107: 31 | AF107: 25 | AG107: 6 | AH107: 0 | AJ107: 6 | AL107: 4 | AM107: 2 | AN107: 2 | AO107: 0 | AQ107: 9 | AR107: 0 | AS107: 3 | AT107: 6 | AV107: 10 | AW107: 6 | AX107: 0 | AY107: 0 | AZ107: 4 | BA107: 0 | BC107: 0 | BD107: 1 | BE107: 4 | BF107: 9
A108: E09000010 | B108: Enfield | E108: 1445 | G108: 459 | I108: 9 | J108: 19 | K108: 3 | L108: 13 | M108: 15 | O108: 2 | Q108: 161 | R108: 106 | S108: 55 | T108: 0 | V108: 7 | W108: 9 | X108: 3 | Y108: 218 | AA108: 47 | AB108: 500 | AC108: 41 | AE108: 115 | AF108: 111 | AG108: 4 | AH108: 0 | AJ108: 37 | AL108: 17 | AM108: 4 | AN108: 5 | AO108: 8 | AQ108: 71 | AR108: 5 | AS108: 17 | AT108: 49 | AV108: 44 | AW108: 33 | AX108: 5 | AY108: 5 | AZ108: 1 | BA108: 0 | BC108: 48 | BD108: 17 | BE108: 0 | BF108: 49
A109: E07000072 | B109: Epping Forest | E109: .. | G109: .. | I109: .. | J109: .. | K109: .. | L109: .. | M109: .. | O109: .. | Q109: .. | R109: .. | S109: .. | T109: .. | V109: .. | W109: .. | X109: .. | Y109: .. | AA109: .. | AB109: .. | AC109: .. | AE109: .. | AF109: .. | AG109: .. | AH109: .. | AJ109: .. | AL109: .. | AM109: .. | AN109: .. | AO109: .. | AQ109: .. | AR109: .. | AS109: .. | AT109: .. | AV109: .. | AW109: .. | AX109: .. | AY109: .. | AZ109: .. | BA109: .. | BC109: .. | BD109: .. | BE109: .. | BF109: ..
A110: E07000208 | B110: Epsom & Ewell | E110: 113 | G110: 23 | I110: 1 | J110: 1 | K110: 0 | L110: 1 | M110: 3 | O110: 0 | Q110: 11 | R110: 5 | S110: 6 | T110: 0 | V110: 0 | W110: 1 | X110: 1 | Y110: 4 | AA110: 0 | AB110: 36 | AC110: 6 | AE110: 18 | AF110: 17 | AG110: 1 | AH110: 0 | AJ110: 8 | AL110: 5 | AM110: 2 | AN110: 0 | AO110: 3 | AQ110: 1 | AR110: 0 | AS110: 1 | AT110: 0 | AV110: 5 | AW110: 2 | AX110: 1 | AY110: 0 | AZ110: 2 | BA110: 0 | BC110: 1 | BD110: 2 | BE110: 0 | BF110: 8
A111: E07000036 | B111: Erewash | E111: 296 | G111: 33 | I111: 4 | J111: 0 | K111: 0 | L111: 0 | M111: 7 | O111: 0 | Q111: 12 | R111: 11 | S111: 1 | T111: 0 | V111: 0 | W111: 0 | X111: 0 | Y111: 10 | AA111: 1 | AB111: 75 | AC111: 19 | AE111: 33 | AF111: 29 | AG111: 4 | AH111: 0 | AJ111: 8 | AL111: 6 | AM111: 1 | AN111: 1 | AO111: 4 | AQ111: 37 | AR111: 9 | AS111: 19 | AT111: 9 | AV111: 23 | AW111: 19 | AX111: 1 | AY111: 3 | AZ111: 0 | BA111: 0 | BC111: 45 | BD111: 1 | BE111: 0 | BF111: 15
A112: E07000041 | B112: Exeter | E112: 539 | G112: 42 | I112: 2 | J112: 1 | K112: 1 | L112: 1 | M112: 3 | O112: 5 | Q112: 9 | R112: 7 | S112: 2 | T112: 0 | V112: 0 | W112: 0 | X112: 9 | Y112: 11 | AA112: 21 | AB112: 107 | AC112: 29 | AE112: 67 | AF112: 53 | AG112: 14 | AH112: 0 | AJ112: 7 | AL112: 27 | AM112: 7 | AN112: 9 | AO112: 11 | AQ112: 133 | AR112: 7 | AS112: 105 | AT112: 21 | AV112: 39 | AW112: 27 | AX112: 4 | AY112: 2 | AZ112: 6 | BA112: 0 | BC112: 3 | BD112: 7 | BE112: 0 | BF112: 57
A113: E07000087 | B113: Fareham | E113: 203 | G113: 15 | I113: 0 | J113: 0 | K113: 1 | L113: 2 | M113: 1 | O113: 1 | Q113: 3 | R113: 1 | S113: 2 | T113: 0 | V113: 0 | W113: 1 | X113: 0 | Y113: 6 | AA113: 17 | AB113: 55 | AC113: 16 | AE113: 42 | AF113: 34 | AG113: 8 | AH113: 0 | AJ113: 4 | AL113: 5 | AM113: 2 | AN113: 2 | AO113: 1 | AQ113: 7 | AR113: 1 | AS113: 2 | AT113: 4 | AV113: 14 | AW113: 9 | AX113: 2 | AY113: 0 | AZ113: 3 | BA113: 0 | BC113: 1 | BD113: 3 | BE113: 0 | BF113: 24
A114: E07000010 | B114: Fenland | E114: 278 | G114: 29 | I114: 4 | J114: 0 | K114: 0 | L114: 0 | M114: 1 | O114: 2 | Q114: 13 | R114: 9 | S114: 4 | T114: 0 | V114: 0 | W114: 1 | X114: 3 | Y114: 5 | AA114: 10 | AB114: 80 | AC114: 31 | AE114: 46 | AF114: 43 | AG114: 3 | AH114: 0 | AJ114: 4 | AL114: 10 | AM114: 4 | AN114: 5 | AO114: 1 | AQ114: 31 | AR114: 2 | AS114: 21 | AT114: 8 | AV114: 18 | AW114: 14 | AX114: 1 | AY114: 1 | AZ114: 2 | BA114: 0 | BC114: 0 | BD114: 3 | BE114: 3 | BF114: 13
A115: E07000112 | B115: Folkestone & Hythe | E115: 264 | G115: 29 | I115: 4 | J115: 0 | K115: 0 | L115: 0 | M115: 1 | O115: 1 | Q115: 13 | R115: 1 | S115: 12 | T115: 0 | V115: 0 | W115: 0 | X115: 1 | Y115: 9 | AA115: 11 | AB115: 76 | AC115: 28 | AE115: 47 | AF115: 42 | AG115: 5 | AH115: 0 | AJ115: 2 | AL115: 5 | AM115: 3 | AN115: 0 | AO115: 2 | AQ115: 2 | AR115: 1 | AS115: 0 | AT115: 1 | AV115: 28 | AW115: 20 | AX115: 0 | AY115: 5 | AZ115: 3 | BA115: 0 | BC115: 0 | BD115: 13 | BE115: 2 | BF115: 21
A116: E07000080 | B116: Forest of Dean | E116: 132 | G116: 7 | I116: 0 | J116: 0 | K116: 0 | L116: 0 | M116: 1 | O116: 0 | Q116: 4 | R116: 3 | S116: 1 | T116: 0 | V116: 0 | W116: 1 | X116: 0 | Y116: 1 | AA116: 2 | AB116: 46 | AC116: 13 | AE116: 30 | AF116: 30 | AG116: 0 | AH116: 0 | AJ116: 1 | AL116: 5 | AM116: 3 | AN116: 1 | AO116: 1 | AQ116: 9 | AR116: 1 | AS116: 8 | AT116: 0 | AV116: 9 | AW116: 9 | AX116: 0 | AY116: 0 | AZ116: 0 | BA116: 0 | BC116: 0 | BD116: 1 | BE116: 2 | BF116: 7
A117: E07000119 | B117: Fylde | E117: 176 | G117: 31 | I117: 1 | J117: 0 | K117: 2 | L117: 0 | M117: 3 | O117: 3 | Q117: 12 | R117: 8 | S117: 4 | T117: 0 | V117: 0 | W117: 4 | X117: 3 | Y117: 3 | AA117: 4 | AB117: 42 | AC117: 23 | AE117: 18 | AF117: 14 | AG117: 4 | AH117: 0 | AJ117: 2 | AL117: 7 | AM117: 2 | AN117: 1 | AO117: 4 | AQ117: 7 | AR117: 0 | AS117: 2 | AT117: 5 | AV117: 11 | AW117: 4 | AX117: 2 | AY117: 4 | AZ117: 1 | BA117: 0 | BC117: 12 | BD117: 2 | BE117: 1 | BF117: 16
A118: E08000037 | B118: Gateshead | E118: 505 | G118: 35 | I118: 4 | J118: 0 | K118: 0 | L118: 1 | M118: 2 | O118: 1 | Q118: 12 | R118: 9 | S118: 3 | T118: 0 | V118: 1 | W118: 2 | X118: 0 | Y118: 12 | AA118: 3 | AB118: 106 | AC118: 36 | AE118: 116 | AF118: 101 | AG118: 15 | AH118: 0 | AJ118: 31 | AL118: 27 | AM118: 2 | AN118: 10 | AO118: 15 | AQ118: 35 | AR118: 4 | AS118: 17 | AT118: 14 | AV118: 33 | AW118: 32 | AX118: 1 | AY118: 0 | AZ118: 0 | BA118: 0 | BC118: 47 | BD118: 7 | BE118: 2 | BF118: 27
A119: E07000173 | B119: Gedling | E119: 164 | G119: 16 | I119: 1 | J119: 0 | K119: 0 | L119: 0 | M119: 2 | O119: 0 | Q119: 7 | R119: 6 | S119: 1 | T119: 0 | V119: 0 | W119: 0 | X119: 0 | Y119: 6 | AA119: 3 | AB119: 55 | AC119: 14 | AE119: 40 | AF119: 38 | AG119: 2 | AH119: 0 | AJ119: 4 | AL119: 3 | AM119: 0 | AN119: 2 | AO119: 1 | AQ119: 8 | AR119: 1 | AS119: 2 | AT119: 5 | AV119: 3 | AW119: 2 | AX119: 1 | AY119: 0 | AZ119: 0 | BA119: 0 | BC119: 0 | BD119: 7 | BE119: 1 | BF119: 10
A120: E07000081 | B120: Gloucester | E120: 686 | G120: 56 | I120: 4 | J120: 0 | K120: 2 | L120: 1 | M120: 6 | O120: 2 | Q120: 26 | R120: 18 | S120: 8 | T120: 0 | V120: 1 | W120: 3 | X120: 1 | Y120: 10 | AA120: 18 | AB120: 204 | AC120: 48 | AE120: 145 | AF120: 122 | AG120: 23 | AH120: 0 | AJ120: 15 | AL120: 9 | AM120: 3 | AN120: 2 | AO120: 4 | AQ120: 81 | AR120: 15 | AS120: 53 | AT120: 13 | AV120: 34 | AW120: 28 | AX120: 2 | AY120: 0 | AZ120: 4 | BA120: 0 | BC120: 35 | BD120: 1 | BE120: 1 | BF120: 39
A121: E07000088 | B121: Gosport | E121: 143 | G121: 11 | I121: 0 | J121: 1 | K121: 1 | L121: 1 | M121: 0 | O121: 0 | Q121: 4 | R121: 2 | S121: 2 | T121: 0 | V121: 0 | W121: 0 | X121: 0 | Y121: 4 | AA121: 4 | AB121: 53 | AC121: 13 | AE121: 23 | AF121: 19 | AG121: 4 | AH121: 0 | AJ121: 0 | AL121: 3 | AM121: 2 | AN121: 0 | AO121: 1 | AQ121: 6 | AR121: 0 | AS121: 6 | AT121: 0 | AV121: 13 | AW121: 11 | AX121: 0 | AY121: 1 | AZ121: 1 | BA121: 0 | BC121: 0 | BD121: 3 | BE121: 0 | BF121: 14
... A137: E09000016 | B137: Havering | E137: 978 | G137: 142 | I137: 12 | J137: 0 | K137: 6 | L137: 6 | M137: 2 | O137: 3 | Q137: 84 | R137: 62 | S137: 22 | T137: 0 | V137: 6 | W137: 3 | X137: 9 | Y137: 11 | AA137: 36 | AB137: 325 | AC137: 50 | AE137: 295 | AF137: 286 | AG137: 9 | AH137: 0 | AJ137: 12 | AL137: 20 | AM137: 10 | AN137: 5 | AO137: 5 | AQ137: 7 | AR137: 3 | AS137: 3 | AT137: 1 | AV137: 38 | AW137: 28 | AX137: 6 | AY137: 4 | AZ137: 0 | BA137: 0 | BC137: 26 | BD137: 8 | BE137: 0 | BF137: 19
A138: E06000019 | B138: Herefordshire | E138: .. | G138: .. | I138: .. | J138: .. | K138: .. | L138: .. | M138: .. | O138: .. | Q138: .. | R138: .. | S138: .. | T138: .. | V138: .. | W138: .. | X138: .. | Y138: .. | AA138: .. | AB138: .. | AC138: .. | AE138: .. | AF138: .. | AG138: .. | AH138: .. | AJ138: .. | AL138: .. | AM138: .. | AN138: .. | AO138: .. | AQ138: .. | AR138: .. | AS138: .. | AT138: .. | AV138: .. | AW138: .. | AX138: .. | AY138: .. | AZ138: .. | BA138: .. | BC138: .. | BD138: .. | BE138: .. | BF138: ..
A139: E07000098 | B139: Hertsmere | E139: 173 | G139: 17 | I139: 3 | J139: 1 | K139: 1 | L139: 0 | M139: 2 | O139: 1 | Q139: 4 | R139: 3 | S139: 1 | T139: 0 | V139: 0 | W139: 0 | X139: 0 | Y139: 5 | AA139: 0 | AB139: 74 | AC139: 13 | AE139: 16 | AF139: 12 | AG139: 4 | AH139: 0 | AJ139: 2 | AL139: 9 | AM139: 5 | AN139: 3 | AO139: 1 | AQ139: 14 | AR139: 2 | AS139: 9 | AT139: 3 | AV139: 11 | AW139: 9 | AX139: 1 | AY139: 1 | AZ139: 0 | BA139: 0 | BC139: 2 | BD139: 3 | BE139: 0 | BF139: 12
A140: E07000037 | B140: High Peak | E140: 173 | G140: 14 | I140: 0 | J140: 0 | K140: 0 | L140: 0 | M140: 1 | O140: 3 | Q140: 6 | R140: 6 | S140: 0 | T140: 0 | V140: 0 | W140: 0 | X140: 1 | Y140: 3 | AA140: 2 | AB140: 47 | AC140: 32 | AE140: 31 | AF140: 28 | AG140: 3 | AH140: 0 | AJ140: 2 | AL140: 2 | AM140: 0 | AN140: 0 | AO140: 2 | AQ140: 15 | AR140: 1 | AS140: 3 | AT140: 11 | AV140: 7 | AW140: 6 | AX140: 1 | AY140: 0 | AZ140: 0 | BA140: 0 | BC140: 0 | BD140: 6 | BE140: 0 | BF140: 15
A141: E09000017 | B141: Hillingdon | E141: 1359 | G141: 159 | I141: 4 | J141: 2 | K141: 2 | L141: 3 | M141: 5 | O141: 1 | Q141: 95 | R141: 62 | S141: 33 | T141: 0 | V141: 1 | W141: 2 | X141: 1 | Y141: 43 | AA141: 41 | AB141: 197 | AC141: 31 | AE141: 121 | AF141: 112 | AG141: 9 | AH141: 0 | AJ141: 17 | AL141: 11 | AM141: 3 | AN141: 0 | AO141: 8 | AQ141: 45 | AR141: 4 | AS141: 6 | AT141: 35 | AV141: 50 | AW141: 40 | AX141: 1 | AY141: 5 | AZ141: 4 | BA141: 0 | BC141: 588 | BD141: 21 | BE141: 2 | BF141: 76
A142: E07000132 | B142: Hinckley & Bosworth | E142: 463 | G142: 41 | I142: 3 | J142: 0 | K142: 4 | L142: 1 | M142: 0 | O142: 1 | Q142: 11 | R142: 9 | S142: 2 | T142: 0 | V142: 0 | W142: 1 | X142: 5 | Y142: 15 | AA142: 10 | AB142: 97 | AC142: 32 | AE142: 199 | AF142: 192 | AG142: 7 | AH142: 0 | AJ142: 23 | AL142: 12 | AM142: 6 | AN142: 1 | AO142: 5 | AQ142: 12 | AR142: 1 | AS142: 8 | AT142: 3 | AV142: 16 | AW142: 13 | AX142: 1 | AY142: 1 | AZ142: 1 | BA142: 0 | BC142: 0 | BD142: 3 | BE142: 0 | BF142: 18
A143: E07000227 | B143: Horsham | E143: 202 | G143: 12 | I143: 2 | J143: 0 | K143: 1 | L143: 0 | M143: 0 | O143: 0 | Q143: 3 | R143: 1 | S143: 2 | T143: 0 | V143: 1 | W143: 1 | X143: 0 | Y143: 4 | AA143: 6 | AB143: 67 | AC143: 16 | AE143: 36 | AF143: 32 | AG143: 4 | AH143: 0 | AJ143: 6 | AL143: 5 | AM143: 3 | AN143: 1 | AO143: 1 | AQ143: 17 | AR143: 1 | AS143: 15 | AT143: 1 | AV143: 9 | AW143: 7 | AX143: 0 | AY143: 1 | AZ143: 1 | BA143: 0 | BC143: 6 | BD143: 4 | BE143: 1 | BF143: 17
A144: E09000018 | B144: Hounslow | E144: 1540 | G144: 218 | I144: 6 | J144: 7 | K144: 4 | L144: 6 | M144: 13 | O144: 4 | Q144: 74 | R144: 43 | S144: 31 | T144: 0 | V144: 1 | W144: 5 | X144: 1 | Y144: 97 | AA144: 70 | AB144: 386 | AC144: 42 | AE144: 137 | AF144: 114 | AG144: 18 | AH144: 5 | AJ144: 18 | AL144: 20 | AM144: 3 | AN144: 4 | AO144: 13 | AQ144: 40 | AR144: 0 | AS144: 5 | AT144: 35 | AV144: 86 | AW144: 54 | AX144: 15 | AY144: 12 | AZ144: 5 | BA144: 0 | BC144: 420 | BD144: 25 | BE144: 3 | BF144: 75
A145: E07000011 | B145: Huntingdonshire | E145: 279 | G145: 12 | I145: 0 | J145: 0 | K145: 2 | L145: 0 | M145: 1 | O145: 0 | Q145: 7 | R145: 5 | S145: 2 | T145: 0 | V145: 0 | W145: 2 | X145: 0 | Y145: 0 | AA145: 15 | AB145: 76 | AC145: 26 | AE145: 71 | AF145: 63 | AG145: 8 | AH145: 0 | AJ145: 9 | AL145: 9 | AM145: 2 | AN145: 5 | AO145: 2 | AQ145: 21 | AR145: 0 | AS145: 19 | AT145: 2 | AV145: 20 | AW145: 14 | AX145: 3 | AY145: 2 | AZ145: 1 | BA145: 0 | BC145: 2 | BD145: 5 | BE145: 1 | BF145: 12
A146: E07000120 | B146: Hyndburn | E146: 256 | G146: 16 | I146: 1 | J146: 1 | K146: 0 | L146: 0 | M146: 2 | O146: 1 | Q146: 3 | R146: 3 | S146: 0 | T146: 0 | V146: 0 | W146: 2 | X146: 2 | Y146: 4 | AA146: 5 | AB146: 64 | AC146: 24 | AE146: 13 | AF146: 10 | AG146: 3 | AH146: 0 | AJ146: 6 | AL146: 5 | AM146: 1 | AN146: 1 | AO146: 3 | AQ146: 21 | AR146: 1 | AS146: 8 | AT146: 12 | AV146: 17 | AW146: 15 | AX146: 2 | AY146: 0 | AZ146: 0 | BA146: 0 | BC146: 61 | BD146: 4 | BE146: 0 | BF146: 20
A147: E07000202 | B147: Ipswich | E147: 539 | G147: 35 | I147: 4 | J147: 1 | K147: 1 | L147: 0 | M147: 3 | O147: 3 | Q147: 8 | R147: 7 | S147: 1 | T147: 0 | V147: 0 | W147: 2 | X147: 3 | Y147: 10 | AA147: 31 | AB147: 187 | AC147: 33 | AE147: 55 | AF147: 49 | AG147: 6 | AH147: 0 | AJ147: 7 | AL147: 14 | AM147: 7 | AN147: 0 | AO147: 7 | AQ147: 74 | AR147: 6 | AS147: 44 | AT147: 24 | AV147: 45 | AW147: 16 | AX147: 0 | AY147: 1 | AZ147: 28 | BA147: 0 | BC147: 12 | BD147: 2 | BE147: 0 | BF147: 44
A148: E06000046 | B148: Isle of Wight | E148: 335 | G148: 39 | I148: 4 | J148: 1 | K148: 1 | L148: 0 | M148: 5 | O148: 1 | Q148: 11 | R148: 11 | S148: 0 | T148: 0 | V148: 0 | W148: 0 | X148: 2 | Y148: 14 | AA148: 21 | AB148: 89 | AC148: 33 | AE148: 33 | AF148: 23 | AG148: 10 | AH148: 0 | AJ148: 8 | AL148: 5 | AM148: 3 | AN148: 1 | AO148: 1 | AQ148: 19 | AR148: 1 | AS148: 16 | AT148: 2 | AV148: 11 | AW148: 6 | AX148: 0 | AY148: 3 | AZ148: 2 | BA148: 0 | BC148: 1 | BD148: 0 | BE148: 0 | BF148: 76
A149: E06000053 | B149: Isles of Scilly | E149: 0 | G149: 0 | I149: 0 | J149: 0 | K149: 0 | L149: 0 | M149: 0 | O149: 0 | Q149: 0 | R149: 0 | S149: 0 | T149: 0 | V149: 0 | W149: 0 | X149: 0 | Y149: 0 | AA149: 0 | AB149: 0 | AC149: 0 | AE149: 0 | AF149: 0 | AG149: 0 | AH149: 0 | AJ149: 0 | AL149: 0 | AM149: 0 | AN149: 0 | AO149: 0 | AQ149: 0 | AR149: 0 | AS149: 0 | AT149: 0 | AV149: 0 | AW149: 0 | AX149: 0 | AY149: 0 | AZ149: 0 | BA149: 0 | BC149: 0 | BD149: 0 | BE149: 0 | BF149: 0
A150: E09000019 | B150: Islington | E150: 2279 | G150: 266 | I150: 8 | J150: 5 | K150: 3 | L150: 0 | M150: 4 | O150: 2 | Q150: 36 | R150: 19 | S150: 17 | T150: 0 | V150: 0 | W150: 17 | X150: 0 | Y150: 191 | AA150: 19 | AB150: 695 | AC150: 35 | AE150: 310 | AF150: 301 | AG150: 9 | AH150: 0 | AJ150: 123 | AL150: 56 | AM150: 9 | AN150: 1 | AO150: 46 | AQ150: 149 | AR150: 4 | AS150: 15 | AT150: 130 | AV150: 94 | AW150: 57 | AX150: 24 | AY150: 13 | AZ150: 0 | BA150: 0 | BC150: 428 | BD150: 41 | BE150: 0 | BF150: 63
... A153: E06000010 | B153: Kingston upon Hull | E153: 1872 | G153: 162 | I153: 8 | J153: 7 | K153: 11 | L153: 6 | M153: 16 | O153: 7 | Q153: 40 | R153: 25 | S153: 15 | T153: 0 | V153: 2 | W153: 12 | X153: 21 | Y153: 32 | AA153: 13 | AB153: 452 | AC153: 219 | AE153: 341 | AF153: 318 | AG153: 23 | AH153: 0 | AJ153: 20 | AL153: 40 | AM153: 11 | AN153: 5 | AO153: 24 | AQ153: 235 | AR153: 20 | AS153: 177 | AT153: 38 | AV153: 134 | AW153: 113 | AX153: 2 | AY153: 19 | AZ153: 0 | BA153: 0 | BC153: 101 | BD153: 9 | BE153: 0 | BF153: 146
A154: E09000021 | B154: Kingston upon Thames | E154: .. | G154: .. | I154: .. | J154: .. | K154: .. | L154: .. | M154: .. | O154: .. | Q154: .. | R154: .. | S154: .. | T154: .. | V154: .. | W154: .. | X154: .. | Y154: .. | AA154: .. | AB154: .. | AC154: .. | AE154: .. | AF154: .. | AG154: .. | AH154: .. | AJ154: .. | AL154: .. | AM154: .. | AN154: .. | AO154: .. | AQ154: .. | AR154: .. | AS154: .. | AT154: .. | AV154: .. | AW154: .. | AX154: .. | AY154: .. | AZ154: .. | BA154: .. | BC154: .. | BD154: .. | BE154: .. | BF154: ..
...

Sheet A3
A1: Table A3 – Number of households owed a homelessness duty by support needs of household England, April 2024 to March 2025
H2: Total households with support need(s) owed a duty | M2: Total number of support needs for those owed a duty5 | N2: Young person aged 16-17 years | O2: Young person aged 18-25 years requiring support to manage independently | P2: Young parent requiring support to manage independently | Q2: Care leaver aged 18-20 years | R2: Care leaver aged 21-24 years | S2: Care leaver aged 25+ years | T2: Care leaver aged 21+ years (retired option) | U2: Physical ill health and disability | V2: History of mental health problems | W2: Learning disability | X2: At risk of / has experienced sexual abuse / exploitation | Y2: At risk of / has experienced domestic abuse | Z2: At risk of / has experienced abuse (non-domestic abuse) | AA2: Drug dependency needs | AB2: Alcohol dependency needs | AC2: Offending history | AD2: History of repeat homelessness | AE2: History of rough sleeping | AF2: Former asylum seeker | AG2: Old age | AH2: Served in HM Forces | AI2: Access to education, employment or training | AJ2: Victim of modern slavery | AK2: Difficulties budgeting
K3: Number of households | M3: Total number of support needs1 | N3: Of which households with:
E4: Households with no support needs owed duty1,2 | F4: Households with unknown support needs owed duty | H4: Households with one or more support needs owed duty1,2 | N4: Young person aged 16-17 years | O4: Young person aged 18-25 years requiring support to manage independently | P4: Young parent requiring support to manage independently | Q4: Care leaver aged 18-20 years | R4: Care leaver aged 21-24 3 | S4: Care leaver aged 25+ 4 | T4: Care leaver - retired option 5 | U4: Physical ill health and disability | V4: History of mental health problems | W4: Learning disability | X4: At risk of / has experienced sexual abuse / exploitation | Y4: At risk of / has experienced domestic abuse | Z4: At risk of / has experienced abuse (non-domestic abuse) | AA4: Drug dependency needs | AB4: Alcohol dependency needs | AC4: Offending history | AD4: History of repeat homelessness | AE4: History of rough sleeping | AF4: Former asylum seeker | AG4: Old age | AH4: Served in HM Forces | AI4: Access to education, employment or training | AJ4: Victim of modern slavery | AK4: Difficulties budgeting
H5: Total households with support needs | I5: 1 | J5: 2 | K5: 3+
A6: E92000001 | B6: ENGLAND | E6: 141620 | F6: 270 | H6: 188520 | I6: 83280 | J6: 45350 | K6: 59880 | M6: 431190 | N6: 2710 | O6: 12680 | P6: 3670 | Q6: 4610 | R6: 1750 | S6: 2220 | T6: 700 | U6: 69980 | V6: 91080 | W6: 20750 | X6: 8300 | Y6: 39870 | Z6: 9850 | AA6: 19680 | AB6: 15390 | AC6: 27760 | AD6: 23420 | AE6: 19540 | AF6: 13090 | AG6: 6580 | AH6: 2180 | AI6: 16950 | AJ6: 970 | AK6: 17490
A7: E12000007 | B7: London | E7: 38230 | F7: 90 | H7: 32430 | I7: 17510 | J7: 7700 | K7: 7220 | M7: 62650 | N7: 440 | O7: 1950 | P7: 650 | Q7: 350 | R7: 230 | S7: 180 | T7: 130 | U7: 13000 | V7: 12400 | W7: 2740 | X7: 1230 | Y7: 5830 | Z7: 1520 | AA7: 1950 | AB7: 1520 | AC7: 2920 | AD7: 2580 | AE7: 2870 | AF7: 2360 | AG7: 1520 | AH7: 90 | AI7: 4040 | AJ7: 180 | AK7: 1970
A8: - | B8: Rest of England | E8: 103390 | F8: 180 | H8: 156090 | I8: 65770 | J8: 37650 | K8: 52670 | M8: 368550 | N8: 2270 | O8: 10730 | P8: 3010 | Q8: 4260 | R8: 1510 | S8: 2030 | T8: 560 | U8: 56980 | V8: 78680 | W8: 18010 | X8: 7080 | Y8: 34040 | Z8: 8330 | AA8: 17730 | AB8: 13870 | AC8: 24840 | AD8: 20840 | AE8: 16670 | AF8: 10730 | AG8: 5060 | AH8: 2090 | AI8: 12910 | AJ8: 780 | AK8: 15520
A10: E12000001 | B10: North East | E10: 5130 | F10: 0 | H10: 14580 | I10: 4800 | J10: 3680 | K10: 6090 | M10: 38350 | N10: 70 | O10: 530 | P10: 130 | Q10: 300 | R10: 120 | S10: 270 | T10: 70 | U10: 5820 | V10: 9040 | W10: 1780 | X10: 640 | Y10: 3170 | Z10: 860 | AA10: 2520 | AB10: 1710 | AC10: 3480 | AD10: 2200 | AE10: 1610 | AF10: 1360 | AG10: 260 | AH10: 280 | AI10: 770 | AJ10: 50 | AK10: 1320
A11: E12000002 | B11: North West | E11: 18950 | F11: 10 | H11: 28470 | I11: 11510 | J11: 6800 | K11: 10150 | M11: 68880 | N11: 380 | O11: 1910 | P11: 480 | Q11: 640 | R11: 340 | S11: 440 | T11: 60 | U11: 10090 | V11: 14110 | W11: 3340 | X11: 1160 | Y11: 5720 | Z11: 1420 | AA11: 3150 | AB11: 2540 | AC11: 5170 | AD11: 4400 | AE11: 3410 | AF11: 2960 | AG11: 910 | AH11: 500 | AI11: 2850 | AJ11: 120 | AK11: 2780
A12: E12000003 | B12: Yorkshire and The Humber | E12: 12480 | F12: 10 | H12: 18790 | I12: 8120 | J12: 4540 | K12: 6120 | M12: 43830 | N12: 390 | O12: 1530 | P12: 460 | Q12: 450 | R12: 60 | S12: 60 | T12: 210 | U12: 6760 | V12: 9600 | W12: 2150 | X12: 870 | Y12: 4300 | Z12: 990 | AA12: 2400 | AB12: 1590 | AC12: 3080 | AD12: 2370 | AE12: 1800 | AF12: 1590 | AG12: 410 | AH12: 200 | AI12: 1160 | AJ12: 160 | AK12: 1230
A13: E12000004 | B13: East Midlands | E13: 10150 | F13: 10 | H13: 14480 | I13: 7120 | J13: 3610 | K13: 3760 | M13: 29420 | N13: 110 | O13: 610 | P13: 200 | Q13: 320 | R13: 120 | S13: 100 | T13: 40 | U13: 5530 | V13: 7170 | W13: 1330 | X13: 460 | Y13: 2890 | Z13: 490 | AA13: 1480 | AB13: 1140 | AC13: 2110 | AD13: 1400 | AE13: 1200 | AF13: 960 | AG13: 350 | AH13: 120 | AI13: 370 | AJ13: 70 | AK13: 820
A14: E12000005 | B14: West Midlands | E14: 16560 | F14: 120 | H14: 14980 | I14: 6880 | J14: 3370 | K14: 4730 | M14: 34040 | N14: 310 | O14: 1300 | P14: 330 | Q14: 540 | R14: 120 | S14: 240 | T14: 40 | U14: 5020 | V14: 6730 | W14: 1420 | X14: 750 | Y14: 3950 | Z14: 880 | AA14: 1310 | AB14: 1020 | AC14: 1960 | AD14: 1920 | AE14: 1440 | AF14: 1090 | AG14: 390 | AH14: 170 | AI14: 1560 | AJ14: 80 | AK14: 1470
A15: E12000006 | B15: East of England | E15: 12530 | F15: 30 | H15: 20060 | I15: 8810 | J15: 5030 | K15: 6220 | M15: 45320 | N15: 340 | O15: 1420 | P15: 420 | Q15: 650 | R15: 170 | S15: 180 | T15: 60 | U15: 7280 | V15: 9840 | W15: 2420 | X15: 890 | Y15: 4520 | Z15: 1110 | AA15: 1700 | AB15: 1450 | AC15: 2390 | AD15: 2230 | AE15: 1960 | AF15: 730 | AG15: 830 | AH15: 180 | AI15: 2230 | AJ15: 70 | AK15: 2230
A16: E12000007 | B16: London | E16: 38230 | F16: 90 | H16: 32430 | I16: 17510 | J16: 7700 | K16: 7220 | M16: 62650 | N16: 440 | O16: 1950 | P16: 650 | Q16: 350 | R16: 230 | S16: 180 | T16: 130 | U16: 13000 | V16: 12400 | W16: 2740 | X16: 1230 | Y16: 5830 | Z16: 1520 | AA16: 1950 | AB16: 1520 | AC16: 2920 | AD16: 2580 | AE16: 2870 | AF16: 2360 | AG16: 1520 | AH16: 90 | AI16: 4040 | AJ16: 180 | AK16: 1970
A17: E12000008 | B17: South East | E17: 18570 | F17: 20 | H17: 25440 | I17: 11860 | J17: 6210 | K17: 7370 | M17: 54470 | N17: 220 | O17: 1790 | P17: 510 | Q17: 730 | R17: 290 | S17: 270 | T17: 20 | U17: 8850 | V17: 11830 | W17: 2980 | X17: 910 | Y17: 4970 | Z17: 1020 | AA17: 2550 | AB17: 2250 | AC17: 3140 | AD17: 2770 | AE17: 2170 | AF17: 1200 | AG17: 1010 | AH17: 250 | AI17: 1850 | AJ17: 120 | AK17: 2780
A18: E12000009 | B18: South West | E18: 9000 | F18: 0 | H18: 19280 | I18: 6660 | J18: 4410 | K18: 8210 | M18: 54230 | N18: 450 | O18: 1640 | P18: 470 | Q18: 620 | R18: 290 | S18: 470 | T18: 70 | U18: 7640 | V18: 10360 | W18: 2600 | X18: 1390 | Y18: 4510 | Z18: 1550 | AA18: 2620 | AB18: 2170 | AC18: 3510 | AD18: 3560 | AE18: 3080 | AF18: 850 | AG18: 890 | AH18: 380 | AI18: 2100 | AJ18: 120 | AK18: 2900
... A46: E07000143 | B46: Breckland | E46: 79 | F46: 0 | H46: 630 | I46: 77 | J46: 100 | K46: 453 | M46: 2456 | N46: 4 | O46: 42 | P46: 19 | Q46: 15 | R46: 9 | S46: 29 | T46: 0 | U46: 303 | V46: 416 | W46: 192 | X46: 86 | Y46: 256 | Z46: 84 | AA46: 70 | AB46: 44 | AC46: 125 | AD46: 182 | AE46: 151 | AF46: 3 | AG46: 30 | AH46: 18 | AI46: 231 | AJ46: 1 | AK46: 146
A47: E09000005 | B47: Brent | E47: .. | F47: .. | H47: .. | I47: .. | J47: .. | K47: .. | M47: .. | N47: .. | O47: .. | P47: .. | Q47: .. | R47: .. | S47: .. | T47: .. | U47: .. | V47: .. | W47: .. | X47: .. | Y47: .. | Z47: .. | AA47: .. | AB47: .. | AC47: .. | AD47: .. | AE47: .. | AF47: .. | AG47: .. | AH47: .. | AI47: .. | AJ47: .. | AK47: ..
A48: E07000068 | B48: Brentwood | E48: 86 | F48: 0 | H48: 119 | I48: 43 | J48: 31 | K48: 45 | M48: 309 | N48: 1 | O48: 8 | P48: 3 | Q48: 0 | R48: 0 | S48: 1 | T48: 0 | U48: 52 | V48: 62 | W48: 26 | X48: 9 | Y48: 29 | Z48: 10 | AA48: 10 | AB48: 17 | AC48: 10 | AD48: 12 | AE48: 16 | AF48: 2 | AG48: 9 | AH48: 3 | AI48: 15 | AJ48: 2 | AK48: 12
A49: E06000043 | B49: Brighton & Hove | E49: 260 | F49: 19 | H49: 1108 | I49: 420 | J49: 276 | K49: 412 | M49: 2715 | N49: 5 | O49: 122 | P49: 27 | Q49: 26 | R49: 17 | S49: 15 | T49: 1 | U49: 426 | V49: 554 | W49: 102 | X49: 61 | Y49: 203 | Z49: 50 | AA49: 190 | AB49: 132 | AC49: 146 | AD49: 185 | AE49: 146 | AF49: 104 | AG49: 33 | AH49: 6 | AI49: 69 | AJ49: 19 | AK49: 76
A50: E06000023 | B50: Bristol | E50: 678 | F50: 0 | H50: 2465 | I50: 849 | J50: 569 | K50: 1047 | M50: 6645 | N50: 17 | O50: 142 | P50: 29 | Q50: 51 | R50: 15 | S50: 44 | T50: 1 | U50: 1140 | V50: 1419 | W50: 248 | X50: 194 | Y50: 541 | Z50: 205 | AA50: 342 | AB50: 263 | AC50: 467 | AD50: 540 | AE50: 481 | AF50: 233 | AG50: 42 | AH50: 7 | AI50: 77 | AJ50: 21 | AK50: 126
A51: E07000144 | B51: Broadland | E51: 180 | F51: 0 | H51: 289 | I51: 200 | J51: 59 | K51: 30 | M51: 422 | N51: 4 | O51: 17 | P51: 5 | Q51: 25 | R51: 1 | S51: 1 | T51: 1 | U51: 62 | V51: 78 | W51: 17 | X51: 5 | Y51: 110 | Z51: 5 | AA51: 14 | AB51: 20 | AC51: 12 | AD51: 6 | AE51: 4 | AF51: 19 | AG51: 9 | AH51: 2 | AI51: 0 | AJ51: 0 | AK51: 5
A52: E09000006 | B52: Bromley | E52: 421 | F52: 0 | H52: 1240 | I52: 619 | J52: 354 | K52: 267 | M52: 2279 | N52: 14 | O52: 42 | P52: 19 | Q52: 5 | R52: 6 | S52: 5 | T52: 0 | U52: 519 | V52: 627 | W52: 155 | X52: 33 | Y52: 288 | Z52: 70 | AA52: 70 | AB52: 85 | AC52: 94 | AD52: 43 | AE52: 63 | AF52: 11 | AG52: 29 | AH52: 1 | AI52: 45 | AJ52: 3 | AK52: 52
A53: E07000234 | B53: Bromsgrove | E53: 141 | F53: 0 | H53: 214 | I53: 123 | J53: 60 | K53: 31 | M53: 360 | N53: 4 | O53: 49 | P53: 14 | Q53: 11 | R53: 5 | S53: 0 | T53: 0 | U53: 54 | V53: 90 | W53: 8 | X53: 6 | Y53: 67 | Z53: 3 | AA53: 9 | AB53: 13 | AC53: 4 | AD53: 12 | AE53: 0 | AF53: 1 | AG53: 7 | AH53: 0 | AI53: 0 | AJ53: 1 | AK53: 2
A54: E07000095 | B54: Broxbourne | E54: 85 | F54: 0 | H54: 481 | I54: 111 | J54: 124 | K54: 246 | M54: 1393 | N54: 9 | O54: 21 | P54: 6 | Q54: 12 | R54: 5 | S54: 5 | T54: 0 | U54: 241 | V54: 273 | W54: 93 | X54: 25 | Y54: 99 | Z54: 45 | AA54: 23 | AB54: 19 | AC54: 54 | AD54: 104 | AE54: 80 | AF54: 54 | AG54: 17 | AH54: 3 | AI54: 170 | AJ54: 4 | AK54: 31
A55: E07000172 | B55: Broxtowe | E55: 170 | F55: 0 | H55: 77 | I55: 40 | J55: 14 | K55: 23 | M55: 159 | N55: 0 | O55: 3 | P55: 1 | Q55: 0 | R55: 4 | S55: 1 | T55: 0 | U55: 27 | V55: 36 | W55: 7 | X55: 2 | Y55: 17 | Z55: 3 | AA55: 10 | AB55: 7 | AC55: 8 | AD55: 12 | AE55: 6 | AF55: 6 | AG55: 1 | AH55: 0 | AI55: 3 | AJ55: 2 | AK55: 3
A56: E06000060 | B56: Buckinghamshire | E56: 1328 | F56: 0 | H56: 1190 | I56: 406 | J56: 281 | K56: 503 | M56: 3114 | N56: 20 | O56: 87 | P56: 16 | Q56: 21 | R56: 9 | S56: 8 | T56: 1 | U56: 478 | V56: 644 | W56: 291 | X56: 66 | Y56: 263 | Z56: 101 | AA56: 100 | AB56: 105 | AC56: 193 | AD56: 163 | AE56: 131 | AF56: 17 | AG56: 60 | AH56: 15 | AI56: 166 | AJ56: 8 | AK56: 151
A57: E07000117 | B57: Burnley | E57: 309 | F57: 0 | H57: 378 | I57: 183 | J57: 81 | K57: 114 | M57: 831 | N57: 6 | O57: 13 | P57: 3 | Q57: 10 | R57: 1 | S57: 4 | T57: 0 | U57: 129 | V57: 181 | W57: 49 | X57: 13 | Y57: 50 | Z57: 20 | AA57: 62 | AB57: 30 | AC57: 60 | AD57: 42 | AE57: 36 | AF57: 43 | AG57: 11 | AH57: 13 | AI57: 20 | AJ57: 3 | AK57: 32
A58: E08000002 | B58: Bury | E58: .. | F58: .. | H58: .. | I58: .. | J58: .. | K58: .. | M58: .. | N58: .. | O58: .. | P58: .. | Q58: .. | R58: .. | S58: .. | T58: .. | U58: .. | V58: .. | W58: .. | X58: .. | Y58: .. | Z58: .. | AA58: .. | AB58: .. | AC58: .. | AD58: .. | AE58: .. | AF58: .. | AG58: .. | AH58: .. | AI58: .. | AJ58: .. | AK58: ..
A59: E08000033 | B59: Calderdale | E59: 231 | F59: 0 | H59: 996 | I59: 345 | J59: 239 | K59: 412 | M59: 2697 | N59: 66 | O59: 85 | P59: 26 | Q59: 40 | R59: 20 | S59: 22 | T59: 5 | U59: 379 | V59: 520 | W59: 159 | X59: 49 | Y59: 201 | Z59: 59 | AA59: 162 | AB59: 97 | AC59: 210 | AD59: 125 | AE59: 103 | AF59: 96 | AG59: 36 | AH59: 10 | AI59: 75 | AJ59: 9 | AK59: 143
A60: E07000008 | B60: Cambridge | E60: 348 | F60: 0 | H60: 424 | I60: 146 | J60: 85 | K60: 193 | M60: 1229 | N60: 7 | O60: 38 | P60: 3 | Q60: 27 | R60: 4 | S60: 8 | T60: 3 | U60: 141 | V60: 231 | W60: 41 | X60: 30 | Y60: 96 | Z60: 50 | AA60: 72 | AB60: 48 | AC60: 82 | AD60: 87 | AE60: 78 | AF60: 22 | AG60: 15 | AH60: 4 | AI60: 68 | AJ60: 2 | AK60: 72
A61: E09000007 | B61: Camden | E61: .. | F61: .. | H61: .. | I61: .. | J61: .. | K61: .. | M61: .. | N61: .. | O61: .. | P61: .. | Q61: .. | R61: .. | S61: .. | T61: .. | U61: .. | V61: .. | W61: .. | X61: .. | Y61: .. | Z61: .. | AA61: .. | AB61: .. | AC61: .. | AD61: .. | AE61: .. | AF61: .. | AG61: .. | AH61: .. | AI61: .. | AJ61: .. | AK61: ..
A62: E07000192 | B62: Cannock Chase | E62: 147 | F62: 0 | H62: 24 | I62: 18 | J62: 3 | K62: 3 | M62: 33 | N62: 0 | O62: 2 | P62: 0 | Q62: 0 | R62: 0 | S62: 0 | T62: 0 | U62: 4 | V62: 13 | W62: 2 | X62: 0 | Y62: 6 | Z62: 0 | AA62: 3 | AB62: 1 | AC62: 1 | AD62: 1 | AE62: 0 | AF62: 0 | AG62: 0 | AH62: 0 | AI62: 0 | AJ62: 0 | AK62: 0
A63: E07000106 | B63: Canterbury | E63: .. | F63: .. | H63: .. | I63: .. | J63: .. | K63: .. | M63: .. | N63: .. | O63: .. | P63: .. | Q63: .. | R63: .. | S63: .. | T63: .. | U63: .. | V63: .. | W63: .. | X63: .. | Y63: .. | Z63: .. | AA63: .. | AB63: .. | AC63: .. | AD63: .. | AE63: .. | AF63: .. | AG63: .. | AH63: .. | AI63: .. | AJ63: .. | AK63: ..
A64: E07000069 | B64: Castle Point | E64: 132 | F64: 0 | H64: 127 | I64: 88 | J64: 27 | K64: 12 | M64: 185 | N64: 1 | O64: 7 | P64: 1 | Q64: 1 | R64: 2 | S64: 0 | T64: 0 | U64: 48 | V64: 55 | W64: 3 | X64: 1 | Y64: 15 | Z64: 0 | AA64: 10 | AB64: 10 | AC64: 10 | AD64: 5 | AE64: 1 | AF64: 0 | AG64: 11 | AH64: 1 | AI64: 1 | AJ64: 0 | AK64: 2
A65: E06000056 | B65: Central Bedfordshire | E65: 108 | F65: 0 | H65: 1025 | I65: 185 | J65: 232 | K65: 608 | M65: 3371 | N65: 20 | O65: 68 | P65: 35 | Q65: 21 | R65: 15 | S65: 17 | T65: 1 | U65: 447 | V65: 605 | W65: 230 | X65: 85 | Y65: 355 | Z65: 107 | AA65: 79 | AB65: 71 | AC65: 149 | AD65: 178 | AE65: 145 | AF65: 38 | AG65: 64 | AH65: 11 | AI65: 418 | AJ65: 5 | AK65: 207
A66: E07000130 | B66: Charnwood | E66: 319 | F66: 3 | H66: 303 | I66: 178 | J66: 75 | K66: 50 | M66: 511 | N66: 2 | O66: 15 | P66: 10 | Q66: 3 | R66: 1 | S66: 3 | T66: 0 | U66: 86 | V66: 143 | W66: 27 | X66: 7 | Y66: 51 | Z66: 9 | AA66: 18 | AB66: 31 | AC66: 24 | AD66: 13 | AE66: 16 | AF66: 16 | AG66: 17 | AH66: 3 | AI66: 1 | AJ66: 1 | AK66: 14
A67: E07000070 | B67: Chelmsford | E67: 332 | F67: 0 | H67: 553 | I67: 167 | J67: 145 | K67: 241 | M67: 1525 | N67: 17 | O67: 36 | P67: 6 | Q67: 6 | R67: 8 | S67: 15 | T67: 3 | U67: 206 | V67: 322 | W67: 108 | X67: 38 | Y67: 146 | Z67: 62 | AA67: 43 | AB67: 34 | AC67: 77 | AD67: 100 | AE67: 93 | AF67: 35 | AG67: 22 | AH67: 5 | AI67: 74 | AJ67: 4 | AK67: 65
A68: E07000078 | B68: Cheltenham | E68: 174 | F68: 0 | H68: 434 | I68: 165 | J68: 83 | K68: 186 | M68: 1202 | N68: 5 | O68: 30 | P68: 5 | Q68: 11 | R68: 6 | S68: 4 | T68: 1 | U68: 132 | V68: 196 | W68: 43 | X68: 33 | Y68: 119 | Z68: 30 | AA68: 79 | AB68: 63 | AC68: 93 | AD68: 77 | AE68: 68 | AF68: 30 | AG68: 14 | AH68: 7 | AI68: 94 | AJ68: 2 | AK68: 60
A69: E07000177 | B69: Cherwell | E69: 141 | F69: 0 | H69: 419 | I69: 169 | J69: 119 | K69: 131 | M69: 923 | N69: 0 | O69: 25 | P69: 3 | Q69: 3 | R69: 2 | S69: 4 | T69: 0 | U69: 156 | V69: 205 | W69: 28 | X69: 23 | Y69: 90 | Z69: 8 | AA69: 57 | AB69: 45 | AC69: 65 | AD69: 41 | AE69: 24 | AF69: 32 | AG69: 11 | AH69: 5 | AI69: 20 | AJ69: 3 | AK69: 73
A70: E06000049 | B70: Cheshire East | E70: 517 | F70: 0 | H70: 1367 | I70: 509 | J70: 316 | K70: 542 | M70: 3564 | N70: 6 | O70: 57 | P70: 5 | Q70: 39 | R70: 24 | S70: 23 | T70: 8 | U70: 558 | V70: 709 | W70: 157 | X70: 69 | Y70: 233 | Z70: 115 | AA70: 161 | AB70: 180 | AC70: 291 | AD70: 256 | AE70: 189 | AF70: 97 | AG70: 49 | AH70: 37 | AI70: 143 | AJ70: 5 | AK70: 153
A71: E06000050 | B71: Cheshire West & Chester | E71: 429 | F71: 0 | H71: 1325 | I71: 624 | J71: 344 | K71: 357 | M71: 2723 | N71: 42 | O71: 109 | P71: 43 | Q71: 20 | R71: 10 | S71: 16 | T71: 1 | U71: 454 | V71: 618 | W71: 168 | X71: 19 | Y71: 234 | Z71: 42 | AA71: 113 | AB71: 118 | AC71: 199 | AD71: 131 | AE71: 124 | AF71: 157 | AG71: 26 | AH71: 18 | AI71: 20 | AJ71: 7 | AK71: 34
A72: E07000034 | B72: Chesterfield | E72: 239 | F72: 0 | H72: 334 | I72: 119 | J72: 97 | K72: 118 | M72: 776 | N72: 0 | O72: 17 | P72: 2 | Q72: 6 | R72: 7 | S72: 2 | T72: 3 | U72: 140 | V72: 206 | W72: 41 | X72: 9 | Y72: 53 | Z72: 17 | AA72: 42 | AB72: 34 | AC72: 72 | AD72: 47 | AE72: 33 | AF72: 8 | AG72: 4 | AH72: 3 | AI72: 9 | AJ72: 2 | AK72: 19
A73: E07000225 | B73: Chichester | E73: 158 | F73: 0 | H73: 327 | I73: 159 | J73: 77 | K73: 91 | M73: 667 | N73: 0 | O73: 18 | P73: 14 | Q73: 12 | R73: 4 | S73: 3 | T73: 0 | U73: 89 | V73: 155 | W73: 19 | X73: 7 | Y73: 68 | Z73: 20 | AA73: 34 | AB73: 39 | AC73: 39 | AD73: 55 | AE73: 25 | AF73: 13 | AG73: 6 | AH73: 4 | AI73: 3 | AJ73: 0 | AK73: 40
A74: E07000118 | B74: Chorley | E74: 195 | F74: 0 | H74: 372 | I74: 264 | J74: 71 | K74: 37 | M74: 547 | N74: 7 | O74: 27 | P74: 4 | Q74: 6 | R74: 1 | S74: 0 | T74: 0 | U74: 106 | V74: 148 | W74: 12 | X74: 2 | Y74: 79 | Z74: 2 | AA74: 28 | AB74: 35 | AC74: 29 | AD74: 16 | AE74: 8 | AF74: 25 | AG74: 5 | AH74: 1 | AI74: 1 | AJ74: 0 | AK74: 5
A75: E09000001 | B75: City of London | E75: 6 | F75: 0 | H75: 21 | I75: 11 | J75: 7 | K75: 3 | M75: 39 | N75: 0 | O75: 0 | P75: 0 | Q75: 0 | R75: 0 | S75: 0 | T75: 0 | U75: 4 | V75: 10 | W75: 0 | X75: 1 | Y75: 6 | Z75: 1 | AA75: 2 | AB75: 1 | AC75: 5 | AD75: 3 | AE75: 3 | AF75: 0 | AG75: 1 | AH75: 0 | AI75: 0 | AJ75: 0 | AK75: 2
... A80: E07000226 | B80: Crawley | E80: 379 | F80: 0 | H80: 618 | I80: 390 | J80: 134 | K80: 94 | M80: 1017 | N80: 3 | O80: 78 | P80: 43 | Q80: 18 | R80: 1 | S80: 2 | T80: 0 | U80: 187 | V80: 175 | W80: 23 | X80: 15 | Y80: 93 | Z80: 13 | AA80: 35 | AB80: 17 | AC80: 34 | AD80: 42 | AE80: 24 | AF80: 34 | AG80: 16 | AH80: 4 | AI80: 86 | AJ80: 2 | AK80: 72
A81: E09000008 | B81: Croydon | E81: .. | F81: .. | H81: .. | I81: .. | J81: .. | K81: .. | M81: .. | N81: .. | O81: .. | P81: .. | Q81: .. | R81: .. | S81: .. | T81: .. | U81: .. | V81: .. | W81: .. | X81: .. | Y81: .. | Z81: .. | AA81: .. | AB81: .. | AC81: .. | AD81: .. | AE81: .. | AF81: .. | AG81: .. | AH81: .. | AI81: .. | AJ81: .. | AK81: ..
A82: E06000063 | B82: Cumberland Council | E82: 357 | F82: 0 | H82: 1301 | I82: 282 | J82: 276 | K82: 743 | M82: 4314 | N82: 10 | O82: 130 | P82: 23 | Q82: 27 | R82: 14 | S82: 58 | T82: 1 | U82: 586 | V82: 843 | W82: 187 | X82: 88 | Y82: 313 | Z82: 105 | AA82: 198 | AB82: 161 | AC82: 431 | AD82: 378 | AE82: 240 | AF82: 69 | AG82: 57 | AH82: 47 | AI82: 152 | AJ82: 7 | AK82: 189
A83: E07000096 | B83: Dacorum | E83: 286 | F83: 0 | H83: 624 | I83: 369 | J83: 179 | K83: 76 | M83: 997 | N83: 2 | O83: 45 | P83: 17 | Q83: 10 | R83: 1 | S83: 0 | T83: 0 | U83: 208 | V83: 249 | W83: 23 | X83: 7 | Y83: 139 | Z83: 11 | AA83: 32 | AB83: 27 | AC83: 25 | AD83: 24 | AE83: 11 | AF83: 55 | AG83: 28 | AH83: 2 | AI83: 29 | AJ83: 0 | AK83: 52
A84: E06000005 | B84: Darlington | E84: 316 | F84: 0 | H84: 1038 | I84: 363 | J84: 264 | K84: 411 | M84: 2515 | N84: 19 | O84: 74 | P84: 12 | Q84: 21 | R84: 10 | S84: 12 | T84: 0 | U84: 338 | V84: 594 | W84: 82 | X84: 20 | Y84: 188 | Z84: 24 | AA84: 244 | AB84: 145 | AC84: 304 | AD84: 170 | AE84: 83 | AF84: 72 | AG84: 24 | AH84: 14 | AI84: 21 | AJ84: 5 | AK84: 39
A85: E07000107 | B85: Dartford | E85: 312 | F85: 0 | H85: 323 | I85: 126 | J85: 80 | K85: 117 | M85: 765 | N85: 6 | O85: 23 | P85: 14 | Q85: 9 | R85: 9 | S85: 3 | T85: 0 | U85: 134 | V85: 164 | W85: 64 | X85: 9 | Y85: 102 | Z85: 22 | AA85: 22 | AB85: 23 | AC85: 26 | AD85: 27 | AE85: 29 | AF85: 4 | AG85: 16 | AH85: 1 | AI85: 23 | AJ85: 1 | AK85: 34
A86: E06000015 | B86: Derby | E86: 328 | F86: 0 | H86: 1986 | I86: 634 | J86: 537 | K86: 815 | M86: 4969 | N86: 5 | O86: 21 | P86: 1 | Q86: 33 | R86: 23 | S86: 33 | T86: 0 | U86: 938 | V86: 1230 | W86: 289 | X86: 82 | Y86: 359 | Z86: 60 | AA86: 302 | AB86: 182 | AC86: 462 | AD86: 205 | AE86: 135 | AF86: 329 | AG86: 17 | AH86: 18 | AI86: 104 | AJ86: 12 | AK86: 129
A87: E07000035 | B87: Derbyshire Dales | E87: 90 | F87: 0 | H87: 127 | I87: 60 | J87: 37 | K87: 30 | M87: 253 | N87: 1 | O87: 4 | P87: 0 | Q87: 0 | R87: 0 | S87: 2 | T87: 1 | U87: 47 | V87: 72 | W87: 4 | X87: 3 | Y87: 26 | Z87: 4 | AA87: 8 | AB87: 13 | AC87: 19 | AD87: 14 | AE87: 6 | AF87: 2 | AG87: 5 | AH87: 1 | AI87: 3 | AJ87: 1 | AK87: 17
A88: E08000017 | B88: Doncaster | E88: 955 | F88: 0 | H88: 1409 | I88: 774 | J88: 358 | K88: 277 | M88: 2522 | N88: 34 | O88: 83 | P88: 20 | Q88: 51 | R88: 3 | S88: 3 | T88: 29 | U88: 411 | V88: 555 | W88: 117 | X88: 36 | Y88: 340 | Z88: 48 | AA88: 185 | AB88: 83 | AC88: 196 | AD88: 80 | AE88: 66 | AF88: 125 | AG88: 35 | AH88: 11 | AI88: 9 | AJ88: 0 | AK88: 2
A89: E06000059 | B89: Dorset | E89: 449 | F89: 0 | H89: 1101 | I89: 448 | J89: 315 | K89: 338 | M89: 2384 | N89: 9 | O89: 51 | P89: 28 | Q89: 28 | R89: 17 | S89: 9 | T89: 0 | U89: 367 | V89: 526 | W89: 135 | X89: 22 | Y89: 166 | Z89: 30 | AA89: 71 | AB89: 74 | AC89: 92 | AD89: 75 | AE89: 74 | AF89: 2 | AG89: 89 | AH89: 20 | AI89: 280 | AJ89: 1 | AK89: 218
A90: E07000108 | B90: Dover | E90: 277 | F90: 0 | H90: 224 | I90: 100 | J90: 44 | K90: 80 | M90: 512 | N90: 4 | O90: 9 | P90: 0 | Q90: 17 | R90: 2 | S90: 10 | T90: 0 | U90: 92 | V90: 116 | W90: 50 | X90: 7 | Y90: 40 | Z90: 15 | AA90: 11 | AB90: 19 | AC90: 19 | AD90: 22 | AE90: 15 | AF90: 2 | AG90: 9 | AH90: 3 | AI90: 21 | AJ90: 0 | AK90: 29
A91: E08000027 | B91: Dudley | E91: 2040 | F91: 0 | H91: 326 | I91: 177 | J91: 83 | K91: 66 | M91: 577 | N91: 2 | O91: 31 | P91: 14 | Q91: 8 | R91: 4 | S91: 2 | T91: 0 | U91: 69 | V91: 110 | W91: 19 | X91: 8 | Y91: 65 | Z91: 4 | AA91: 32 | AB91: 34 | AC91: 56 | AD91: 34 | AE91: 19 | AF91: 26 | AG91: 9 | AH91: 3 | AI91: 17 | AJ91: 0 | AK91: 11
A92: E06000047 | B92: Durham | E92: 719 | F92: 0 | H92: 3050 | I92: 1102 | J92: 888 | K92: 1060 | M92: 7359 | N92: 5 | O92: 145 | P92: 37 | Q92: 62 | R92: 2 | S92: 0 | T92: 49 | U92: 1173 | V92: 2091 | W92: 377 | X92: 76 | Y92: 523 | Z92: 113 | AA92: 456 | AB92: 375 | AC92: 533 | AD92: 405 | AE92: 379 | AF92: 99 | AG92: 89 | AH92: 43 | AI92: 94 | AJ92: 1 | AK92: 232
A93: E09000009 | B93: Ealing | E93: 2430 | F93: 0 | H93: 629 | I93: 475 | J93: 114 | K93: 40 | M93: 839 | N93: 1 | O93: 27 | P93: 3 | Q93: 3 | R93: 7 | S93: 4 | T93: 1 | U93: 265 | V93: 186 | W93: 24 | X93: 7 | Y93: 70 | Z93: 4 | AA93: 14 | AB93: 29 | AC93: 40 | AD93: 13 | AE93: 25 | AF93: 64 | AG93: 41 | AH93: 0 | AI93: 7 | AJ93: 1 | AK93: 3
... A99: E06000011 | B99: East Riding of Yorkshire | E99: 334 | F99: 0 | H99: 851 | I99: 346 | J99: 249 | K99: 256 | M99: 1838 | N99: 3 | O99: 28 | P99: 6 | Q99: 17 | R99: 7 | S99: 5 | T99: 0 | U99: 371 | V99: 444 | W99: 139 | X99: 30 | Y99: 229 | Z99: 33 | AA99: 64 | AB99: 61 | AC99: 115 | AD99: 66 | AE99: 56 | AF99: 5 | AG99: 38 | AH99: 9 | AI99: 48 | AJ99: 1 | AK99: 63
A100: E07000193 | B100: East Staffordshire | E100: .. | F100: .. | H100: .. | I100: .. | J100: .. | K100: .. | M100: .. | N100: .. | O100: .. | P100: .. | Q100: .. | R100: .. | S100: .. | T100: .. | U100: .. | V100: .. | W100: .. | X100: .. | Y100: .. | Z100: .. | AA100: .. | AB100: .. | AC100: .. | AD100: .. | AE100: .. | AF100: .. | AG100: .. | AH100: .. | AI100: .. | AJ100: .. | AK100: ..
A101: E07000244 | B101: East Suffolk | E101: 489 | F101: 0 | H101: 732 | I101: 384 | J101: 202 | K101: 146 | M101: 1377 | N101: 11 | O101: 83 | P101: 27 | Q101: 25 | R101: 0 | S101: 0 | T101: 10 | U101: 232 | V101: 346 | W101: 44 | X101: 19 | Y101: 136 | Z101: 17 | AA101: 75 | AB101: 78 | AC101: 96 | AD101: 60 | AE101: 46 | AF101: 7 | AG101: 32 | AH101: 5 | AI101: 3 | AJ101: 0 | AK101: 25
A102: E07000061 | B102: Eastbourne | E102: 120 | F102: 0 | H102: 617 | I102: 287 | J102: 194 | K102: 136 | M102: 1169 | N102: 2 | O102: 65 | P102: 23 | Q102: 15 | R102: 10 | S102: 1 | T102: 0 | U102: 240 | V102: 305 | W102: 58 | X102: 15 | Y102: 97 | Z102: 20 | AA102: 34 | AB102: 55 | AC102: 41 | AD102: 27 | AE102: 37 | AF102: 17 | AG102: 29 | AH102: 3 | AI102: 9 | AJ102: 0 | AK102: 66
A103: E07000086 | B103: Eastleigh | E103: 94 | F103: 0 | H103: 241 | I103: 130 | J103: 58 | K103: 53 | M103: 463 | N103: 0 | O103: 37 | P103: 6 | Q103: 15 | R103: 4 | S103: 2 | T103: 0 | U103: 60 | V103: 134 | W103: 16 | X103: 5 | Y103: 40 | Z103: 10 | AA103: 13 | AB103: 19 | AC103: 16 | AD103: 18 | AE103: 17 | AF103: 0 | AG103: 10 | AH103: 0 | AI103: 3 | AJ103: 0 | AK103: 38
A104: E07000207 | B104: Elmbridge | E104: 229 | F104: 0 | H104: 128 | I104: 59 | J104: 32 | K104: 37 | M104: 270 | N104: 2 | O104: 7 | P104: 1 | Q104: 13 | R104: 2 | S104: 0 | T104: 0 | U104: 40 | V104: 61 | W104: 12 | X104: 1 | Y104: 27 | Z104: 9 | AA104: 12 | AB104: 19 | AC104: 14 | AD104: 12 | AE104: 6 | AF104: 7 | AG104: 5 | AH104: 1 | AI104: 10 | AJ104: 1 | AK104: 8
A105: E09000010 | B105: Enfield | E105: 1365 | F105: 0 | H105: 903 | I105: 675 | J105: 174 | K105: 54 | M105: 1200 | N105: 6 | O105: 35 | P105: 11 | Q105: 7 | R105: 2 | S105: 1 | T105: 1 | U105: 309 | V105: 239 | W105: 52 | X105: 10 | Y105: 114 | Z105: 12 | AA105: 17 | AB105: 14 | AC105: 67 | AD105: 32 | AE105: 79 | AF105: 11 | AG105: 19 | AH105: 0 | AI105: 38 | AJ105: 3 | AK105: 121
A106: E07000072 | B106: Epping Forest | E106: .. | F106: .. | H106: .. | I106: .. | J106: .. | K106: .. | M106: .. | N106: .. | O106: .. | P106: .. | Q106: .. | R106: .. | S106: .. | T106: .. | U106: .. | V106: .. | W106: .. | X106: .. | Y106: .. | Z106: .. | AA106: .. | AB106: .. | AC106: .. | AD106: .. | AE106: .. | AF106: .. | AG106: .. | AH106: .. | AI106: .. | AJ106: .. | AK106: ..
A107: E07000208 | B107: Epsom & Ewell | E107: 74 | F107: 0 | H107: 136 | I107: 65 | J107: 49 | K107: 22 | M107: 236 | N107: 1 | O107: 8 | P107: 1 | Q107: 6 | R107: 2 | S107: 1 | T107: 0 | U107: 61 | V107: 66 | W107: 9 | X107: 2 | Y107: 16 | Z107: 8 | AA107: 6 | AB107: 12 | AC107: 8 | AD107: 14 | AE107: 8 | AF107: 1 | AG107: 5 | AH107: 0 | AI107: 1 | AJ107: 0 | AK107: 0
A108: E07000036 | B108: Erewash | E108: 300 | F108: 2 | H108: 282 | I108: 112 | J108: 74 | K108: 96 | M108: 681 | N108: 1 | O108: 13 | P108: 9 | Q108: 8 | R108: 5 | S108: 2 | T108: 4 | U108: 87 | V108: 159 | W108: 30 | X108: 17 | Y108: 43 | Z108: 18 | AA108: 38 | AB108: 27 | AC108: 51 | AD108: 35 | AE108: 31 | AF108: 40 | AG108: 8 | AH108: 5 | AI108: 16 | AJ108: 3 | AK108: 31
A109: E07000041 | B109: Exeter | E109: 99 | F109: 0 | H109: 872 | I109: 86 | J109: 129 | K109: 657 | M109: 4007 | N109: 43 | O109: 99 | P109: 28 | Q109: 66 | R109: 35 | S109: 45 | T109: 14 | U109: 381 | V109: 603 | W109: 230 | X109: 123 | Y109: 259 | Z109: 159 | AA109: 253 | AB109: 149 | AC109: 284 | AD109: 386 | AE109: 292 | AF109: 52 | AG109: 27 | AH109: 16 | AI109: 236 | AJ109: 5 | AK109: 222
A110: E07000087 | B110: Fareham | E110: 149 | F110: 0 | H110: 201 | I110: 63 | J110: 59 | K110: 79 | M110: 528 | N110: 5 | O110: 12 | P110: 6 | Q110: 7 | R110: 3 | S110: 6 | T110: 0 | U110: 80 | V110: 102 | W110: 19 | X110: 24 | Y110: 55 | Z110: 20 | AA110: 22 | AB110: 24 | AC110: 24 | AD110: 30 | AE110: 21 | AF110: 1 | AG110: 15 | AH110: 5 | AI110: 18 | AJ110: 0 | AK110: 29
A111: E07000010 | B111: Fenland | E111: 34 | F111: 0 | H111: 436 | I111: 63 | J111: 76 | K111: 297 | M111: 1649 | N111: 14 | O111: 30 | P111: 11 | Q111: 14 | R111: 6 | S111: 12 | T111: 1 | U111: 205 | V111: 269 | W111: 119 | X111: 49 | Y111: 147 | Z111: 46 | AA111: 46 | AB111: 34 | AC111: 91 | AD111: 106 | AE111: 98 | AF111: 4 | AG111: 39 | AH111: 9 | AI111: 182 | AJ111: 0 | AK111: 117
A112: E07000112 | B112: Folkestone & Hythe | E112: 285 | F112: 0 | H112: 287 | I112: 125 | J112: 51 | K112: 111 | M112: 713 | N112: 9 | O112: 12 | P112: 2 | Q112: 9 | R112: 3 | S112: 5 | T112: 0 | U112: 117 | V112: 147 | W112: 76 | X112: 13 | Y112: 49 | Z112: 11 | AA112: 32 | AB112: 16 | AC112: 50 | AD112: 34 | AE112: 32 | AF112: 4 | AG112: 8 | AH112: 7 | AI112: 33 | AJ112: 2 | AK112: 42
A113: E07000080 | B113: Forest of Dean | E113: 122 | F113: 0 | H113: 209 | I113: 59 | J113: 55 | K113: 95 | M113: 620 | N113: 0 | O113: 15 | P113: 3 | Q113: 2 | R113: 5 | S113: 3 | T113: 0 | U113: 101 | V113: 125 | W113: 42 | X113: 18 | Y113: 56 | Z113: 21 | AA113: 27 | AB113: 23 | AC113: 30 | AD113: 33 | AE113: 30 | AF113: 0 | AG113: 15 | AH113: 4 | AI113: 24 | AJ113: 0 | AK113: 43
A114: E07000119 | B114: Fylde | E114: 43 | F114: 0 | H114: 255 | I114: 72 | J114: 53 | K114: 130 | M114: 750 | N114: 3 | O114: 28 | P114: 2 | Q114: 4 | R114: 6 | S114: 4 | T114: 0 | U114: 127 | V114: 173 | W114: 53 | X114: 14 | Y114: 57 | Z114: 12 | AA114: 38 | AB114: 27 | AC114: 34 | AD114: 42 | AE114: 28 | AF114: 13 | AG114: 25 | AH114: 8 | AI114: 16 | AJ114: 0 | AK114: 36
A115: E08000037 | B115: Gateshead | E115: 519 | F115: 1 | H115: 957 | I115: 331 | J115: 258 | K115: 368 | M115: 2383 | N115: 7 | O115: 68 | P115: 20 | Q115: 10 | R115: 7 | S115: 24 | T115: 19 | U115: 298 | V115: 541 | W115: 98 | X115: 48 | Y115: 339 | Z115: 35 | AA115: 148 | AB115: 127 | AC115: 193 | AD115: 116 | AE115: 59 | AF115: 114 | AG115: 26 | AH115: 8 | AI115: 11 | AJ115: 2 | AK115: 65
A116: E07000173 | B116: Gedling | E116: 147 | F116: 0 | H116: 212 | I116: 169 | J116: 35 | K116: 8 | M116: 265 | N116: 0 | O116: 6 | P116: 2 | Q116: 1 | R116: 4 | S116: 0 | T116: 0 | U116: 65 | V116: 90 | W116: 13 | X116: 1 | Y116: 35 | Z116: 2 | AA116: 8 | AB116: 10 | AC116: 9 | AD116: 0 | AE116: 3 | AF116: 9 | AG116: 2 | AH116: 1 | AI116: 2 | AJ116: 0 | AK116: 2
A117: E07000081 | B117: Gloucester | E117: 234 | F117: 0 | H117: 1066 | I117: 262 | J117: 198 | K117: 606 | M117: 3772 | N117: 9 | O117: 83 | P117: 14 | Q117: 40 | R117: 17 | S117: 34 | T117: 13 | U117: 392 | V117: 616 | W117: 188 | X117: 124 | Y117: 375 | Z117: 194 | AA117: 136 | AB117: 90 | AC117: 226 | AD117: 320 | AE117: 235 | AF117: 111 | AG117: 24 | AH117: 19 | AI117: 225 | AJ117: 30 | AK117: 257
A118: E07000088 | B118: Gosport | E118: 208 | F118: 0 | H118: 300 | I118: 112 | J118: 74 | K118: 114 | M118: 726 | N118: 0 | O118: 19 | P118: 5 | Q118: 7 | R118: 5 | S118: 9 | T118: 3 | U118: 96 | V118: 144 | W118: 31 | X118: 25 | Y118: 96 | Z118: 9 | AA118: 51 | AB118: 38 | AC118: 62 | AD118: 49 | AE118: 31 | AF118: 5 | AG118: 10 | AH118: 9 | AI118: 1 | AJ118: 0 | AK118: 21
... A134: E09000016 | B134: Havering | E134: 1424 | F134: 0 | H134: 615 | I134: 369 | J134: 163 | K134: 83 | M134: 967 | N134: 3 | O134: 45 | P134: 3 | Q134: 4 | R134: 0 | S134: 3 | T134: 0 | U134: 214 | V134: 233 | W134: 40 | X134: 5 | Y134: 186 | Z134: 7 | AA134: 29 | AB134: 27 | AC134: 56 | AD134: 27 | AE134: 19 | AF134: 13 | AG134: 35 | AH134: 2 | AI134: 4 | AJ134: 2 | AK134: 10
A135: E06000019 | B135: Herefordshire | E135: .. | F135: .. | H135: .. | I135: .. | J135: .. | K135: .. | M135: .. | N135: .. | O135: .. | P135: .. | Q135: .. | R135: .. | S135: .. | T135: .. | U135: .. | V135: .. | W135: .. | X135: .. | Y135: .. | Z135: .. | AA135: .. | AB135: .. | AC135: .. | AD135: .. | AE135: .. | AF135: .. | AG135: .. | AH135: .. | AI135: .. | AJ135: .. | AK135: ..
A136: E07000098 | B136: Hertsmere | E136: 327 | F136: 0 | H136: 197 | I136: 90 | J136: 62 | K136: 45 | M136: 404 | N136: 3 | O136: 17 | P136: 0 | Q136: 1 | R136: 2 | S136: 2 | T136: 0 | U136: 70 | V136: 111 | W136: 32 | X136: 5 | Y136: 24 | Z136: 8 | AA136: 11 | AB136: 10 | AC136: 15 | AD136: 23 | AE136: 15 | AF136: 3 | AG136: 11 | AH136: 0 | AI136: 17 | AJ136: 1 | AK136: 23
A137: E07000037 | B137: High Peak | E137: 148 | F137: 0 | H137: 179 | I137: 62 | J137: 57 | K137: 60 | M137: 481 | N137: 3 | O137: 7 | P137: 2 | Q137: 5 | R137: 1 | S137: 1 | T137: 0 | U137: 87 | V137: 96 | W137: 37 | X137: 9 | Y137: 33 | Z137: 18 | AA137: 25 | AB137: 19 | AC137: 23 | AD137: 26 | AE137: 22 | AF137: 0 | AG137: 13 | AH137: 2 | AI137: 19 | AJ137: 0 | AK137: 33
A138: E09000017 | B138: Hillingdon | E138: 706 | F138: 2 | H138: 1390 | I138: 477 | J138: 425 | K138: 488 | M138: 3193 | N138: 27 | O138: 93 | P138: 15 | Q138: 18 | R138: 22 | S138: 14 | T138: 0 | U138: 628 | V138: 474 | W138: 153 | X138: 65 | Y138: 188 | Z138: 66 | AA138: 44 | AB138: 50 | AC138: 72 | AD138: 70 | AE138: 122 | AF138: 398 | AG138: 55 | AH138: 4 | AI138: 503 | AJ138: 20 | AK138: 92
A139: E07000132 | B139: Hinckley & Bosworth | E139: 270 | F139: 0 | H139: 342 | I139: 230 | J139: 77 | K139: 35 | M139: 503 | N139: 1 | O139: 11 | P139: 1 | Q139: 6 | R139: 3 | S139: 1 | T139: 0 | U139: 92 | V139: 145 | W139: 13 | X139: 4 | Y139: 148 | Z139: 4 | AA139: 22 | AB139: 15 | AC139: 18 | AD139: 7 | AE139: 1 | AF139: 0 | AG139: 4 | AH139: 2 | AI139: 1 | AJ139: 1 | AK139: 3
A140: E07000227 | B140: Horsham | E140: 210 | F140: 0 | H140: 215 | I140: 128 | J140: 35 | K140: 52 | M140: 411 | N140: 2 | O140: 33 | P140: 7 | Q140: 6 | R140: 3 | S140: 1 | T140: 0 | U140: 48 | V140: 81 | W140: 18 | X140: 11 | Y140: 24 | Z140: 8 | AA140: 24 | AB140: 22 | AC140: 25 | AD140: 23 | AE140: 23 | AF140: 8 | AG140: 22 | AH140: 2 | AI140: 2 | AJ140: 0 | AK140: 18
A141: E09000018 | B141: Hounslow | E141: 1281 | F141: 0 | H141: 1033 | I141: 686 | J141: 240 | K141: 107 | M141: 1592 | N141: 5 | O141: 42 | P141: 27 | Q141: 4 | R141: 7 | S141: 6 | T141: 0 | U141: 418 | V141: 335 | W141: 54 | X141: 17 | Y141: 93 | Z141: 9 | AA141: 45 | AB141: 42 | AC141: 52 | AD141: 66 | AE141: 90 | AF141: 183 | AG141: 56 | AH141: 1 | AI141: 9 | AJ141: 6 | AK141: 25
A142: E07000011 | B142: Huntingdonshire | E142: 271 | F142: 0 | H142: 594 | I142: 277 | J142: 180 | K142: 137 | M142: 1162 | N142: 6 | O142: 37 | P142: 1 | Q142: 14 | R142: 7 | S142: 4 | T142: 1 | U142: 235 | V142: 325 | W142: 79 | X142: 12 | Y142: 158 | Z142: 20 | AA142: 41 | AB142: 34 | AC142: 60 | AD142: 33 | AE142: 25 | AF142: 3 | AG142: 22 | AH142: 9 | AI142: 5 | AJ142: 1 | AK142: 30
A143: E07000120 | B143: Hyndburn | E143: 151 | F143: 0 | H143: 256 | I143: 82 | J143: 66 | K143: 108 | M143: 666 | N143: 4 | O143: 23 | P143: 7 | Q143: 5 | R143: 9 | S143: 6 | T143: 0 | U143: 93 | V143: 128 | W143: 46 | X143: 14 | Y143: 21 | Z143: 11 | AA143: 27 | AB143: 31 | AC143: 38 | AD143: 37 | AE143: 26 | AF143: 45 | AG143: 8 | AH143: 5 | AI143: 41 | AJ143: 0 | AK143: 41
A144: E07000202 | B144: Ipswich | E144: 827 | F144: 26 | H144: 696 | I144: 348 | J144: 185 | K144: 163 | M144: 1362 | N144: 9 | O144: 84 | P144: 17 | Q144: 100 | R144: 0 | S144: 0 | T144: 0 | U144: 173 | V144: 265 | W144: 37 | X144: 25 | Y144: 93 | Z144: 18 | AA144: 60 | AB144: 61 | AC144: 144 | AD144: 73 | AE144: 49 | AF144: 66 | AG144: 17 | AH144: 7 | AI144: 6 | AJ144: 1 | AK144: 57
A145: E06000046 | B145: Isle of Wight | E145: 213 | F145: 0 | H145: 555 | I145: 338 | J145: 173 | K145: 44 | M145: 831 | N145: 0 | O145: 29 | P145: 8 | Q145: 18 | R145: 1 | S145: 1 | T145: 0 | U145: 222 | V145: 292 | W145: 30 | X145: 3 | Y145: 44 | Z145: 5 | AA145: 40 | AB145: 57 | AC145: 52 | AD145: 6 | AE145: 4 | AF145: 1 | AG145: 11 | AH145: 7 | AI145: 0 | AJ145: 0 | AK145: 0
A146: E06000053 | B146: Isles of Scilly | E146: 4 | F146: 0 | H146: 1 | I146: - | J146: - | K146: - | M146: - | N146: - | O146: - | P146: - | Q146: - | R146: - | S146: - | T146: - | U146: - | V146: - | W146: - | X146: - | Y146: - | Z146: - | AA146: - | AB146: - | AC146: - | AD146: - | AE146: - | AF146: - | AG146: - | AH146: - | AI146: - | AJ146: - | AK146: -
A147: E09000019 | B147: Islington | E147: 934 | F147: 0 | H147: 2025 | I147: 1255 | J147: 466 | K147: 304 | M147: 3362 | N147: 69 | O147: 234 | P147: 22 | Q147: 49 | R147: 3 | S147: 5 | T147: 2 | U147: 338 | V147: 479 | W147: 40 | X147: 42 | Y147: 251 | Z147: 68 | AA147: 133 | AB147: 71 | AC147: 109 | AD147: 38 | AE147: 116 | AF147: 198 | AG147: 37 | AH147: 0 | AI147: 1044 | AJ147: 4 | AK147: 10
A148: E09000020 | B148: Kensington & Chelsea | E148: 841 | F148: 0 | H148: 495 | I148: 292 | J148: 107 | K148: 96 | M148: 867 | N148: 0 | O148: 16 | P148: 2 | Q148: 0 | R148: 2 | S148: 2 | T148: 3 | U148: 130 | V148: 153 | W148: 20 | X148: 31 | Y148: 178 | Z148: 19 | AA148: 37 | AB148: 29 | AC148: 28 | AD148: 54 | AE148: 49 | AF148: 16 | AG148: 33 | AH148: 1 | AI148: 36 | AJ148: 2 | AK148: 26
A149: E07000146 | B149: King's Lynn & West Norfolk | E149: 117 | F149: 0 | H149: 429 | I149: 239 | J149: 111 | K149: 79 | M149: 749 | N149: 4 | O149: 23 | P149: 12 | Q149: 7 | R149: 0 | S149: 0 | T149: 0 | U149: 159 | V149: 241 | W149: 24 | X149: 7 | Y149: 71 | Z149: 11 | AA149: 33 | AB149: 44 | AC149: 43 | AD149: 33 | AE149: 17 | AF149: 1 | AG149: 9 | AH149: 7 | AI149: 0 | AJ149: 0 | AK149: 3
A150: E06000010 | B150: Kingston upon Hull | E150: 1286 | F150: 0 | H150: 2176 | I150: 771 | J150: 543 | K150: 862 | M150: 5549 | N150: 38 | O150: 70 | P150: 13 | Q150: 46 | R150: 4 | S150: 0 | T150: 0 | U150: 913 | V150: 1419 | W150: 267 | X150: 54 | Y150: 734 | Z150: 36 | AA150: 411 | AB150: 269 | AC150: 428 | AD150: 437 | AE150: 285 | AF150: 31 | AG150: 23 | AH150: 32 | AI150: 38 | AJ150: 0 | AK150: 1
A151: E09000021 | B151: Kingston upon Thames | E151: .. | F151: .. | H151: .. | I151: .. | J151: .. | K151: .. | M151: .. | N151: .. | O151: .. | P151: .. | Q151: .. | R151: .. | S151: .. | T151: .. | U151: .. | V151: .. | W151: .. | X151: .. | Y151: .. | Z151: .. | AA151: .. | AB151: .. | AC151: .. | AD151: .. | AE151: .. | AF151: .. | AG151: .. | AH151: .. | AI151: .. | AJ151: .. | AK151: ..
A152: E08000034 | B152: Kirklees | E152: 390 | F152: 0 | H152: 1512 | I152: 1003 | J152: 316 | K152: 193 | M152: 2363 | N152: 51 | O152: 276 | P152: 53 | Q152: 17 | R152: 0 | S152: 0 | T152: 24 | U152: 385 | V152: 516 | W152: 90 | X152: 18 | Y152: 153 | Z152: 34 | AA152: 118 | AB152: 82 | AC152: 144 | AD152: 92 | AE152: 50 | AF152: 182 | AG152: 25 | AH152: 8 | AI152: 40 | AJ152: 1 | AK152: 4
...

Sheet A4P
A1: Table A4P - Number of households owed a prevention duty by accommodation at time of application England, April 2024 to March 2025
G2: Private rented sector | L2: Social rented sector | Q2: Owner-occupier / shared ownership | R2: Living with family | S2: Living with friends | T2: Temporary accommodation | V2: No fixed abode³ | AB2: Rough sleeping | AC2: Refuge | AD2: National Asylum Seeker Support (NASS) accommodation | AF2: Homeless on departure from institution | AK2: Other / not known⁴
AK3: Number of households
E4: Total owed a prevention duty1,2 | G4: Private rented sector | L4: Social rented sector | Q4: Owner-occupier / shared ownership | R4: Living with family | S4: Living with friends | T4: Temporary accommodation | V4: No fixed abode | AB4: Rough sleeping | AC4: Refuge | AD4: National Asylum Seeker Support (NASS) accommodation | AF4: Homeless on departure from institution: | AK4: Other / not known3
G5: Total PRS | H5: Of which: | L5: Total SRS | M5: Of which: | V5: Total No fixed abode | W5: Of which: | AF5: Total homeless on departure from institution | AG5: Of which:
H6: Self-contained | I6: House in multiple occupation (HMO) | J6: Lodging (not with family or friends) | M6: Council tenant | N6: Registered provider tenant | O6: Supported housing / hostel | W6: Slept rough in the last year | X6: Previously slept rough | Y6: Never slept rough | Z6: Retired "No fixed abode" option | AG6: Custody | AH6: General hospital | AI6: Psychiatric hospital
A7: E92000001 | B7: ENGLAND | E7: 147870 | G7: 66790 | H7: 59100 | I7: 5560 | J7: 2120 | L7: 17360 | M7: 4700 | N7: 5900 | O7: 6760 | Q7: 2410 | R7: 34980 | S7: 10820 | T7: 960 | V7: 230 | W7: 80 | X7: 20 | Y7: 130 | Z7: 0 | AB7: 110 | AC7: 700 | AD7: 4410 | AF7: 4770 | AG7: 3760 | AH7: 490 | AI7: 510 | AK7: 4310
A8: E12000007 | B8: London | E8: 28240 | G8: 15240 | H8: 12860 | I8: 1890 | J8: 490 | L8: 3180 | M8: 1320 | N8: 910 | O8: 940 | Q8: 160 | R8: 6140 | S8: 1620 | T8: 210 | V8: 160 | W8: 50 | X8: 10 | Y8: 90 | Z8: 0 | AB8: 70 | AC8: 160 | AD8: 400 | AF8: 480 | AG8: 360 | AH8: 60 | AI8: 70 | AK8: 410
A9: - | B9: Rest of England | E9: 119630 | G9: 51550 | H9: 46240 | I9: 3680 | J9: 1630 | L9: 14190 | M9: 3380 | N9: 4990 | O9: 5820 | Q9: 2250 | R9: 28830 | S9: 9210 | T9: 750 | V9: 80 | W9: 30 | X9: 10 | Y9: 40 | Z9: 0 | AB9: 30 | AC9: 540 | AD9: 4010 | AF9: 4280 | AG9: 3410 | AH9: 430 | AI9: 450 | AK9: 3900
A11: E12000001 | B11: North East | E11: 8930 | G11: 3380 | H11: 3270 | I11: 60 | J11: 40 | L11: 1140 | M11: 310 | N11: 370 | O11: 460 | Q11: 250 | R11: 2180 | S11: 780 | T11: 30 | V11: 0 | W11: 0 | X11: 0 | Y11: 0 | Z11: 0 | AB11: 0 | AC11: 70 | AD11: 470 | AF11: 480 | AG11: 380 | AH11: 40 | AI11: 60 | AK11: 160
A12: E12000002 | B12: North West | E12: 20570 | G12: 9220 | H12: 8520 | I12: 490 | J12: 210 | L12: 2130 | M12: 230 | N12: 1260 | O12: 640 | Q12: 460 | R12: 4620 | S12: 1470 | T12: 160 | V12: 10 | W12: 0 | X12: 0 | Y12: 10 | Z12: 0 | AB12: 0 | AC12: 80 | AD12: 1050 | AF12: 830 | AG12: 600 | AH12: 120 | AI12: 110 | AK12: 540
A13: E12000003 | B13: Yorkshire and The Humber | E13: 15100 | G13: 4980 | H13: 4540 | I13: 330 | J13: 100 | L13: 1720 | M13: 550 | N13: 290 | O13: 870 | Q13: 230 | R13: 4360 | S13: 1760 | T13: 110 | V13: 0 | W13: 0 | X13: 0 | Y13: 0 | Z13: 0 | AB13: 0 | AC13: 90 | AD13: 720 | AF13: 860 | AG13: 720 | AH13: 70 | AI13: 60 | AK13: 280
A14: E12000004 | B14: East Midlands | E14: 10800 | G14: 5140 | H14: 4710 | I14: 320 | J14: 100 | L14: 1210 | M14: 250 | N14: 350 | O14: 610 | Q14: 180 | R14: 2460 | S14: 760 | T14: 40 | V14: 0 | W14: 0 | X14: 0 | Y14: 0 | Z14: 0 | AB14: 0 | AC14: 30 | AD14: 440 | AF14: 310 | AG14: 270 | AH14: 20 | AI14: 20 | AK14: 220
A15: E12000005 | B15: West Midlands | E15: 11810 | G15: 4910 | H15: 4130 | I15: 630 | J15: 150 | L15: 1960 | M15: 630 | N15: 430 | O15: 900 | Q15: 230 | R15: 2710 | S15: 770 | T15: 50 | V15: 60 | W15: 20 | X15: 10 | Y15: 30 | Z15: 0 | AB15: 30 | AC15: 70 | AD15: 350 | AF15: 260 | AG15: 190 | AH15: 40 | AI15: 30 | AK15: 430
A16: E12000006 | B16: East of England | E16: 15450 | G16: 6860 | H16: 6110 | I16: 480 | J16: 270 | L16: 2100 | M16: 570 | N16: 780 | O16: 750 | Q16: 270 | R16: 3800 | S16: 1000 | T16: 100 | V16: 0 | W16: 0 | X16: 0 | Y16: 0 | Z16: 0 | AB16: 0 | AC16: 100 | AD16: 240 | AF16: 390 | AG16: 320 | AH16: 40 | AI16: 30 | AK16: 590
A17: E12000007 | B17: London | E17: 28240 | G17: 15240 | H17: 12860 | I17: 1890 | J17: 490 | L17: 3180 | M17: 1320 | N17: 910 | O17: 940 | Q17: 160 | R17: 6140 | S17: 1620 | T17: 210 | V17: 160 | W17: 50 | X17: 10 | Y17: 90 | Z17: 0 | AB17: 70 | AC17: 160 | AD17: 400 | AF17: 480 | AG17: 360 | AH17: 60 | AI17: 70 | AK17: 410
A18: E12000008 | B18: South East | E18: 23080 | G18: 10760 | H18: 9370 | I18: 950 | J18: 440 | L18: 2260 | M18: 410 | N18: 940 | O18: 910 | Q18: 340 | R18: 5630 | S18: 1700 | T18: 180 | V18: 0 | W18: 0 | X18: 0 | Y18: 0 | Z18: 0 | AB18: 0 | AC18: 70 | AD18: 500 | AF18: 690 | AG18: 550 | AH18: 70 | AI18: 70 | AK18: 940
A19: E12000009 | B19: South West | E19: 13880 | G19: 6310 | H19: 5590 | I19: 410 | J19: 310 | L19: 1670 | M19: 430 | N19: 570 | O19: 680 | Q19: 290 | R19: 3060 | S19: 980 | T19: 70 | V19: 0 | W19: 0 | X19: 0 | Y19: 0 | Z19: 0 | AB19: 0 | AC19: 30 | AD19: 250 | AF19: 470 | AG19: 380 | AH19: 40 | AI19: 60 | AK19: 740
... A47: E07000143 | B47: Breckland | E47: 199 | G47: 103 | H47: 100 | I47: 2 | J47: 1 | L47: 25 | M47: 3 | N47: 12 | O47: 10 | Q47: 4 | R47: 47 | S47: 4 | T47: 0 | V47: 0 | W47: 0 | X47: 0 | Y47: 0 | Z47: 0 | AB47: 0 | AC47: 0 | AD47: 0 | AF47: 3 | AG47: 3 | AH47: 0 | AI47: 0 | AK47: 13
A48: E09000005 | B48: Brent | E48: .. | G48: .. | H48: .. | I48: .. | J48: .. | L48: .. | M48: .. | N48: .. | O48: .. | Q48: .. | R48: .. | S48: .. | T48: .. | V48: .. | W48: .. | X48: .. | Y48: .. | Z48: .. | AB48: .. | AC48: .. | AD48: .. | AF48: .. | AG48: .. | AH48: .. | AI48: .. | AK48: ..
A49: E07000068 | B49: Brentwood | E49: 111 | G49: 64 | H49: 59 | I49: 2 | J49: 3 | L49: 4 | M49: 2 | N49: 0 | O49: 2 | Q49: 2 | R49: 30 | S49: 3 | T49: 2 | V49: 0 | W49: 0 | X49: 0 | Y49: 0 | Z49: 0 | AB49: 0 | AC49: 3 | AD49: 0 | AF49: 1 | AG49: 1 | AH49: 0 | AI49: 0 | AK49: 2
A50: E06000043 | B50: Brighton & Hove | E50: 403 | G50: 230 | H50: 210 | I50: 13 | J50: 7 | L50: 39 | M50: 2 | N50: 0 | O50: 37 | Q50: 1 | R50: 57 | S50: 26 | T50: 3 | V50: 1 | W50: 0 | X50: 0 | Y50: 1 | Z50: 0 | AB50: 0 | AC50: 2 | AD50: 24 | AF50: 1 | AG50: 1 | AH50: 0 | AI50: 0 | AK50: 19
A51: E06000023 | B51: Bristol | E51: 897 | G51: 308 | H51: 259 | I51: 27 | J51: 22 | L51: 201 | M51: 122 | N51: 19 | O51: 60 | Q51: 9 | R51: 153 | S51: 71 | T51: 9 | V51: 0 | W51: 0 | X51: 0 | Y51: 0 | Z51: 0 | AB51: 0 | AC51: 1 | AD51: 31 | AF51: 103 | AG51: 101 | AH51: 1 | AI51: 1 | AK51: 11
A52: E07000144 | B52: Broadland | E52: 156 | G52: 77 | H52: 71 | I52: 0 | J52: 6 | L52: 7 | M52: 0 | N52: 4 | O52: 3 | Q52: 3 | R52: 39 | S52: 17 | T52: 0 | V52: 0 | W52: 0 | X52: 0 | Y52: 0 | Z52: 0 | AB52: 0 | AC52: 0 | AD52: 1 | AF52: 0 | AG52: 0 | AH52: 0 | AI52: 0 | AK52: 12
A53: E09000006 | B53: Bromley | E53: 577 | G53: 335 | H53: 300 | I53: 24 | J53: 11 | L53: 38 | M53: 4 | N53: 25 | O53: 9 | Q53: 6 | R53: 141 | S53: 41 | T53: 3 | V53: 0 | W53: 0 | X53: 0 | Y53: 0 | Z53: 0 | AB53: 0 | AC53: 3 | AD53: 0 | AF53: 5 | AG53: 5 | AH53: 0 | AI53: 0 | AK53: 5
A54: E07000234 | B54: Bromsgrove | E54: 183 | G54: 57 | H54: 49 | I54: 7 | J54: 1 | L54: 20 | M54: 3 | N54: 15 | O54: 2 | Q54: 5 | R54: 72 | S54: 19 | T54: 0 | V54: 0 | W54: 0 | X54: 0 | Y54: 0 | Z54: 0 | AB54: 0 | AC54: 0 | AD54: 0 | AF54: 3 | AG54: 3 | AH54: 0 | AI54: 0 | AK54: 7
A55: E07000095 | B55: Broxbourne | E55: 240 | G55: 124 | H55: 110 | I55: 10 | J55: 4 | L55: 19 | M55: 4 | N55: 10 | O55: 5 | Q55: 3 | R55: 59 | S55: 17 | T55: 3 | V55: 0 | W55: 0 | X55: 0 | Y55: 0 | Z55: 0 | AB55: 0 | AC55: 4 | AD55: 6 | AF55: 3 | AG55: 1 | AH55: 1 | AI55: 1 | AK55: 2
A56: E07000172 | B56: Broxtowe | E56: 133 | G56: 70 | H56: 69 | I56: 0 | J56: 1 | L56: 4 | M56: 1 | N56: 0 | O56: 3 | Q56: 0 | R56: 35 | S56: 16 | T56: 0 | V56: 0 | W56: 0 | X56: 0 | Y56: 0 | Z56: 0 | AB56: 0 | AC56: 0 | AD56: 5 | AF56: 1 | AG56: 1 | AH56: 0 | AI56: 0 | AK56: 2
A57: E06000060 | B57: Buckinghamshire | E57: 1777 | G57: 706 | H57: 625 | I57: 42 | J57: 39 | L57: 255 | M57: 18 | N57: 176 | O57: 61 | Q57: 40 | R57: 466 | S57: 166 | T57: 17 | V57: 0 | W57: 0 | X57: 0 | Y57: 0 | Z57: 0 | AB57: 0 | AC57: 1 | AD57: 4 | AF57: 54 | AG57: 44 | AH57: 5 | AI57: 5 | AK57: 68
A58: E07000117 | B58: Burnley | E58: 292 | G58: 162 | H58: 154 | I58: 6 | J58: 2 | L58: 17 | M58: 0 | N58: 5 | O58: 12 | Q58: 11 | R58: 61 | S58: 11 | T58: 1 | V58: 0 | W58: 0 | X58: 0 | Y58: 0 | Z58: 0 | AB58: 0 | AC58: 0 | AD58: 22 | AF58: 1 | AG58: 0 | AH58: 0 | AI58: 1 | AK58: 6
A59: E08000002 | B59: Bury | E59: .. | G59: .. | H59: .. | I59: .. | J59: .. | L59: .. | M59: .. | N59: .. | O59: .. | Q59: .. | R59: .. | S59: .. | T59: .. | V59: .. | W59: .. | X59: .. | Y59: .. | Z59: .. | AB59: .. | AC59: .. | AD59: .. | AF59: .. | AG59: .. | AH59: .. | AI59: .. | AK59: ..
A60: E08000033 | B60: Calderdale | E60: 887 | G60: 260 | H60: 235 | I60: 17 | J60: 8 | L60: 100 | M60: 14 | N60: 45 | O60: 41 | Q60: 22 | R60: 208 | S60: 112 | T60: 2 | V60: 0 | W60: 0 | X60: 0 | Y60: 0 | Z60: 0 | AB60: 0 | AC60: 3 | AD60: 63 | AF60: 68 | AG60: 62 | AH60: 3 | AI60: 3 | AK60: 49
A61: E07000008 | B61: Cambridge | E61: 285 | G61: 98 | H61: 62 | I61: 17 | J61: 19 | L61: 40 | M61: 13 | N61: 10 | O61: 17 | Q61: 3 | R61: 76 | S61: 19 | T61: 3 | V61: 0 | W61: 0 | X61: 0 | Y61: 0 | Z61: 0 | AB61: 0 | AC61: 1 | AD61: 0 | AF61: 13 | AG61: 10 | AH61: 0 | AI61: 3 | AK61: 32
A62: E09000007 | B62: Camden | E62: .. | G62: .. | H62: .. | I62: .. | J62: .. | L62: .. | M62: .. | N62: .. | O62: .. | Q62: .. | R62: .. | S62: .. | T62: .. | V62: .. | W62: .. | X62: .. | Y62: .. | Z62: .. | AB62: .. | AC62: .. | AD62: .. | AF62: .. | AG62: .. | AH62: .. | AI62: .. | AK62: ..
